Workbook

Sheet Categorias
B2: CATEGORIAS
B4: Establece nombres de categorías y subcategorías para tus ingresos y gastos. Elimina las que no necesitas, cambia, o añade nuevas. Los cambios que realices aquí, se cambian automaticamente en todos los meses.
B7: Lista de categorías
B9: Ingresos
B11: INGRESOS TOTALES
B12: Nomina
B13: Aguinaldo
B14: Fondo de ahorro
B15: Vales despensa
B16: Vales comedor
B17: -
B18: -
... B164: -

Sheet TODO EL AÑO
B2: Presupuesto | C2: AÑO 2026
C4: En este lugar no llenas nada. Es una vista del presupuesto de todo el año y todo se hará automicamente después de llenar los datos en los meses, de Enero hasta Diciembre - Todos los otros datos se convertirán automáticamente
C5: Fuente: | D5: =HYPERLINK("http://www.aprendizfinanciero.com/","http://www.aprendizfinanciero.com") -> http://www.aprendizfinanciero.com
B6: Ingresos
B8: Categoría | C8: Ingresos previstos | D8: Ingresos reales | E8: Diferencia | F8: Notas
B9: SUMA | C9: =C11 -> 467281.6 | D9: =D11 -> 324561.2 | E9: =E11 -> -142720.4
B11: =Categorias!B11 -> INGRESOS TOTALES | C11: =SUM(C12:C20) -> 467281.6 | D11: =SUM(D12:D20) -> 324561.2 | E11: =SUM(E12:E20) -> -142720.4
B12: =Categorias!B12 -> Nomina | C12: =Enero!C12+Febrero!C12+Marzo!C12+Abril!C12+Mayo!C12+Junio!C12+Julio!C12+Agosto!C12+Septiembre!C12+Octubre!C12+Noviembre!C12+Diciembre!C12 -> 442881.6 | D12: =Enero!D12+Febrero!D12+Marzo!D12+Abril!D12+Mayo!D12+Junio!D12+Julio!D12+Agosto!D12+Septiembre!D12+Octubre!D12+Noviembre!D12+Diciembre!D12 -> 308161.2 | E12: =D12-C12 -> -134720.4
B13: =Categorias!B13 -> Aguinaldo | C13: =Enero!C13+Febrero!C13+Marzo!C13+Abril!C13+Mayo!C13+Junio!C13+Julio!C13+Agosto!C13+Septiembre!C13+Octubre!C13+Noviembre!C13+Diciembre!C13 -> 15000 | D13: =Enero!D13+Febrero!D13+Marzo!D13+Abril!D13+Mayo!D13+Junio!D13+Julio!D13+Agosto!D13+Septiembre!D13+Octubre!D13+Noviembre!D13+Diciembre!D13 -> 10000 | E13: =D13-C13 -> -5000
B14: =Categorias!B14 -> Fondo de ahorro | C14: =Enero!C14+Febrero!C14+Marzo!C14+Abril!C14+Mayo!C14+Junio!C14+Julio!C14+Agosto!C14+Septiembre!C14+Octubre!C14+Noviembre!C14+Diciembre!C14 -> 0 | D14: =Enero!D14+Febrero!D14+Marzo!D14+Abril!D14+Mayo!D14+Junio!D14+Julio!D14+Agosto!D14+Septiembre!D14+Octubre!D14+Noviembre!D14+Diciembre!D14 -> 0 | E14: =D14-C14 -> 0
B15: =Categorias!B15 -> Vales despensa | C15: =Enero!C15+Febrero!C15+Marzo!C15+Abril!C15+Mayo!C15+Junio!C15+Julio!C15+Agosto!C15+Septiembre!C15+Octubre!C15+Noviembre!C15+Diciembre!C15 -> 9400 | D15: =Enero!D15+Febrero!D15+Marzo!D15+Abril!D15+Mayo!D15+Junio!D15+Julio!D15+Agosto!D15+Septiembre!D15+Octubre!D15+Noviembre!D15+Diciembre!D15 -> 6400 | E15: =D15-C15 -> -3000
B16: =Categorias!B16 -> Vales comedor | C16: =Enero!C16+Febrero!C16+Marzo!C16+Abril!C16+Mayo!C16+Junio!C16+Julio!C16+Agosto!C16+Septiembre!C16+Octubre!C16+Noviembre!C16+Diciembre!C16 -> 0 | D16: =Enero!D16+Febrero!D16+Marzo!D16+Abril!D16+Mayo!D16+Junio!D16+Julio!D16+Agosto!D16+Septiembre!D16+Octubre!D16+Noviembre!D16+Diciembre!D16 -> 0 | E16: =D16-C16 -> 0
B17: =Categorias!B17 -> - | C17: =Enero!C17+Febrero!C17+Marzo!C17+Abril!C17+Mayo!C17+Junio!C17+Julio!C17+Agosto!C17+Septiembre!C17+Octubre!C17+Noviembre!C17+Diciembre!C17 -> 0 | D17: =Enero!D17+Febrero!D17+Marzo!D17+Abril!D17+Mayo!D17+Junio!D17+Julio!D17+Agosto!D17+Septiembre!D17+Octubre!D17+Noviembre!D17+Diciembre!D17 -> 0 | E17: =D17-C17 -> 0
B18: =Categorias!B18 -> - | C18: =Enero!C18+Febrero!C18+Marzo!C18+Abril!C18+Mayo!C18+Junio!C18+Julio!C18+Agosto!C18+Septiembre!C18+Octubre!C18+Noviembre!C18+Diciembre!C18 -> 0 | D18: =Enero!D18+Febrero!D18+Marzo!D18+Abril!D18+Mayo!D18+Junio!D18+Julio!D18+Agosto!D18+Septiembre!D18+Octubre!D18+Noviembre!D18+Diciembre!D18 -> 0 | E18: =D18-C18 -> 0
B19: =Categorias!B19 -> - | C19: =Enero!C19+Febrero!C19+Marzo!C19+Abril!C19+Mayo!C19+Junio!C19+Julio!C19+Agosto!C19+Septiembre!C19+Octubre!C19+Noviembre!C19+Diciembre!C19 -> 0 | D19: =Enero!D19+Febrero!D19+Marzo!D19+Abril!D19+Mayo!D19+Junio!D19+Julio!D19+Agosto!D19+Septiembre!D19+Octubre!D19+Noviembre!D19+Diciembre!D19 -> 0 | E19: =D19-C19 -> 0
B20: =Categorias!B20 -> - | C20: =Enero!C20+Febrero!C20+Marzo!C20+Abril!C20+Mayo!C20+Junio!C20+Julio!C20+Agosto!C20+Septiembre!C20+Octubre!C20+Noviembre!C20+Diciembre!C20 -> 0 | D20: =Enero!D20+Febrero!D20+Marzo!D20+Abril!D20+Mayo!D20+Junio!D20+Julio!D20+Agosto!D20+Septiembre!D20+Octubre!D20+Noviembre!D20+Diciembre!D20 -> 0 | E20: =D20-C20 -> 0
B23: Gastos
B25: Categoría | C25: Gastos previstos | D25: Gastos reales | E25: Diferencia | F25: Notas
B26: SUMA | C26: =C28+C37+C45+C58+C68+C77+C88+C97+C107+C115+C126+C136+C146+C158 -> 322192.45 | D26: =D28+D37+D45+D58+D68+D77+D88+D97+D107+D115+D126+D136+D146+D158 -> 304907.15 | E26: =E28+E37+E45+E58+E68+E77+E88+E97+E107+E115+E126+E136+E146+E158 -> 17285.3
B28: =Categorias!B24 -> ALIMENTOS Y BEBIDAS | C28: =SUM(C29:C35) -> 29000 | D28: =SUM(D29:D35) -> 44168.02 | E28: =SUM(E29:E35) -> -15168.02
B29: =Categorias!B25 -> Restaurantes | C29: =Enero!C29+Febrero!C29+Marzo!C29+Abril!C29+Mayo!C29+Junio!C29+Julio!C29+Agosto!C29+Septiembre!C29+Octubre!C29+Noviembre!C29+Diciembre!C29 -> 20500 | D29: =Enero!D29+Febrero!D29+Marzo!D29+Abril!D29+Mayo!D29+Junio!D29+Julio!D29+Agosto!D29+Septiembre!D29+Octubre!D29+Noviembre!D29+Diciembre!D29 -> 34421.82 | E29: =C29-D29 -> -13921.82
B30: =Categorias!B26 -> Comida Carlos | C30: =Enero!C30+Febrero!C30+Marzo!C30+Abril!C30+Mayo!C30+Junio!C30+Julio!C30+Agosto!C30+Septiembre!C30+Octubre!C30+Noviembre!C30+Diciembre!C30 -> 6500 | D30: =Enero!D30+Febrero!D30+Marzo!D30+Abril!D30+Mayo!D30+Junio!D30+Julio!D30+Agosto!D30+Septiembre!D30+Octubre!D30+Noviembre!D30+Diciembre!D30 -> 6362.6 | E30: =C30-D30 -> 137.4
B31: =Categorias!B27 -> - | C31: =Enero!C31+Febrero!C31+Marzo!C31+Abril!C31+Mayo!C31+Junio!C31+Julio!C31+Agosto!C31+Septiembre!C31+Octubre!C31+Noviembre!C31+Diciembre!C31 -> 1000 | D31: =Enero!D31+Febrero!D31+Marzo!D31+Abril!D31+Mayo!D31+Junio!D31+Julio!D31+Agosto!D31+Septiembre!D31+Octubre!D31+Noviembre!D31+Diciembre!D31 -> 505.6 | E31: =C31-D31 -> 494.4
B32: =Categorias!B28 -> - | C32: =Enero!C32+Febrero!C32+Marzo!C32+Abril!C32+Mayo!C32+Junio!C32+Julio!C32+Agosto!C32+Septiembre!C32+Octubre!C32+Noviembre!C32+Diciembre!C32 -> 1000 | D32: =Enero!D32+Febrero!D32+Marzo!D32+Abril!D32+Mayo!D32+Junio!D32+Julio!D32+Agosto!D32+Septiembre!D32+Octubre!D32+Noviembre!D32+Diciembre!D32 -> 1941 | E32: =C32-D32 -> -941
B33: =Categorias!B29 -> - | C33: =Enero!C33+Febrero!C33+Marzo!C33+Abril!C33+Mayo!C33+Junio!C33+Julio!C33+Agosto!C33+Septiembre!C33+Octubre!C33+Noviembre!C33+Diciembre!C33 -> 0 | D33: =Enero!D33+Febrero!D33+Marzo!D33+Abril!D33+Mayo!D33+Junio!D33+Julio!D33+Agosto!D33+Septiembre!D33+Octubre!D33+Noviembre!D33+Diciembre!D33 -> 657 | E33: =C33-D33 -> -657
B34: =Categorias!B30 -> - | C34: =Enero!C34+Febrero!C34+Marzo!C34+Abril!C34+Mayo!C34+Junio!C34+Julio!C34+Agosto!C34+Septiembre!C34+Octubre!C34+Noviembre!C34+Diciembre!C34 -> 0 | D34: =Enero!D34+Febrero!D34+Marzo!D34+Abril!D34+Mayo!D34+Junio!D34+Julio!D34+Agosto!D34+Septiembre!D34+Octubre!D34+Noviembre!D34+Diciembre!D34 -> 280 | E34: =C34-D34 -> -280
B35: =Categorias!B31 -> - | C35: =Enero!C35+Febrero!C35+Marzo!C35+Abril!C35+Mayo!C35+Junio!C35+Julio!C35+Agosto!C35+Septiembre!C35+Octubre!C35+Noviembre!C35+Diciembre!C35 -> 0 | D35: =Enero!D35+Febrero!D35+Marzo!D35+Abril!D35+Mayo!D35+Junio!D35+Julio!D35+Agosto!D35+Septiembre!D35+Octubre!D35+Noviembre!D35+Diciembre!D35 -> 0 | E35: =C35-D35 -> 0
B37: =Categorias!B33 -> SALUD | C37: =Enero!C37+Febrero!C37+Marzo!C37+Abril!C37+Mayo!C37+Junio!C37+Julio!C37+Agosto!C37+Septiembre!C37+Octubre!C37+Noviembre!C37+Diciembre!C37 -> 13500 | D37: =Enero!D37+Febrero!D37+Marzo!D37+Abril!D37+Mayo!D37+Junio!D37+Julio!D37+Agosto!D37+Septiembre!D37+Octubre!D37+Noviembre!D37+Diciembre!D37 -> 15428.4 | E37: =SUM(E38:E43) -> -1928.4
B38: =Categorias!B34 -> Gastos en médicos | C38: =Enero!C38+Febrero!C38+Marzo!C38+Abril!C38+Mayo!C38+Junio!C38+Julio!C38+Agosto!C38+Septiembre!C38+Octubre!C38+Noviembre!C38+Diciembre!C38 -> 5000 | D38: =Enero!D38+Febrero!D38+Marzo!D38+Abril!D38+Mayo!D38+Junio!D38+Julio!D38+Agosto!D38+Septiembre!D38+Octubre!D38+Noviembre!D38+Diciembre!D38 -> 3080 | E38: =C38-D38 -> 1920
B39: =Categorias!B35 -> Medicamentos | C39: =Enero!C39+Febrero!C39+Marzo!C39+Abril!C39+Mayo!C39+Junio!C39+Julio!C39+Agosto!C39+Septiembre!C39+Octubre!C39+Noviembre!C39+Diciembre!C39 -> 2000 | D39: =Enero!D39+Febrero!D39+Marzo!D39+Abril!D39+Mayo!D39+Junio!D39+Julio!D39+Agosto!D39+Septiembre!D39+Octubre!D39+Noviembre!D39+Diciembre!D39 -> 11848.4 | E39: =C39-D39 -> -9848.4
B40: =Categorias!B36 -> Dentista Kary | C40: =Enero!C40+Febrero!C40+Marzo!C40+Abril!C40+Mayo!C40+Junio!C40+Julio!C40+Agosto!C40+Septiembre!C40+Octubre!C40+Noviembre!C40+Diciembre!C40 -> 4100 | D40: =Enero!D40+Febrero!D40+Marzo!D40+Abril!D40+Mayo!D40+Junio!D40+Julio!D40+Agosto!D40+Septiembre!D40+Octubre!D40+Noviembre!D40+Diciembre!D40 -> 500 | E40: =C40-D40 -> 3600
B41: =Categorias!B37 -> Dentista Thiago | C41: =Enero!C41+Febrero!C41+Marzo!C41+Abril!C41+Mayo!C41+Junio!C41+Julio!C41+Agosto!C41+Septiembre!C41+Octubre!C41+Noviembre!C41+Diciembre!C41 -> 2400 | D41: =Enero!D41+Febrero!D41+Marzo!D41+Abril!D41+Mayo!D41+Junio!D41+Julio!D41+Agosto!D41+Septiembre!D41+Octubre!D41+Noviembre!D41+Diciembre!D41 -> 0 | E41: =C41-D41 -> 2400
B42: =Categorias!B38 -> - | C42: =Enero!C42+Febrero!C42+Marzo!C42+Abril!C42+Mayo!C42+Junio!C42+Julio!C42+Agosto!C42+Septiembre!C42+Octubre!C42+Noviembre!C42+Diciembre!C42 -> 0 | D42: =Enero!D42+Febrero!D42+Marzo!D42+Abril!D42+Mayo!D42+Junio!D42+Julio!D42+Agosto!D42+Septiembre!D42+Octubre!D42+Noviembre!D42+Diciembre!D42 -> 0 | E42: =C42-D42 -> 0
B43: =Categorias!B39 -> - | C43: =Enero!C43+Febrero!C43+Marzo!C43+Abril!C43+Mayo!C43+Junio!C43+Julio!C43+Agosto!C43+Septiembre!C43+Octubre!C43+Noviembre!C43+Diciembre!C43 -> 0 | D43: =Enero!D43+Febrero!D43+Marzo!D43+Abril!D43+Mayo!D43+Junio!D43+Julio!D43+Agosto!D43+Septiembre!D43+Octubre!D43+Noviembre!D43+Diciembre!D43 -> 0 | E43: =C43-D43 -> 0
B45: =Categorias!B41 -> CASA | C45: =Enero!C45+Febrero!C45+Marzo!C45+Abril!C45+Mayo!C45+Junio!C45+Julio!C45+Agosto!C45+Septiembre!C45+Octubre!C45+Noviembre!C45+Diciembre!C45 -> 108340 | D45: =Enero!D45+Febrero!D45+Marzo!D45+Abril!D45+Mayo!D45+Junio!D45+Julio!D45+Agosto!D45+Septiembre!D45+Octubre!D45+Noviembre!D45+Diciembre!D45 -> 106460 | E45: =SUM(E46:E56) -> 1880
B46: =Categorias!B42 -> Reparación | C46: =Enero!C46+Febrero!C46+Marzo!C46+Abril!C46+Mayo!C46+Junio!C46+Julio!C46+Agosto!C46+Septiembre!C46+Octubre!C46+Noviembre!C46+Diciembre!C46 -> 500 | D46: =Enero!D46+Febrero!D46+Marzo!D46+Abril!D46+Mayo!D46+Junio!D46+Julio!D46+Agosto!D46+Septiembre!D46+Octubre!D46+Noviembre!D46+Diciembre!D46 -> 24002 | E46: =C46-D46 -> -23502
B47: =Categorias!B43 -> Electricidad | C47: =Enero!C47+Febrero!C47+Marzo!C47+Abril!C47+Mayo!C47+Junio!C47+Julio!C47+Agosto!C47+Septiembre!C47+Octubre!C47+Noviembre!C47+Diciembre!C47 -> 6700 | D47: =Enero!D47+Febrero!D47+Marzo!D47+Abril!D47+Mayo!D47+Junio!D47+Julio!D47+Agosto!D47+Septiembre!D47+Octubre!D47+Noviembre!D47+Diciembre!D47 -> 3553 | E47: =C47-D47 -> 3147
B48: =Categorias!B44 -> Gas | C48: =Enero!C48+Febrero!C48+Marzo!C48+Abril!C48+Mayo!C48+Junio!C48+Julio!C48+Agosto!C48+Septiembre!C48+Octubre!C48+Noviembre!C48+Diciembre!C48 -> 2640 | D48: =Enero!D48+Febrero!D48+Marzo!D48+Abril!D48+Mayo!D48+Junio!D48+Julio!D48+Agosto!D48+Septiembre!D48+Octubre!D48+Noviembre!D48+Diciembre!D48 -> 850 | E48: =C48-D48 -> 1790
B49: =Categorias!B45 -> Casa Claudia | C49: =Enero!C49+Febrero!C49+Marzo!C49+Abril!C49+Mayo!C49+Junio!C49+Julio!C49+Agosto!C49+Septiembre!C49+Octubre!C49+Noviembre!C49+Diciembre!C49 -> 12500 | D49: =Enero!D49+Febrero!D49+Marzo!D49+Abril!D49+Mayo!D49+Junio!D49+Julio!D49+Agosto!D49+Septiembre!D49+Octubre!D49+Noviembre!D49+Diciembre!D49 -> 8063 | E49: =C49-D49 -> 4437
B50: =Categorias!B46 -> Muebles/electrodomésticos | C50: =Enero!C50+Febrero!C50+Marzo!C50+Abril!C50+Mayo!C50+Junio!C50+Julio!C50+Agosto!C50+Septiembre!C50+Octubre!C50+Noviembre!C50+Diciembre!C50 -> 0 | D50: =Enero!D50+Febrero!D50+Marzo!D50+Abril!D50+Mayo!D50+Junio!D50+Julio!D50+Agosto!D50+Septiembre!D50+Octubre!D50+Noviembre!D50+Diciembre!D50 -> 6642 | E50: =C50-D50 -> -6642
B51: =Categorias!B47 -> Predial | C51: =Enero!C51+Febrero!C51+Marzo!C51+Abril!C51+Mayo!C51+Junio!C51+Julio!C51+Agosto!C51+Septiembre!C51+Octubre!C51+Noviembre!C51+Diciembre!C51 -> 52600 | D51: =Enero!D51+Febrero!D51+Marzo!D51+Abril!D51+Mayo!D51+Junio!D51+Julio!D51+Agosto!D51+Septiembre!D51+Octubre!D51+Noviembre!D51+Diciembre!D51 -> 31150 | E51: =C51-D51 -> 21450
B52: =Categorias!B48 -> Renta Cuarto | C52: =Enero!C52+Febrero!C52+Marzo!C52+Abril!C52+Mayo!C52+Junio!C52+Julio!C52+Agosto!C52+Septiembre!C52+Octubre!C52+Noviembre!C52+Diciembre!C52 -> 31200 | D52: =Enero!D52+Febrero!D52+Marzo!D52+Abril!D52+Mayo!D52+Junio!D52+Julio!D52+Agosto!D52+Septiembre!D52+Octubre!D52+Noviembre!D52+Diciembre!D52 -> 28200 | E52: =C52-D52 -> 3000
B53: =Categorias!B49 -> - | C53: =Enero!C53+Febrero!C53+Marzo!C53+Abril!C53+Mayo!C53+Junio!C53+Julio!C53+Agosto!C53+Septiembre!C53+Octubre!C53+Noviembre!C53+Diciembre!C53 -> 0 | D53: =Enero!D53+Febrero!D53+Marzo!D53+Abril!D53+Mayo!D53+Junio!D53+Julio!D53+Agosto!D53+Septiembre!D53+Octubre!D53+Noviembre!D53+Diciembre!D53 -> 0 | E53: =C53-D53 -> 0
B54: =Categorias!B50 -> - | C54: =Enero!C54+Febrero!C54+Marzo!C54+Abril!C54+Mayo!C54+Junio!C54+Julio!C54+Agosto!C54+Septiembre!C54+Octubre!C54+Noviembre!C54+Diciembre!C54 -> 2200 | D54: =Enero!D54+Febrero!D54+Marzo!D54+Abril!D54+Mayo!D54+Junio!D54+Julio!D54+Agosto!D54+Septiembre!D54+Octubre!D54+Noviembre!D54+Diciembre!D54 -> 4000 | E54: =C54-D54 -> -1800
B55: =Categorias!B51 -> - | C55: =Enero!C55+Febrero!C55+Marzo!C55+Abril!C55+Mayo!C55+Junio!C55+Julio!C55+Agosto!C55+Septiembre!C55+Octubre!C55+Noviembre!C55+Diciembre!C55 -> 0 | D55: =Enero!D55+Febrero!D55+Marzo!D55+Abril!D55+Mayo!D55+Junio!D55+Julio!D55+Agosto!D55+Septiembre!D55+Octubre!D55+Noviembre!D55+Diciembre!D55 -> 0 | E55: =C55-D55 -> 0
B56: =Categorias!B52 -> - | C56: =Enero!C56+Febrero!C56+Marzo!C56+Abril!C56+Mayo!C56+Junio!C56+Julio!C56+Agosto!C56+Septiembre!C56+Octubre!C56+Noviembre!C56+Diciembre!C56 -> 0 | D56: =Enero!D56+Febrero!D56+Marzo!D56+Abril!D56+Mayo!D56+Junio!D56+Julio!D56+Agosto!D56+Septiembre!D56+Octubre!D56+Noviembre!D56+Diciembre!D56 -> 0 | E56: =C56-D56 -> 0
B58: =Categorias!B54 -> ROPA Y CALZADO | C58: =Enero!C58+Febrero!C58+Marzo!C58+Abril!C58+Mayo!C58+Junio!C58+Julio!C58+Agosto!C58+Septiembre!C58+Octubre!C58+Noviembre!C58+Diciembre!C58 -> 2400 | D58: =Enero!D58+Febrero!D58+Marzo!D58+Abril!D58+Mayo!D58+Junio!D58+Julio!D58+Agosto!D58+Septiembre!D58+Octubre!D58+Noviembre!D58+Diciembre!D58 -> 12134 | E58: =SUM(E59:E66) -> -9734
B59: =Categorias!B55 -> Ropa de adultos | C59: =Enero!C59+Febrero!C59+Marzo!C59+Abril!C59+Mayo!C59+Junio!C59+Julio!C59+Agosto!C59+Septiembre!C59+Octubre!C59+Noviembre!C59+Diciembre!C59 -> 1000 | D59: =Enero!D59+Febrero!D59+Marzo!D59+Abril!D59+Mayo!D59+Junio!D59+Julio!D59+Agosto!D59+Septiembre!D59+Octubre!D59+Noviembre!D59+Diciembre!D59 -> 5530 | E59: =C59-D59 -> -4530
B60: =Categorias!B56 -> Ropa de niños | C60: =Enero!C60+Febrero!C60+Marzo!C60+Abril!C60+Mayo!C60+Junio!C60+Julio!C60+Agosto!C60+Septiembre!C60+Octubre!C60+Noviembre!C60+Diciembre!C60 -> 1400 | D60: =Enero!D60+Febrero!D60+Marzo!D60+Abril!D60+Mayo!D60+Junio!D60+Julio!D60+Agosto!D60+Septiembre!D60+Octubre!D60+Noviembre!D60+Diciembre!D60 -> 4772 | E60: =C60-D60 -> -3372
B61: =Categorias!B57 -> Calzado | C61: =Enero!C61+Febrero!C61+Marzo!C61+Abril!C61+Mayo!C61+Junio!C61+Julio!C61+Agosto!C61+Septiembre!C61+Octubre!C61+Noviembre!C61+Diciembre!C61 -> 0 | D61: =Enero!D61+Febrero!D61+Marzo!D61+Abril!D61+Mayo!D61+Junio!D61+Julio!D61+Agosto!D61+Septiembre!D61+Octubre!D61+Noviembre!D61+Diciembre!D61 -> 1759 | E61: =C61-D61 -> -1759
B62: =Categorias!B58 -> Acessorios | C62: =Enero!C62+Febrero!C62+Marzo!C62+Abril!C62+Mayo!C62+Junio!C62+Julio!C62+Agosto!C62+Septiembre!C62+Octubre!C62+Noviembre!C62+Diciembre!C62 -> 0 | D62: =Enero!D62+Febrero!D62+Marzo!D62+Abril!D62+Mayo!D62+Junio!D62+Julio!D62+Agosto!D62+Septiembre!D62+Octubre!D62+Noviembre!D62+Diciembre!D62 -> 73 | E62: =C62-D62 -> -73
B63: =Categorias!B59 -> Joyería | C63: =Enero!C63+Febrero!C63+Marzo!C63+Abril!C63+Mayo!C63+Junio!C63+Julio!C63+Agosto!C63+Septiembre!C63+Octubre!C63+Noviembre!C63+Diciembre!C63 -> 0 | D63: =Enero!D63+Febrero!D63+Marzo!D63+Abril!D63+Mayo!D63+Junio!D63+Julio!D63+Agosto!D63+Septiembre!D63+Octubre!D63+Noviembre!D63+Diciembre!D63 -> 0 | E63: =C63-D63 -> 0
B64: =Categorias!B60 -> Otros | C64: =Enero!C64+Febrero!C64+Marzo!C64+Abril!C64+Mayo!C64+Junio!C64+Julio!C64+Agosto!C64+Septiembre!C64+Octubre!C64+Noviembre!C64+Diciembre!C64 -> 0 | D64: =Enero!D64+Febrero!D64+Marzo!D64+Abril!D64+Mayo!D64+Junio!D64+Julio!D64+Agosto!D64+Septiembre!D64+Octubre!D64+Noviembre!D64+Diciembre!D64 -> 0 | E64: =C64-D64 -> 0
B65: =Categorias!B61 -> - | C65: =Enero!C65+Febrero!C65+Marzo!C65+Abril!C65+Mayo!C65+Junio!C65+Julio!C65+Agosto!C65+Septiembre!C65+Octubre!C65+Noviembre!C65+Diciembre!C65 -> 0 | D65: =Enero!D65+Febrero!D65+Marzo!D65+Abril!D65+Mayo!D65+Junio!D65+Julio!D65+Agosto!D65+Septiembre!D65+Octubre!D65+Noviembre!D65+Diciembre!D65 -> 0 | E65: =C65-D65 -> 0
B66: =Categorias!B62 -> - | C66: =Enero!C66+Febrero!C66+Marzo!C66+Abril!C66+Mayo!C66+Junio!C66+Julio!C66+Agosto!C66+Septiembre!C66+Octubre!C66+Noviembre!C66+Diciembre!C66 -> 0 | D66: =Enero!D66+Febrero!D66+Marzo!D66+Abril!D66+Mayo!D66+Junio!D66+Julio!D66+Agosto!D66+Septiembre!D66+Octubre!D66+Noviembre!D66+Diciembre!D66 -> 0 | E66: =C66-D66 -> 0
B68: =Categorias!B64 -> COMUNICACIÓN | C68: =Enero!C68+Febrero!C68+Marzo!C68+Abril!C68+Mayo!C68+Junio!C68+Julio!C68+Agosto!C68+Septiembre!C68+Octubre!C68+Noviembre!C68+Diciembre!C68 -> 10021 | D68: =Enero!D68+Febrero!D68+Marzo!D68+Abril!D68+Mayo!D68+Junio!D68+Julio!D68+Agosto!D68+Septiembre!D68+Octubre!D68+Noviembre!D68+Diciembre!D68 -> 9897 | E68: =SUM(E69:E75) -> 124
B69: =Categorias!B65 -> Cel. Claudia | C69: =Enero!C69+Febrero!C69+Marzo!C69+Abril!C69+Mayo!C69+Junio!C69+Julio!C69+Agosto!C69+Septiembre!C69+Octubre!C69+Noviembre!C69+Diciembre!C69 -> 2978 | D69: =Enero!D69+Febrero!D69+Marzo!D69+Abril!D69+Mayo!D69+Junio!D69+Julio!D69+Agosto!D69+Septiembre!D69+Octubre!D69+Noviembre!D69+Diciembre!D69 -> 7409 | E69: =C69-D69 -> -4431
B70: =Categorias!B66 -> Cel. Carlos | C70: =Enero!C70+Febrero!C70+Marzo!C70+Abril!C70+Mayo!C70+Junio!C70+Julio!C70+Agosto!C70+Septiembre!C70+Octubre!C70+Noviembre!C70+Diciembre!C70 -> 2948 | D70: =Enero!D70+Febrero!D70+Marzo!D70+Abril!D70+Mayo!D70+Junio!D70+Julio!D70+Agosto!D70+Septiembre!D70+Octubre!D70+Noviembre!D70+Diciembre!D70 -> 799 | E70: =C70-D70 -> 2149
B71: =Categorias!B67 -> Cel.Kary | C71: =Enero!C71+Febrero!C71+Marzo!C71+Abril!C71+Mayo!C71+Junio!C71+Julio!C71+Agosto!C71+Septiembre!C71+Octubre!C71+Noviembre!C71+Diciembre!C71 -> 2000 | D71: =Enero!D71+Febrero!D71+Marzo!D71+Abril!D71+Mayo!D71+Junio!D71+Julio!D71+Agosto!D71+Septiembre!D71+Octubre!D71+Noviembre!D71+Diciembre!D71 -> 870 | E71: =C71-D71 -> 1130
B72: =Categorias!B68 -> - | C72: =Enero!C72+Febrero!C72+Marzo!C72+Abril!C72+Mayo!C72+Junio!C72+Julio!C72+Agosto!C72+Septiembre!C72+Octubre!C72+Noviembre!C72+Diciembre!C72 -> 1656 | D72: =Enero!D72+Febrero!D72+Marzo!D72+Abril!D72+Mayo!D72+Junio!D72+Julio!D72+Agosto!D72+Septiembre!D72+Octubre!D72+Noviembre!D72+Diciembre!D72 -> 600 | E72: =C72-D72 -> 1056
B73: =Categorias!B69 -> - | C73: =Enero!C73+Febrero!C73+Marzo!C73+Abril!C73+Mayo!C73+Junio!C73+Julio!C73+Agosto!C73+Septiembre!C73+Octubre!C73+Noviembre!C73+Diciembre!C73 -> 439 | D73: =Enero!D73+Febrero!D73+Marzo!D73+Abril!D73+Mayo!D73+Junio!D73+Julio!D73+Agosto!D73+Septiembre!D73+Octubre!D73+Noviembre!D73+Diciembre!D73 -> 219 | E73: =C73-D73 -> 220
B74: =Categorias!B70 -> - | C74: =Enero!C74+Febrero!C74+Marzo!C74+Abril!C74+Mayo!C74+Junio!C74+Julio!C74+Agosto!C74+Septiembre!C74+Octubre!C74+Noviembre!C74+Diciembre!C74 -> 0 | D74: =Enero!D74+Febrero!D74+Marzo!D74+Abril!D74+Mayo!D74+Junio!D74+Julio!D74+Agosto!D74+Septiembre!D74+Octubre!D74+Noviembre!D74+Diciembre!D74 -> 0 | E74: =C74-D74 -> 0
B75: =Categorias!B73 -> - | C75: =Enero!C75+Febrero!C75+Marzo!C75+Abril!C75+Mayo!C75+Junio!C75+Julio!C75+Agosto!C75+Septiembre!C75+Octubre!C75+Noviembre!C75+Diciembre!C75 -> 0 | D75: =Enero!D75+Febrero!D75+Marzo!D75+Abril!D75+Mayo!D75+Junio!D75+Julio!D75+Agosto!D75+Septiembre!D75+Octubre!D75+Noviembre!D75+Diciembre!D75 -> 0 | E75: =C75-D75 -> 0
B77: =Categorias!B75 -> TRANSPORTE | C77: =Enero!C77+Febrero!C77+Marzo!C77+Abril!C77+Mayo!C77+Junio!C77+Julio!C77+Agosto!C77+Septiembre!C77+Octubre!C77+Noviembre!C77+Diciembre!C77 -> 38750.68 | D77: =Enero!D77+Febrero!D77+Marzo!D77+Abril!D77+Mayo!D77+Junio!D77+Julio!D77+Agosto!D77+Septiembre!D77+Octubre!D77+Noviembre!D77+Diciembre!D77 -> 32463.21 | E77: =SUM(E78:E86) -> 6287.47
B78: =Categorias!B76 -> Combustible Fusion | C78: =Enero!C78+Febrero!C78+Marzo!C78+Abril!C78+Mayo!C78+Junio!C78+Julio!C78+Agosto!C78+Septiembre!C78+Octubre!C78+Noviembre!C78+Diciembre!C78 -> 19600 | D78: =Enero!D78+Febrero!D78+Marzo!D78+Abril!D78+Mayo!D78+Junio!D78+Julio!D78+Agosto!D78+Septiembre!D78+Octubre!D78+Noviembre!D78+Diciembre!D78 -> 15614.21 | E78: =C78-D78 -> 3985.79
B79: =Categorias!B77 -> Seguro Fusion | C79: =Enero!C79+Febrero!C79+Marzo!C79+Abril!C79+Mayo!C79+Junio!C79+Julio!C79+Agosto!C79+Septiembre!C79+Octubre!C79+Noviembre!C79+Diciembre!C79 -> 2700 | D79: =Enero!D79+Febrero!D79+Marzo!D79+Abril!D79+Mayo!D79+Junio!D79+Julio!D79+Agosto!D79+Septiembre!D79+Octubre!D79+Noviembre!D79+Diciembre!D79 -> 150 | E79: =C79-D79 -> 2550
B80: =Categorias!B78 -> Mantenimiento Fusion | C80: =Enero!C80+Febrero!C80+Marzo!C80+Abril!C80+Mayo!C80+Junio!C80+Julio!C80+Agosto!C80+Septiembre!C80+Octubre!C80+Noviembre!C80+Diciembre!C80 -> 10000 | D80: =Enero!D80+Febrero!D80+Marzo!D80+Abril!D80+Mayo!D80+Junio!D80+Julio!D80+Agosto!D80+Septiembre!D80+Octubre!D80+Noviembre!D80+Diciembre!D80 -> 7536 | E80: =C80-D80 -> 2464
B81: =Categorias!B79 -> Derecho vehicular Fusion | C81: =Enero!C81+Febrero!C81+Marzo!C81+Abril!C81+Mayo!C81+Junio!C81+Julio!C81+Agosto!C81+Septiembre!C81+Octubre!C81+Noviembre!C81+Diciembre!C81 -> 3700 | D81: =Enero!D81+Febrero!D81+Marzo!D81+Abril!D81+Mayo!D81+Junio!D81+Julio!D81+Agosto!D81+Septiembre!D81+Octubre!D81+Noviembre!D81+Diciembre!D81 -> 0 | E81: =C81-D81 -> 3700
B82: =Categorias!B80 -> Casetas | C82: =Enero!C82+Febrero!C82+Marzo!C82+Abril!C82+Mayo!C82+Junio!C82+Julio!C82+Agosto!C82+Septiembre!C82+Octubre!C82+Noviembre!C82+Diciembre!C82 -> 2300 | D82: =Enero!D82+Febrero!D82+Marzo!D82+Abril!D82+Mayo!D82+Junio!D82+Julio!D82+Agosto!D82+Septiembre!D82+Octubre!D82+Noviembre!D82+Diciembre!D82 -> 2860 | E82: =C82-D82 -> -560
B83: =Categorias!B81 -> ADO | C83: =Enero!C83+Febrero!C83+Marzo!C83+Abril!C83+Mayo!C83+Junio!C83+Julio!C83+Agosto!C83+Septiembre!C83+Octubre!C83+Noviembre!C83+Diciembre!C83 -> 0 | D83: =Enero!D83+Febrero!D83+Marzo!D83+Abril!D83+Mayo!D83+Junio!D83+Julio!D83+Agosto!D83+Septiembre!D83+Octubre!D83+Noviembre!D83+Diciembre!D83 -> 5895 | E83: =C83-D83 -> -5895
B84: =Categorias!B82 -> - | C84: =Enero!C84+Febrero!C84+Marzo!C84+Abril!C84+Mayo!C84+Junio!C84+Julio!C84+Agosto!C84+Septiembre!C84+Octubre!C84+Noviembre!C84+Diciembre!C84 -> 450.68 | D84: =Enero!D84+Febrero!D84+Marzo!D84+Abril!D84+Mayo!D84+Junio!D84+Julio!D84+Agosto!D84+Septiembre!D84+Octubre!D84+Noviembre!D84+Diciembre!D84 -> 368 | E84: =C84-D84 -> 82.68
B85: =Categorias!B83 -> - | C85: =Enero!C85+Febrero!C85+Marzo!C85+Abril!C85+Mayo!C85+Junio!C85+Julio!C85+Agosto!C85+Septiembre!C85+Octubre!C85+Noviembre!C85+Diciembre!C85 -> 0 | D85: =Enero!D85+Febrero!D85+Marzo!D85+Abril!D85+Mayo!D85+Junio!D85+Julio!D85+Agosto!D85+Septiembre!D85+Octubre!D85+Noviembre!D85+Diciembre!D85 -> 0 | E85: =C85-D85 -> 0
B86: =Categorias!B84 -> - | C86: =Enero!C86+Febrero!C86+Marzo!C86+Abril!C86+Mayo!C86+Junio!C86+Julio!C86+Agosto!C86+Septiembre!C86+Octubre!C86+Noviembre!C86+Diciembre!C86 -> 0 | D86: =Enero!D86+Febrero!D86+Marzo!D86+Abril!D86+Mayo!D86+Junio!D86+Julio!D86+Agosto!D86+Septiembre!D86+Octubre!D86+Noviembre!D86+Diciembre!D86 -> 40 | E86: =C86-D86 -> -40
B88: =Categorias!B86 -> HIGIENE | C88: =Enero!C88+Febrero!C88+Marzo!C88+Abril!C88+Mayo!C88+Junio!C88+Julio!C88+Agosto!C88+Septiembre!C88+Octubre!C88+Noviembre!C88+Diciembre!C88 -> 1780 | D88: =Enero!D88+Febrero!D88+Marzo!D88+Abril!D88+Mayo!D88+Junio!D88+Julio!D88+Agosto!D88+Septiembre!D88+Octubre!D88+Noviembre!D88+Diciembre!D88 -> 4911.5 | E88: =SUM(E89:E95) -> -3131.5
B89: =Categorias!B87 -> Cosmeticos | C89: =Enero!C89+Febrero!C89+Marzo!C89+Abril!C89+Mayo!C89+Junio!C89+Julio!C89+Agosto!C89+Septiembre!C89+Octubre!C89+Noviembre!C89+Diciembre!C89 -> 0 | D89: =Enero!D89+Febrero!D89+Marzo!D89+Abril!D89+Mayo!D89+Junio!D89+Julio!D89+Agosto!D89+Septiembre!D89+Octubre!D89+Noviembre!D89+Diciembre!D89 -> 1003 | E89: =C89-D89 -> -1003
B90: =Categorias!B88 -> Peluquería / S. Belleza | C90: =Enero!C90+Febrero!C90+Marzo!C90+Abril!C90+Mayo!C90+Junio!C90+Julio!C90+Agosto!C90+Septiembre!C90+Octubre!C90+Noviembre!C90+Diciembre!C90 -> 1580 | D90: =Enero!D90+Febrero!D90+Marzo!D90+Abril!D90+Mayo!D90+Junio!D90+Julio!D90+Agosto!D90+Septiembre!D90+Octubre!D90+Noviembre!D90+Diciembre!D90 -> 520 | E90: =C90-D90 -> 1060
B91: =Categorias!B89 -> Lavanderia | C91: =Enero!C91+Febrero!C91+Marzo!C91+Abril!C91+Mayo!C91+Junio!C91+Julio!C91+Agosto!C91+Septiembre!C91+Octubre!C91+Noviembre!C91+Diciembre!C91 -> 0 | D91: =Enero!D91+Febrero!D91+Marzo!D91+Abril!D91+Mayo!D91+Junio!D91+Julio!D91+Agosto!D91+Septiembre!D91+Octubre!D91+Noviembre!D91+Diciembre!D91 -> 150 | E91: =C91-D91 -> -150
B92: =Categorias!B90 -> Productos de limpieza | C92: =Enero!C92+Febrero!C92+Marzo!C92+Abril!C92+Mayo!C92+Junio!C92+Julio!C92+Agosto!C92+Septiembre!C92+Octubre!C92+Noviembre!C92+Diciembre!C92 -> 200 | D92: =Enero!D92+Febrero!D92+Marzo!D92+Abril!D92+Mayo!D92+Junio!D92+Julio!D92+Agosto!D92+Septiembre!D92+Octubre!D92+Noviembre!D92+Diciembre!D92 -> 1638.5 | E92: =C92-D92 -> -1438.5
B93: =Categorias!B91 -> Otros | C93: =Enero!C93+Febrero!C93+Marzo!C93+Abril!C93+Mayo!C93+Junio!C93+Julio!C93+Agosto!C93+Septiembre!C93+Octubre!C93+Noviembre!C93+Diciembre!C93 -> 0 | D93: =Enero!D93+Febrero!D93+Marzo!D93+Abril!D93+Mayo!D93+Junio!D93+Julio!D93+Agosto!D93+Septiembre!D93+Octubre!D93+Noviembre!D93+Diciembre!D93 -> 1600 | E93: =C93-D93 -> -1600
B94: =Categorias!B92 -> - | C94: =Enero!C94+Febrero!C94+Marzo!C94+Abril!C94+Mayo!C94+Junio!C94+Julio!C94+Agosto!C94+Septiembre!C94+Octubre!C94+Noviembre!C94+Diciembre!C94 -> 0 | D94: =Enero!D94+Febrero!D94+Marzo!D94+Abril!D94+Mayo!D94+Junio!D94+Julio!D94+Agosto!D94+Septiembre!D94+Octubre!D94+Noviembre!D94+Diciembre!D94 -> 0 | E94: =C94-D94 -> 0
B95: =Categorias!B93 -> - | C95: =Enero!C95+Febrero!C95+Marzo!C95+Abril!C95+Mayo!C95+Junio!C95+Julio!C95+Agosto!C95+Septiembre!C95+Octubre!C95+Noviembre!C95+Diciembre!C95 -> 0 | D95: =Enero!D95+Febrero!D95+Marzo!D95+Abril!D95+Mayo!D95+Junio!D95+Julio!D95+Agosto!D95+Septiembre!D95+Octubre!D95+Noviembre!D95+Diciembre!D95 -> 0 | E95: =C95-D95 -> 0
B97: =Categorias!B95 -> NIÑOS | C97: =Enero!C97+Febrero!C97+Marzo!C97+Abril!C97+Mayo!C97+Junio!C97+Julio!C97+Agosto!C97+Septiembre!C97+Octubre!C97+Noviembre!C97+Diciembre!C97 -> 7300 | D97: =Enero!D97+Febrero!D97+Marzo!D97+Abril!D97+Mayo!D97+Junio!D97+Julio!D97+Agosto!D97+Septiembre!D97+Octubre!D97+Noviembre!D97+Diciembre!D97 -> 6531 | E97: =SUM(E98:E105) -> 769
B98: =Categorias!B96 -> Jugetes/juegos | C98: =Enero!C98+Febrero!C98+Marzo!C98+Abril!C98+Mayo!C98+Junio!C98+Julio!C98+Agosto!C98+Septiembre!C98+Octubre!C98+Noviembre!C98+Diciembre!C98 -> 2000 | D98: =Enero!D98+Febrero!D98+Marzo!D98+Abril!D98+Mayo!D98+Junio!D98+Julio!D98+Agosto!D98+Septiembre!D98+Octubre!D98+Noviembre!D98+Diciembre!D98 -> 0 | E98: =C98-D98 -> 2000
B99: =Categorias!B97 -> - | C99: =Enero!C99+Febrero!C99+Marzo!C99+Abril!C99+Mayo!C99+Junio!C99+Julio!C99+Agosto!C99+Septiembre!C99+Octubre!C99+Noviembre!C99+Diciembre!C99 -> 4700 | D99: =Enero!D99+Febrero!D99+Marzo!D99+Abril!D99+Mayo!D99+Junio!D99+Julio!D99+Agosto!D99+Septiembre!D99+Octubre!D99+Noviembre!D99+Diciembre!D99 -> 2881 | E99: =C99-D99 -> 1819
B100: =Categorias!B98 -> - | C100: =Enero!C100+Febrero!C100+Marzo!C100+Abril!C100+Mayo!C100+Junio!C100+Julio!C100+Agosto!C100+Septiembre!C100+Octubre!C100+Noviembre!C100+Diciembre!C100 -> 0 | D100: =Enero!D100+Febrero!D100+Marzo!D100+Abril!D100+Mayo!D100+Junio!D100+Julio!D100+Agosto!D100+Septiembre!D100+Octubre!D100+Noviembre!D100+Diciembre!D100 -> 0 | E100: =C100-D100 -> 0
B101: =Categorias!B99 -> - | C101: =Enero!C101+Febrero!C101+Marzo!C101+Abril!C101+Mayo!C101+Junio!C101+Julio!C101+Agosto!C101+Septiembre!C101+Octubre!C101+Noviembre!C101+Diciembre!C101 -> 200 | D101: =Enero!D101+Febrero!D101+Marzo!D101+Abril!D101+Mayo!D101+Junio!D101+Julio!D101+Agosto!D101+Septiembre!D101+Octubre!D101+Noviembre!D101+Diciembre!D101 -> 3650 | E101: =C101-D101 -> -3450
B102: =Categorias!B100 -> - | C102: =Enero!C102+Febrero!C102+Marzo!C102+Abril!C102+Mayo!C102+Junio!C102+Julio!C102+Agosto!C102+Septiembre!C102+Octubre!C102+Noviembre!C102+Diciembre!C102 -> 400 | D102: =Enero!D102+Febrero!D102+Marzo!D102+Abril!D102+Mayo!D102+Junio!D102+Julio!D102+Agosto!D102+Septiembre!D102+Octubre!D102+Noviembre!D102+Diciembre!D102 -> 0 | E102: =C102-D102 -> 400
B103: =Categorias!B101 -> - | C103: =Enero!C103+Febrero!C103+Marzo!C103+Abril!C103+Mayo!C103+Junio!C103+Julio!C103+Agosto!C103+Septiembre!C103+Octubre!C103+Noviembre!C103+Diciembre!C103 -> 0 | D103: =Enero!D103+Febrero!D103+Marzo!D103+Abril!D103+Mayo!D103+Junio!D103+Julio!D103+Agosto!D103+Septiembre!D103+Octubre!D103+Noviembre!D103+Diciembre!D103 -> 0 | E103: =C103-D103 -> 0
B104: =Categorias!B102 -> - | C104: =Enero!C104+Febrero!C104+Marzo!C104+Abril!C104+Mayo!C104+Junio!C104+Julio!C104+Agosto!C104+Septiembre!C104+Octubre!C104+Noviembre!C104+Diciembre!C104 -> 0 | D104: =Enero!D104+Febrero!D104+Marzo!D104+Abril!D104+Mayo!D104+Junio!D104+Julio!D104+Agosto!D104+Septiembre!D104+Octubre!D104+Noviembre!D104+Diciembre!D104 -> 0 | E104: =C104-D104 -> 0
B105: =Categorias!B103 -> - | C105: =Enero!C105+Febrero!C105+Marzo!C105+Abril!C105+Mayo!C105+Junio!C105+Julio!C105+Agosto!C105+Septiembre!C105+Octubre!C105+Noviembre!C105+Diciembre!C105 -> 0 | D105: =Enero!D105+Febrero!D105+Marzo!D105+Abril!D105+Mayo!D105+Junio!D105+Julio!D105+Agosto!D105+Septiembre!D105+Octubre!D105+Noviembre!D105+Diciembre!D105 -> 0 | E105: =C105-D105 -> 0
B107: =Categorias!B105 -> DESARROLLO PERSONAL | C107: =Enero!C107+Febrero!C107+Marzo!C107+Abril!C107+Mayo!C107+Junio!C107+Julio!C107+Agosto!C107+Septiembre!C107+Octubre!C107+Noviembre!C107+Diciembre!C107 -> 3950 | D107: =Enero!D107+Febrero!D107+Marzo!D107+Abril!D107+Mayo!D107+Junio!D107+Julio!D107+Agosto!D107+Septiembre!D107+Octubre!D107+Noviembre!D107+Diciembre!D107 -> 3902 | E107: =SUM(E108:E113) -> 48
B108: =Categorias!B106 -> Libros | C108: =Enero!C108+Febrero!C108+Marzo!C108+Abril!C108+Mayo!C108+Junio!C108+Julio!C108+Agosto!C108+Septiembre!C108+Octubre!C108+Noviembre!C108+Diciembre!C108 -> 0 | D108: =Enero!D108+Febrero!D108+Marzo!D108+Abril!D108+Mayo!D108+Junio!D108+Julio!D108+Agosto!D108+Septiembre!D108+Octubre!D108+Noviembre!D108+Diciembre!D108 -> 502 | E108: =C108-D108 -> -502
B109: =Categorias!B107 -> Platzi | C109: =Enero!C109+Febrero!C109+Marzo!C109+Abril!C109+Mayo!C109+Junio!C109+Julio!C109+Agosto!C109+Septiembre!C109+Octubre!C109+Noviembre!C109+Diciembre!C109 -> 0 | D109: =Enero!D109+Febrero!D109+Marzo!D109+Abril!D109+Mayo!D109+Junio!D109+Julio!D109+Agosto!D109+Septiembre!D109+Octubre!D109+Noviembre!D109+Diciembre!D109 -> 0 | E109: =C109-D109 -> 0
B110: =Categorias!B108 -> Papeleria | C110: =Enero!C110+Febrero!C110+Marzo!C110+Abril!C110+Mayo!C110+Junio!C110+Julio!C110+Agosto!C110+Septiembre!C110+Octubre!C110+Noviembre!C110+Diciembre!C110 -> 0 | D110: =Enero!D110+Febrero!D110+Marzo!D110+Abril!D110+Mayo!D110+Junio!D110+Julio!D110+Agosto!D110+Septiembre!D110+Octubre!D110+Noviembre!D110+Diciembre!D110 -> 0 | E110: =C110-D110 -> 0
B111: =Categorias!B109 -> Inglés Thiago | C111: =Enero!C111+Febrero!C111+Marzo!C111+Abril!C111+Mayo!C111+Junio!C111+Julio!C111+Agosto!C111+Septiembre!C111+Octubre!C111+Noviembre!C111+Diciembre!C111 -> 1500 | D111: =Enero!D111+Febrero!D111+Marzo!D111+Abril!D111+Mayo!D111+Junio!D111+Julio!D111+Agosto!D111+Septiembre!D111+Octubre!D111+Noviembre!D111+Diciembre!D111 -> 0 | E111: =C111-D111 -> 1500
B112: =Categorias!B110 -> Arte Thiago | C112: =Enero!C112+Febrero!C112+Marzo!C112+Abril!C112+Mayo!C112+Junio!C112+Julio!C112+Agosto!C112+Septiembre!C112+Octubre!C112+Noviembre!C112+Diciembre!C112 -> 450 | D112: =Enero!D112+Febrero!D112+Marzo!D112+Abril!D112+Mayo!D112+Junio!D112+Julio!D112+Agosto!D112+Septiembre!D112+Octubre!D112+Noviembre!D112+Diciembre!D112 -> 400 | E112: =C112-D112 -> 50
B113: =Categorias!B111 -> Escuela kary | C113: =Enero!C113+Febrero!C113+Marzo!C113+Abril!C113+Mayo!C113+Junio!C113+Julio!C113+Agosto!C113+Septiembre!C113+Octubre!C113+Noviembre!C113+Diciembre!C113 -> 2000 | D113: =Enero!D113+Febrero!D113+Marzo!D113+Abril!D113+Mayo!D113+Junio!D113+Julio!D113+Agosto!D113+Septiembre!D113+Octubre!D113+Noviembre!D113+Diciembre!D113 -> 3000 | E113: =C113-D113 -> -1000
B115: =Categorias!B113 -> DIVERSIÓN | C115: =Enero!C115+Febrero!C115+Marzo!C115+Abril!C115+Mayo!C115+Junio!C115+Julio!C115+Agosto!C115+Septiembre!C115+Octubre!C115+Noviembre!C115+Diciembre!C115 -> 7450 | D115: =Enero!D115+Febrero!D115+Marzo!D115+Abril!D115+Mayo!D115+Junio!D115+Julio!D115+Agosto!D115+Septiembre!D115+Octubre!D115+Noviembre!D115+Diciembre!D115 -> 7588 | E115: =SUM(E116:E124) -> -138
B116: =Categorias!B114 -> Cine/teatro | C116: =Enero!C116+Febrero!C116+Marzo!C116+Abril!C116+Mayo!C116+Junio!C116+Julio!C116+Agosto!C116+Septiembre!C116+Octubre!C116+Noviembre!C116+Diciembre!C116 -> 0 | D116: =Enero!D116+Febrero!D116+Marzo!D116+Abril!D116+Mayo!D116+Junio!D116+Julio!D116+Agosto!D116+Septiembre!D116+Octubre!D116+Noviembre!D116+Diciembre!D116 -> 3577 | E116: =C116-D116 -> -3577
B117: =Categorias!B115 -> Gimnasio/piscina | C117: =Enero!C117+Febrero!C117+Marzo!C117+Abril!C117+Mayo!C117+Junio!C117+Julio!C117+Agosto!C117+Septiembre!C117+Octubre!C117+Noviembre!C117+Diciembre!C117 -> 7300 | D117: =Enero!D117+Febrero!D117+Marzo!D117+Abril!D117+Mayo!D117+Junio!D117+Julio!D117+Agosto!D117+Septiembre!D117+Octubre!D117+Noviembre!D117+Diciembre!D117 -> 3605 | E117: =C117-D117 -> 3695
...

Sheet Enero
B2: Presupuesto | C2: 45292
C4: Para crear un presupuesto: - A principios de este mes, rellene los campos en amarillo, despues de forma regular registre los gastos de cada dia en la tabla a la derecha - Todos los otros datos se convertirá automáticamente
C5: Fuente: | D5: =HYPERLINK("http://www.aprendizfinanciero.com/","http://www.aprendizfinanciero.com") -> http://www.aprendizfinanciero.com
B6: Ingresos
B8: Categoría | C8: Ingresos previstos | D8: Ingresos reales | E8: Diferencia | F8: Notas
B9: SUMA | C9: =C11 -> 53400 | D9: =D11 -> 26400 | E9: =E11 -> -27000
B11: =Categorias!B11 -> INGRESOS TOTALES | C11: =SUM(C12:C20) -> 53400 | D11: =SUM(D12:D20) -> 26400 | E11: =SUM(E12:E20) -> -27000 | H11: 1 | I11: 2 | J11: 3 | K11: 4 | L11: 5 | M11: 6 | N11: 7 | O11: 8 | P11: 9 | Q11: 10 | R11: 11 | S11: 12 | T11: 13 | U11: 14 | V11: 15 | W11: 16 | X11: 17 | Y11: 18 | Z11: 19 | AA11: 20 | AB11: 21 | AC11: 22 | AD11: 23 | AE11: 24 | AF11: 25 | AG11: 26 | AH11: 27 | AI11: 28 | AJ11: 29 | AK11: 30 | AL11: 31
B12: =Categorias!B12 -> Nomina | C12: 50000 | D12: =SUM(Enero!$H12:$AL12) -> 23000 | E12: =D12-C12 -> -27000 | H12: 23000
B13: =Categorias!B13 -> Aguinaldo | C13: 0 | D13: =SUM(Enero!$H13:$AL13) -> 0 | E13: =D13-C13 -> 0
B14: =Categorias!B14 -> Fondo de ahorro | C14: 0 | D14: =SUM(Enero!$H14:$AL14) -> 0 | E14: =D14-C14 -> 0
B15: =Categorias!B15 -> Vales despensa | C15: 3400 | D15: =SUM(Enero!$H15:$AL15) -> 3400 | E15: =D15-C15 -> 0 | H15: 3400
B16: =Categorias!B16 -> Vales comedor | C16: 0 | D16: =SUM(Enero!$H16:$AL16) -> 0 | E16: =D16-C16 -> 0
B17: =Categorias!B17 -> - | C17: 0 | D17: =SUM(Enero!$H17:$AL17) -> 0 | E17: =D17-C17 -> 0
B18: =Categorias!B18 -> - | C18: 0 | D18: =SUM(Enero!$H18:$AL18) -> 0 | E18: =D18-C18 -> 0
B19: =Categorias!B19 -> - | C19: 0 | D19: =SUM(Enero!$H19:$AL19) -> 0 | E19: =D19-C19 -> 0
B20: =Categorias!B20 -> - | C20: 0 | D20: =SUM(Enero!$H20:$AL20) -> 0 | E20: =D20-C20 -> 0
B23: Gastos | H23: Registro de gastos diarios
B25: Categoría | C25: Gastos previstos | D25: Gastos reales | E25: Diferencia | F25: Notas | H25: Los campos siguientes son para un registro diario de gastos en cada categoría.
B26: SUMA | C26: =C28+C37+C45+C58+C68+C77+C88+C97+C107+C115+C126+C136+C146+C158 -> 59100 | D26: =D28+D37+D45+D58+D68+D77+D88+D97+D107+D115+D126+D136+D146+D158 -> 48977.83 | E26: =E28+E37+E45+E58+E68+E77+E88+E97+E107+E115+E126+E136+E146+E158 -> 10122.17 | H26: Si quieres incluir mas gastos en una celda, por el mismo dia, ingresa "=" y sigue la ecuación, por ejemplo:. = 25 + 20.5
B28: =Categorias!B24 -> ALIMENTOS Y BEBIDAS | C28: =SUM(C29:C35) -> 5000 | D28: =SUM(D29:D35) -> 9325 | E28: =SUM(E29:E35) -> -4325 | H28: 1 | I28: 2 | J28: 3 | K28: 4 | L28: 5 | M28: 6 | N28: 7 | O28: 8 | P28: 9 | Q28: 10 | R28: 11 | S28: 12 | T28: 13 | U28: 14 | V28: 15 | W28: 16 | X28: 17 | Y28: 18 | Z28: 19 | AA28: 20 | AB28: 21 | AC28: 22 | AD28: 23 | AE28: 24 | AF28: 25 | AG28: 26 | AH28: 27 | AI28: 28 | AJ28: 29 | AK28: 30 | AL28: 31
B29: =Categorias!B25 -> Restaurantes | C29: 0 | D29: =SUM(Enero!$H29:$AL29) -> 7710 | E29: =C29-D29 -> -7710 | J29: 460 | L29: 980 | M29: 430 | O29: 70 | P29: 750 | Q29: 1300 | R29: 320 | U29: 423 | V29: 180 | W29: 370 | X29: 235 | Y29: 176 | Z29: 882 | AA29: 136 | AB29: 219 | AC29: 505 | AD29: 204 | AE29: 70
B30: =Categorias!B26 -> Comida Carlos | C30: 5000 | D30: =SUM(Enero!$H30:$AL30) -> 1615 | E30: =C30-D30 -> 3385 | W30: 432 | X30: 297 | Y30: 164 | AA30: 90 | AB30: 80 | AE30: 552
B31: =Categorias!B27 -> - | C31: 0 | D31: =SUM(Enero!$H31:$AL31) -> 0 | E31: =C31-D31 -> 0
B32: =Categorias!B28 -> - | C32: 0 | D32: =SUM(Enero!$H32:$AL32) -> 0 | E32: =C32-D32 -> 0
B33: =Categorias!B29 -> - | C33: 0 | D33: =SUM(Enero!$H33:$AL33) -> 0 | E33: =C33-D33 -> 0
B34: =Categorias!B30 -> - | C34: 0 | D34: =SUM(Enero!$H34:$AL34) -> 0 | E34: =C34-D34 -> 0
B35: =Categorias!B31 -> - | C35: 0 | D35: =SUM(Enero!$H35:$AL35) -> 0 | E35: =C35-D35 -> 0
B37: =Categorias!B33 -> SALUD | C37: =SUM(C38:C43) -> 1000 | D37: =SUM(D38:D43) -> 1229 | E37: =SUM(E38:E43) -> -229 | H37: 1 | I37: 2 | J37: 3 | K37: 4 | L37: 5 | M37: 6 | N37: 7 | O37: 8 | P37: 9 | Q37: 10 | R37: 11 | S37: 12 | T37: 13 | U37: 14 | V37: 15 | W37: 16 | X37: 17 | Y37: 18 | Z37: 19 | AA37: 20 | AB37: 21 | AC37: 22 | AD37: 23 | AE37: 24 | AF37: 25 | AG37: 26 | AH37: 27 | AI37: 28 | AJ37: 29 | AK37: 30 | AL37: 31
B38: =Categorias!B34 -> Gastos en médicos | C38: 0 | D38: =SUM(Enero!$H38:$AL38) -> 0 | E38: =C38-D38 -> 0
B39: =Categorias!B35 -> Medicamentos | C39: 1000 | D39: =SUM(Enero!$H39:$AL39) -> 1229 | E39: =C39-D39 -> -229 | J39: 300 | AA39: 929
B40: =Categorias!B36 -> Dentista Kary | C40: 0 | D40: =SUM(Enero!$H40:$AL40) -> 0 | E40: =C40-D40 -> 0
B41: =Categorias!B37 -> Dentista Thiago | C41: 0 | D41: =SUM(Enero!$H41:$AL41) -> 0 | E41: =C41-D41 -> 0
B42: =Categorias!B38 -> - | C42: 0 | D42: =SUM(Enero!$H42:$AL42) -> 0 | E42: =C42-D42 -> 0
B43: =Categorias!B39 -> - | C43: 0 | D43: =SUM(Enero!$H43:$AL43) -> 0 | E43: =C43-D43 -> 0
B45: =Categorias!B41 -> CASA | C45: =SUM(C46:C56) -> 29700 | D45: =SUM(D46:D56) -> 23585 | E45: =SUM(E46:E56) -> 6115 | H45: 1 | I45: 2 | J45: 3 | K45: 4 | L45: 5 | M45: 6 | N45: 7 | O45: 8 | P45: 9 | Q45: 10 | R45: 11 | S45: 12 | T45: 13 | U45: 14 | V45: 15 | W45: 16 | X45: 17 | Y45: 18 | Z45: 19 | AA45: 20 | AB45: 21 | AC45: 22 | AD45: 23 | AE45: 24 | AF45: 25 | AG45: 26 | AH45: 27 | AI45: 28 | AJ45: 29 | AK45: 30 | AL45: 31
B46: =Categorias!B42 -> Reparación | C46: 0 | D46: =SUM(Enero!$H46:$AL46) -> 345 | E46: =C46-D46 -> -345 | O46: 345
B47: =Categorias!B43 -> Electricidad | C47: 2500 | D47: =SUM(Enero!$H47:$AL47) -> 0 | E47: =C47-D47 -> 2500
B48: =Categorias!B44 -> Gas | C48: 200 | D48: =SUM(Enero!$H48:$AL48) -> 0 | E48: =C48-D48 -> 200
B49: =Categorias!B45 -> Casa Claudia | C49: 12400 | D49: =SUM(Enero!$H49:$AL49) -> 7900 | E49: =C49-D49 -> 4500 | H49: 4500 | I49: 3400
B50: =Categorias!B46 -> Muebles/electrodomésticos | C50: 0 | D50: =SUM(Enero!$H50:$AL50) -> 1340 | E50: =C50-D50 -> -1340 | L50: 350 | X50: 370 | AA50: 300 | AD50: 320
B51: =Categorias!B47 -> Predial | C51: 600 | D51: =SUM(Enero!$H51:$AL51) -> 0 | E51: =C51-D51 -> 600
B52: =Categorias!B48 -> Renta Cuarto | C52: 14000 | D52: =SUM(Enero!$H52:$AL52) -> 14000 | E52: =C52-D52 -> 0 | V52: 14000
B53: =Categorias!B49 -> - | C53: 0 | D53: =SUM(Enero!$H53:$AL53) -> 0 | E53: =C53-D53 -> 0
B54: =Categorias!B50 -> - | C54: 0 | D54: =SUM(Enero!$H54:$AL54) -> 0 | E54: =C54-D54 -> 0
B55: =Categorias!B51 -> - | C55: 0 | D55: =SUM(Enero!$H55:$AL55) -> 0 | E55: =C55-D55 -> 0
B56: =Categorias!B52 -> - | C56: 0 | D56: =SUM(Enero!$H56:$AL56) -> 0 | E56: =C56-D56 -> 0
B58: =Categorias!B54 -> ROPA Y CALZADO | C58: =SUM(C59:C66) -> 0 | D58: =SUM(D59:D66) -> 1930 | E58: =SUM(E59:E66) -> -1930 | H58: 1 | I58: 2 | J58: 3 | K58: 4 | L58: 5 | M58: 6 | N58: 7 | O58: 8 | P58: 9 | Q58: 10 | R58: 11 | S58: 12 | T58: 13 | U58: 14 | V58: 15 | W58: 16 | X58: 17 | Y58: 18 | Z58: 19 | AA58: 20 | AB58: 21 | AC58: 22 | AD58: 23 | AE58: 24 | AF58: 25 | AG58: 26 | AH58: 27 | AI58: 28 | AJ58: 29 | AK58: 30 | AL58: 31
B59: =Categorias!B55 -> Ropa de adultos | C59: 0 | D59: =SUM(Enero!$H59:$AL59) -> 1930 | E59: =C59-D59 -> -1930 | Y59: 1930
B60: =Categorias!B56 -> Ropa de niños | C60: 0 | D60: =SUM(Enero!$H60:$AL60) -> 0 | E60: =C60-D60 -> 0
B61: =Categorias!B57 -> Calzado | C61: 0 | D61: =SUM(Enero!$H61:$AL61) -> 0 | E61: =C61-D61 -> 0
B62: =Categorias!B58 -> Acessorios | C62: 0 | D62: =SUM(Enero!$H62:$AL62) -> 0 | E62: =C62-D62 -> 0
B63: =Categorias!B59 -> Joyería | C63: 0 | D63: =SUM(Enero!$H63:$AL63) -> 0 | E63: =C63-D63 -> 0
B64: =Categorias!B60 -> Otros | C64: 0 | D64: =SUM(Enero!$H64:$AL64) -> 0 | E64: =C64-D64 -> 0
B65: =Categorias!B61 -> - | C65: 0 | D65: =SUM(Enero!$H65:$AL65) -> 0 | E65: =C65-D65 -> 0
B66: =Categorias!B62 -> - | C66: 0 | D66: =SUM(Enero!$H66:$AL66) -> 0 | E66: =C66-D66 -> 0
B68: =Categorias!B64 -> COMUNICACIÓN | C68: =SUM(C69:C75) -> 1300 | D68: =SUM(D69:D75) -> 0 | E68: =SUM(E69:E75) -> 1300 | H68: 1 | I68: 2 | J68: 3 | K68: 4 | L68: 5 | M68: 6 | N68: 7 | O68: 8 | P68: 9 | Q68: 10 | R68: 11 | S68: 12 | T68: 13 | U68: 14 | V68: 15 | W68: 16 | X68: 17 | Y68: 18 | Z68: 19 | AA68: 20 | AB68: 21 | AC68: 22 | AD68: 23 | AE68: 24 | AF68: 25 | AG68: 26 | AH68: 27 | AI68: 28 | AJ68: 29 | AK68: 30 | AL68: 31
B69: =Categorias!B65 -> Cel. Claudia | C69: 300 | D69: =SUM(Enero!$H69:$AL69) -> 0 | E69: =C69-D69 -> 300
B70: =Categorias!B66 -> Cel. Carlos | C70: 700 | D70: =SUM(Enero!$H70:$AL70) -> 0 | E70: =C70-D70 -> 700
B71: =Categorias!B67 -> Cel.Kary | C71: 300 | D71: =SUM(Enero!$H71:$AL71) -> 0 | E71: =C71-D71 -> 300
B72: =Categorias!B68 -> - | C72: 0 | D72: =SUM(Enero!$H72:$AL72) -> 0 | E72: =C72-D72 -> 0
B73: =Categorias!B69 -> - | C73: 0 | D73: =SUM(Enero!$H73:$AL73) -> 0 | E73: =C73-D73 -> 0
B74: =Categorias!B70 -> - | C74: 0 | D74: =SUM(Enero!$H74:$AL74) -> 0 | E74: =C74-D74 -> 0
B75: =Categorias!B73 -> - | C75: 0 | D75: =SUM(Enero!$H75:$AL75) -> 0 | E75: =C75-D75 -> 0
B77: =Categorias!B75 -> TRANSPORTE | C77: =SUM(C78:C86) -> 4700 | D77: =SUM(D78:D86) -> 7578.83 | E77: =SUM(E78:E86) -> -2878.83 | H77: 1 | I77: 2 | J77: 3 | K77: 4 | L77: 5 | M77: 6 | N77: 7 | O77: 8 | P77: 9 | Q77: 10 | R77: 11 | S77: 12 | T77: 13 | U77: 14 | V77: 15 | W77: 16 | X77: 17 | Y77: 18 | Z77: 19 | AA77: 20 | AB77: 21 | AC77: 22 | AD77: 23 | AE77: 24 | AF77: 25 | AG77: 26 | AH77: 27 | AI77: 28 | AJ77: 29 | AK77: 30 | AL77: 31
B78: =Categorias!B76 -> Combustible Fusion | C78: 2000 | D78: =SUM(Enero!$H78:$AL78) -> 3277.83 | E78: =C78-D78 -> -1277.83 | J78: 1151.83 | M78: 500 | P78: 716 | U78: 910
B79: =Categorias!B77 -> Seguro Fusion | C79: 700 | D79: =SUM(Enero!$H79:$AL79) -> 0 | E79: =C79-D79 -> 700
B80: =Categorias!B78 -> Mantenimiento Fusion | C80: 0 | D80: =SUM(Enero!$H80:$AL80) -> 0 | E80: =C80-D80 -> 0
B81: =Categorias!B79 -> Derecho vehicular Fusion | C81: 1200 | D81: =SUM(Enero!$H81:$AL81) -> 0 | E81: =C81-D81 -> 1200
B82: =Categorias!B80 -> Casetas | C82: 800 | D82: =SUM(Enero!$H82:$AL82) -> 303 | E82: =C82-D82 -> 497 | O82: 101 | P82: 202
B83: =Categorias!B81 -> ADO | C83: 0 | D83: =SUM(Enero!$H83:$AL83) -> 3630 | E83: =C83-D83 -> -3630 | O83: 320 | P83: 3310
B84: =Categorias!B82 -> - | C84: 0 | D84: =SUM(Enero!$H84:$AL84) -> 368 | E84: =C84-D84 -> -368 | V84: 288 | Y84: 80
B85: =Categorias!B83 -> - | C85: 0 | D85: =SUM(Enero!$H85:$AL85) -> 0 | E85: =C85-D85 -> 0
B86: =Categorias!B84 -> - | C86: 0 | D86: =SUM(Enero!$H86:$AL86) -> 0 | E86: =C86-D86 -> 0
B88: =Categorias!B86 -> HIGIENE | C88: =SUM(C89:C95) -> 400 | D88: =SUM(D89:D95) -> 1490 | E88: =SUM(E89:E95) -> -1090 | H88: 1 | I88: 2 | J88: 3 | K88: 4 | L88: 5 | M88: 6 | N88: 7 | O88: 8 | P88: 9 | Q88: 10 | R88: 11 | S88: 12 | T88: 13 | U88: 14 | V88: 15 | W88: 16 | X88: 17 | Y88: 18 | Z88: 19 | AA88: 20 | AB88: 21 | AC88: 22 | AD88: 23 | AE88: 24 | AF88: 25 | AG88: 26 | AH88: 27 | AI88: 28 | AJ88: 29 | AK88: 30 | AL88: 31
B89: =Categorias!B87 -> Cosmeticos | C89: 0 | D89: =SUM(Enero!$H89:$AL89) -> 0 | E89: =C89-D89 -> 0
B90: =Categorias!B88 -> Peluquería / S. Belleza | C90: 200 | D90: =SUM(Enero!$H90:$AL90) -> 0 | E90: =C90-D90 -> 200
B91: =Categorias!B89 -> Lavanderia | C91: 0 | D91: =SUM(Enero!$H91:$AL91) -> 150 | E91: =C91-D91 -> -150 | AA91: 150
B92: =Categorias!B90 -> Productos de limpieza | C92: 200 | D92: =SUM(Enero!$H92:$AL92) -> 1340 | E92: =C92-D92 -> -1140 | L92: 140 | Q92: 590 | X92: 494 | Y92: 16 | AA92: 100
B93: =Categorias!B91 -> Otros | C93: 0 | D93: =SUM(Enero!$H93:$AL93) -> 0 | E93: =C93-D93 -> 0
B94: =Categorias!B92 -> - | C94: 0 | D94: =SUM(Enero!$H94:$AL94) -> 0 | E94: =C94-D94 -> 0
B95: =Categorias!B93 -> - | C95: 0 | D95: =SUM(Enero!$H95:$AL95) -> 0 | E95: =C95-D95 -> 0
B97: =Categorias!B95 -> NIÑOS | C97: =SUM(C98:C105) -> 3600 | D97: =SUM(D98:D105) -> 0 | E97: =SUM(E98:E105) -> 3600 | H97: 1 | I97: 2 | J97: 3 | K97: 4 | L97: 5 | M97: 6 | N97: 7 | O97: 8 | P97: 9 | Q97: 10 | R97: 11 | S97: 12 | T97: 13 | U97: 14 | V97: 15 | W97: 16 | X97: 17 | Y97: 18 | Z97: 19 | AA97: 20 | AB97: 21 | AC97: 22 | AD97: 23 | AE97: 24 | AF97: 25 | AG97: 26 | AH97: 27 | AI97: 28 | AJ97: 29 | AK97: 30 | AL97: 31
B98: =Categorias!B96 -> Jugetes/juegos | C98: 2000 | D98: =SUM(Enero!$H98:$AL98) -> 0 | E98: =C98-D98 -> 2000
B99: =Categorias!B97 -> - | C99: 1600 | D99: =SUM(Enero!$H99:$AL99) -> 0 | E99: =C99-D99 -> 1600
B100: =Categorias!B98 -> - | C100: 0 | D100: =SUM(Enero!$H100:$AL100) -> 0 | E100: =C100-D100 -> 0
B101: =Categorias!B99 -> - | C101: 0 | D101: =SUM(Enero!$H101:$AL101) -> 0 | E101: =C101-D101 -> 0
B102: =Categorias!B100 -> - | C102: 0 | D102: =SUM(Enero!$H102:$AL102) -> 0 | E102: =C102-D102 -> 0
B103: =Categorias!B101 -> - | C103: 0 | D103: =SUM(Enero!$H103:$AL103) -> 0 | E103: =C103-D103 -> 0
B104: =Categorias!B102 -> - | C104: 0 | D104: =SUM(Enero!$H104:$AL104) -> 0 | E104: =C104-D104 -> 0
B105: =Categorias!B103 -> - | C105: 0 | D105: =SUM(Enero!$H105:$AL105) -> 0 | E105: =C105-D105 -> 0
B107: =Categorias!B105 -> DESARROLLO PERSONAL | C107: =SUM(C108:C113) -> 3950 | D107: =SUM(D108:D113) -> 3190 | E107: =SUM(E108:E113) -> 760 | H107: 1 | I107: 2 | J107: 3 | K107: 4 | L107: 5 | M107: 6 | N107: 7 | O107: 8 | P107: 9 | Q107: 10 | R107: 11 | S107: 12 | T107: 13 | U107: 14 | V107: 15 | W107: 16 | X107: 17 | Y107: 18 | Z107: 19 | AA107: 20 | AB107: 21 | AC107: 22 | AD107: 23 | AE107: 24 | AF107: 25 | AG107: 26 | AH107: 27 | AI107: 28 | AJ107: 29 | AK107: 30 | AL107: 31
B108: =Categorias!B106 -> Libros | C108: 0 | D108: =SUM(Enero!$H108:$AL108) -> 190 | E108: =C108-D108 -> -190 | AE108: 190
B109: =Categorias!B107 -> Platzi | C109: 0 | D109: =SUM(Enero!$H109:$AL109) -> 0 | E109: =C109-D109 -> 0
B110: =Categorias!B108 -> Papeleria | C110: 0 | D110: =SUM(Enero!$H110:$AL110) -> 0 | E110: =C110-D110 -> 0
B111: =Categorias!B109 -> Inglés Thiago | C111: 1500 | D111: =SUM(Enero!$H111:$AL111) -> 0 | E111: =C111-D111 -> 1500
B112: =Categorias!B110 -> Arte Thiago | C112: 450 | D112: =SUM(Enero!$H112:$AL112) -> 0 | E112: =C112-D112 -> 450
B113: Tec Kary | C113: 2000 | D113: =SUM(Enero!$H113:$AL113) -> 3000 | E113: =C113-D113 -> -1000 | AA113: 3000
B115: =Categorias!B113 -> DIVERSIÓN | C115: =SUM(C116:C124) -> 750 | D115: =SUM(D116:D124) -> 255 | E115: =SUM(E116:E124) -> 495 | H115: 1 | I115: 2 | J115: 3 | K115: 4 | L115: 5 | M115: 6 | N115: 7 | O115: 8 | P115: 9 | Q115: 10 | R115: 11 | S115: 12 | T115: 13 | U115: 14 | V115: 15 | W115: 16 | X115: 17 | Y115: 18 | Z115: 19 | AA115: 20 | AB115: 21 | AC115: 22 | AD115: 23 | AE115: 24 | AF115: 25 | AG115: 26 | AH115: 27 | AI115: 28 | AJ115: 29 | AK115: 30 | AL115: 31
B116: =Categorias!B114 -> Cine/teatro | C116: 0 | D116: =SUM(Enero!$H116:$AL116) -> 0 | E116: =C116-D116 -> 0
B117: =Categorias!B115 -> Gimnasio/piscina | C117: 600 | D117: =SUM(Enero!$H117:$AL117) -> 105 | E117: =C117-D117 -> 495 | Y117: 105
...

Sheet Febrero
B2: Presupuesto | C2: 44958
C4: Para crear un presupuesto: - A principios de este mes, rellene los campos en amarillo, despues de forma regular registre los gastos de cada dia en la tabla a la derecha - Todos los otros datos se convertirá automáticamente
C5: Fuente: | D5: =HYPERLINK("http://www.aprendizfinanciero.com/","http://www.aprendizfinanciero.com") -> http://www.aprendizfinanciero.com
B6: Ingresos
B8: Categoría | C8: Ingresos previstos | D8: Ingresos reales | E8: Diferencia | F8: Notas
B9: SUMA | C9: =C11 -> 44000 | D9: =D11 -> 0 | E9: =E11 -> -44000
B11: =Categorias!B11 -> INGRESOS TOTALES | C11: =SUM(C12:C20) -> 44000 | D11: =SUM(D12:D20) -> 0 | E11: =SUM(E12:E20) -> -44000 | H11: 1 | I11: 2 | J11: 3 | K11: 4 | L11: 5 | M11: 6 | N11: 7 | O11: 8 | P11: 9 | Q11: 10 | R11: 11 | S11: 12 | T11: 13 | U11: 14 | V11: 15 | W11: 16 | X11: 17 | Y11: 18 | Z11: 19 | AA11: 20 | AB11: 21 | AC11: 22 | AD11: 23 | AE11: 24 | AF11: 25 | AG11: 26 | AH11: 27 | AI11: 28 | AJ11: 29 | AK11: 30 | AL11: 31
B12: =Categorias!B12 -> Nomina | C12: 44000 | D12: =SUM(Febrero!$H12:$AL12) -> 0 | E12: =D12-C12 -> -44000
B13: =Categorias!B13 -> Aguinaldo | C13: 0 | D13: =SUM(Febrero!$H13:$AL13) -> 0 | E13: =D13-C13 -> 0
B14: =Categorias!B14 -> Fondo de ahorro | C14: 0 | D14: =SUM(Febrero!$H14:$AL14) -> 0 | E14: =D14-C14 -> 0
B15: =Categorias!B15 -> Vales despensa | C15: 0 | D15: =SUM(Febrero!$H15:$AL15) -> 0 | E15: =D15-C15 -> 0
B16: =Categorias!B16 -> Vales comedor | C16: 0 | D16: =SUM(Febrero!$H16:$AL16) -> 0 | E16: =D16-C16 -> 0
B17: =Categorias!B17 -> - | C17: 0 | D17: =SUM(Febrero!$H17:$AL17) -> 0 | E17: =D17-C17 -> 0
B18: =Categorias!B18 -> - | C18: 0 | D18: =SUM(Febrero!$H18:$AL18) -> 0 | E18: =D18-C18 -> 0
B19: =Categorias!B19 -> - | C19: 0 | D19: =SUM(Febrero!$H19:$AL19) -> 0 | E19: =D19-C19 -> 0
B20: =Categorias!B20 -> - | C20: 0 | D20: =SUM(Febrero!$H20:$AL20) -> 0 | E20: =D20-C20 -> 0
B23: Gastos | H23: Registre de gastos diarios
B25: Categoría | C25: Gastos previstos | D25: Gastos reales | E25: Diferencia | F25: Notas | H25: Los campos siguientes son para un registro diario de gastos en cada categoría.
B26: SUMA | C26: =C28+C37+C45+C58+C68+C77+C88+C97+C107+C115+C126+C136+C146+C158 -> 29298 | D26: =D28+D37+D45+D58+D68+D77+D88+D97+D107+D115+D126+D136+D146+D158 -> 4741.72 | E26: =E28+E37+E45+E58+E68+E77+E88+E97+E107+E115+E126+E136+E146+E158 -> 24556.28 | H26: Si quieres incluir mas gastos en una celda, por el mismo dia, ingresa "=" y sigue la ecuación, por ejemplo:. = 25 + 20.5
B28: =Categorias!B24 -> ALIMENTOS Y BEBIDAS | C28: =SUM(C29:C35) -> 2000 | D28: =SUM(D29:D35) -> 1034 | E28: =SUM(E29:E35) -> 966 | H28: 1 | I28: 2 | J28: 3 | K28: 4 | L28: 5 | M28: 6 | N28: 7 | O28: 8 | P28: 9 | Q28: 10 | R28: 11 | S28: 12 | T28: 13 | U28: 14 | V28: 15 | W28: 16 | X28: 17 | Y28: 18 | Z28: 19 | AA28: 20 | AB28: 21 | AC28: 22 | AD28: 23 | AE28: 24 | AF28: 25 | AG28: 26 | AH28: 27 | AI28: 28 | AJ28: 29 | AK28: 30 | AL28: 31
B29: =Categorias!B25 -> Restaurantes | C29: 500 | D29: =SUM(Febrero!$H29:$AL29) -> 374 | E29: =C29-D29 -> 126 | L29: 374
B30: =Categorias!B26 -> Comida Carlos | C30: 500 | D30: =SUM(Febrero!$H30:$AL30) -> 370 | E30: =C30-D30 -> 130 | T30: 40 | U30: 280 | V30: 50
B31: =Categorias!B27 -> - | C31: 500 | D31: =SUM(Febrero!$H31:$AL31) -> 0 | E31: =C31-D31 -> 500
B32: =Categorias!B28 -> - | C32: 500 | D32: =SUM(Febrero!$H32:$AL32) -> 0 | E32: =C32-D32 -> 500
B33: =Categorias!B29 -> - | C33: 0 | D33: =SUM(Febrero!$H33:$AL33) -> 290 | E33: =C33-D33 -> -290 | X33: 150 | Y33: 100 | Z33: 40
B34: =Categorias!B30 -> - | C34: 0 | D34: =SUM(Febrero!$H34:$AL34) -> 0 | E34: =C34-D34 -> 0
B35: =Categorias!B31 -> - | C35: 0 | D35: =SUM(Febrero!$H35:$AL35) -> 0 | E35: =C35-D35 -> 0
B37: =Categorias!B33 -> SALUD | C37: =SUM(C38:C43) -> 6000 | D37: =SUM(D38:D43) -> 428.4 | E37: =SUM(E38:E43) -> 5571.6 | H37: 1 | I37: 2 | J37: 3 | K37: 4 | L37: 5 | M37: 6 | N37: 7 | O37: 8 | P37: 9 | Q37: 10 | R37: 11 | S37: 12 | T37: 13 | U37: 14 | V37: 15 | W37: 16 | X37: 17 | Y37: 18 | Z37: 19 | AA37: 20 | AB37: 21 | AC37: 22 | AD37: 23 | AE37: 24 | AF37: 25 | AG37: 26 | AH37: 27 | AI37: 28 | AJ37: 29 | AK37: 30 | AL37: 31
B38: =Categorias!B34 -> Gastos en médicos | C38: 5000 | D38: =SUM(Febrero!$H38:$AL38) -> 0 | E38: =C38-D38 -> 5000
B39: =Categorias!B35 -> Medicamentos | C39: 1000 | D39: =SUM(Febrero!$H39:$AL39) -> 428.4 | E39: =C39-D39 -> 571.6 | L39: 428.4
B40: =Categorias!B36 -> Dentista Kary | C40: 0 | D40: =SUM(Febrero!$H40:$AL40) -> 0 | E40: =C40-D40 -> 0
B41: =Categorias!B37 -> Dentista Thiago | C41: 0 | D41: =SUM(Febrero!$H41:$AL41) -> 0 | E41: =C41-D41 -> 0
B42: =Categorias!B38 -> - | C42: 0 | D42: =SUM(Febrero!$H42:$AL42) -> 0 | E42: =C42-D42 -> 0
B43: =Categorias!B39 -> - | C43: 0 | D43: =SUM(Febrero!$H43:$AL43) -> 0 | E43: =C43-D43 -> 0
B45: =Categorias!B41 -> CASA | C45: =SUM(C46:C56) -> 2900 | D45: =SUM(D46:D56) -> 40 | E45: =SUM(E46:E56) -> 2860 | H45: 1 | I45: 2 | J45: 3 | K45: 4 | L45: 5 | M45: 6 | N45: 7 | O45: 8 | P45: 9 | Q45: 10 | R45: 11 | S45: 12 | T45: 13 | U45: 14 | V45: 15 | W45: 16 | X45: 17 | Y45: 18 | Z45: 19 | AA45: 20 | AB45: 21 | AC45: 22 | AD45: 23 | AE45: 24 | AF45: 25 | AG45: 26 | AH45: 27 | AI45: 28 | AJ45: 29 | AK45: 30 | AL45: 31
B46: =Categorias!B42 -> Reparación | C46: 500 | D46: =SUM(Febrero!$H46:$AL46) -> 40 | E46: =C46-D46 -> 460 | S46: 40
B47: =Categorias!B43 -> Electricidad | C47: 0 | D47: =SUM(Febrero!$H47:$AL47) -> 0 | E47: =C47-D47 -> 0
B48: =Categorias!B44 -> Gas | C48: 200 | D48: =SUM(Febrero!$H48:$AL48) -> 0 | E48: =C48-D48 -> 200
B49: =Categorias!B45 -> Casa Claudia | C49: 0 | D49: =SUM(Febrero!$H49:$AL49) -> 0 | E49: =C49-D49 -> 0
B50: =Categorias!B46 -> Muebles/electrodomésticos | C50: 0 | D50: =SUM(Febrero!$H50:$AL50) -> 0 | E50: =C50-D50 -> 0
B51: =Categorias!B47 -> Predial | C51: 0 | D51: =SUM(Febrero!$H51:$AL51) -> 0 | E51: =C51-D51 -> 0
B52: =Categorias!B48 -> Renta Cuarto | C52: 2200 | D52: =SUM(Febrero!$H52:$AL52) -> 0 | E52: =C52-D52 -> 2200
B53: =Categorias!B49 -> - | C53: 0 | D53: =SUM(Febrero!$H53:$AL53) -> 0 | E53: =C53-D53 -> 0
B54: =Categorias!B50 -> - | C54: 0 | D54: =SUM(Febrero!$H54:$AL54) -> 0 | E54: =C54-D54 -> 0
B55: =Categorias!B51 -> - | C55: 0 | D55: =SUM(Febrero!$H55:$AL55) -> 0 | E55: =C55-D55 -> 0
B56: =Categorias!B52 -> - | C56: 0 | D56: =SUM(Febrero!$H56:$AL56) -> 0 | E56: =C56-D56 -> 0
B58: =Categorias!B54 -> ROPA Y CALZADO | C58: =SUM(C59:C66) -> 0 | D58: =SUM(D59:D66) -> 0 | E58: =SUM(E59:E66) -> 0 | H58: 1 | I58: 2 | J58: 3 | K58: 4 | L58: 5 | M58: 6 | N58: 7 | O58: 8 | P58: 9 | Q58: 10 | R58: 11 | S58: 12 | T58: 13 | U58: 14 | V58: 15 | W58: 16 | X58: 17 | Y58: 18 | Z58: 19 | AA58: 20 | AB58: 21 | AC58: 22 | AD58: 23 | AE58: 24 | AF58: 25 | AG58: 26 | AH58: 27 | AI58: 28 | AJ58: 29 | AK58: 30 | AL58: 31
B59: =Categorias!B55 -> Ropa de adultos | C59: 0 | D59: =SUM(Febrero!$H59:$AL59) -> 0 | E59: =C59-D59 -> 0
B60: =Categorias!B56 -> Ropa de niños | C60: 0 | D60: =SUM(Febrero!$H60:$AL60) -> 0 | E60: =C60-D60 -> 0
B61: =Categorias!B57 -> Calzado | C61: 0 | D61: =SUM(Febrero!$H61:$AL61) -> 0 | E61: =C61-D61 -> 0
B62: =Categorias!B58 -> Acessorios | C62: 0 | D62: =SUM(Febrero!$H62:$AL62) -> 0 | E62: =C62-D62 -> 0
B63: =Categorias!B59 -> Joyería | C63: 0 | D63: =SUM(Febrero!$H63:$AL63) -> 0 | E63: =C63-D63 -> 0
B64: =Categorias!B60 -> Otros | C64: 0 | D64: =SUM(Febrero!$H64:$AL64) -> 0 | E64: =C64-D64 -> 0
B65: =Categorias!B61 -> - | C65: 0 | D65: =SUM(Febrero!$H65:$AL65) -> 0 | E65: =C65-D65 -> 0
B66: =Categorias!B62 -> - | C66: 0 | D66: =SUM(Febrero!$H66:$AL66) -> 0 | E66: =C66-D66 -> 0
B68: =Categorias!B64 -> COMUNICACIÓN | C68: =SUM(C69:C75) -> 1278 | D68: =SUM(D69:D75) -> 0 | E68: =SUM(E69:E75) -> 1278 | H68: 1 | I68: 2 | J68: 3 | K68: 4 | L68: 5 | M68: 6 | N68: 7 | O68: 8 | P68: 9 | Q68: 10 | R68: 11 | S68: 12 | T68: 13 | U68: 14 | V68: 15 | W68: 16 | X68: 17 | Y68: 18 | Z68: 19 | AA68: 20 | AB68: 21 | AC68: 22 | AD68: 23 | AE68: 24 | AF68: 25 | AG68: 26 | AH68: 27 | AI68: 28 | AJ68: 29 | AK68: 30 | AL68: 31
B69: =Categorias!B65 -> Cel. Claudia | C69: 300 | D69: =SUM(Febrero!$H69:$AL69) -> 0 | E69: =C69-D69 -> 300
B70: =Categorias!B66 -> Cel. Carlos | C70: 250 | D70: =SUM(Febrero!$H70:$AL70) -> 0 | E70: =C70-D70 -> 250
B71: =Categorias!B67 -> Cel.Kary | C71: 200 | D71: =SUM(Febrero!$H71:$AL71) -> 0 | E71: =C71-D71 -> 200
B72: =Categorias!B68 -> - | C72: 528 | D72: =SUM(Febrero!$H72:$AL72) -> 0 | E72: =C72-D72 -> 528
B73: =Categorias!B69 -> - | C73: 0 | D73: =SUM(Febrero!$H73:$AL73) -> 0 | E73: =C73-D73 -> 0
B74: =Categorias!B70 -> - | C74: 0 | D74: =SUM(Febrero!$H74:$AL74) -> 0 | E74: =C74-D74 -> 0
B75: =Categorias!B73 -> - | C75: 0 | D75: =SUM(Febrero!$H75:$AL75) -> 0 | E75: =C75-D75 -> 0
B77: =Categorias!B75 -> TRANSPORTE | C77: =SUM(C78:C86) -> 4000 | D77: =SUM(D78:D86) -> 2439.32 | E77: =SUM(E78:E86) -> 1560.68 | H77: 1 | I77: 2 | J77: 3 | K77: 4 | L77: 5 | M77: 6 | N77: 7 | O77: 8 | P77: 9 | Q77: 10 | R77: 11 | S77: 12 | T77: 13 | U77: 14 | V77: 15 | W77: 16 | X77: 17 | Y77: 18 | Z77: 19 | AA77: 20 | AB77: 21 | AC77: 22 | AD77: 23 | AE77: 24 | AF77: 25 | AG77: 26 | AH77: 27 | AI77: 28 | AJ77: 29 | AK77: 30 | AL77: 31
B78: =Categorias!B76 -> Combustible Fusion | C78: 2000 | D78: =SUM(Febrero!$H78:$AL78) -> 1824.32 | E78: =C78-D78 -> 175.68 | I78: 754.4 | V78: 1069.92
B79: =Categorias!B77 -> Seguro Fusion | C79: 2000 | D79: =SUM(Febrero!$H79:$AL79) -> 0 | E79: =C79-D79 -> 2000
B80: =Categorias!B78 -> Mantenimiento Fusion | C80: 0 | D80: =SUM(Febrero!$H80:$AL80) -> 0 | E80: =C80-D80 -> 0
B81: =Categorias!B79 -> Derecho vehicular Fusion | C81: 0 | D81: =SUM(Febrero!$H81:$AL81) -> 0 | E81: =C81-D81 -> 0
B82: =Categorias!B80 -> Casetas | C82: 0 | D82: =SUM(Febrero!$H82:$AL82) -> 615 | E82: =C82-D82 -> -615 | J82: 123 | N82: 123 | Q82: 123 | U82: 123 | X82: 123
B83: =Categorias!B81 -> ADO | C83: 0 | D83: =SUM(Febrero!$H83:$AL83) -> 0 | E83: =C83-D83 -> 0
B84: =Categorias!B82 -> - | C84: 0 | D84: =SUM(Febrero!$H84:$AL84) -> 0 | E84: =C84-D84 -> 0
B85: =Categorias!B83 -> - | C85: 0 | D85: =SUM(Febrero!$H85:$AL85) -> 0 | E85: =C85-D85 -> 0
B86: =Categorias!B84 -> - | C86: 0 | D86: =SUM(Febrero!$H86:$AL86) -> 0 | E86: =C86-D86 -> 0
B88: =Categorias!B86 -> HIGIENE | C88: =SUM(C89:C95) -> 300 | D88: =SUM(D89:D95) -> 0 | E88: =SUM(E89:E95) -> 300 | H88: 1 | I88: 2 | J88: 3 | K88: 4 | L88: 5 | M88: 6 | N88: 7 | O88: 8 | P88: 9 | Q88: 10 | R88: 11 | S88: 12 | T88: 13 | U88: 14 | V88: 15 | W88: 16 | X88: 17 | Y88: 18 | Z88: 19 | AA88: 20 | AB88: 21 | AC88: 22 | AD88: 23 | AE88: 24 | AF88: 25 | AG88: 26 | AH88: 27 | AI88: 28 | AJ88: 29 | AK88: 30 | AL88: 31
B89: =Categorias!B87 -> Cosmeticos | C89: 0 | D89: =SUM(Febrero!$H89:$AL89) -> 0 | E89: =C89-D89 -> 0
B90: =Categorias!B88 -> Peluquería / S. Belleza | C90: 300 | D90: =SUM(Febrero!$H90:$AL90) -> 0 | E90: =C90-D90 -> 300
B91: =Categorias!B89 -> Lavanderia | C91: 0 | D91: =SUM(Febrero!$H91:$AL91) -> 0 | E91: =C91-D91 -> 0
B92: =Categorias!B90 -> Productos de limpieza | C92: 0 | D92: =SUM(Febrero!$H92:$AL92) -> 0 | E92: =C92-D92 -> 0
B93: =Categorias!B91 -> Otros | C93: 0 | D93: =SUM(Febrero!$H93:$AL93) -> 0 | E93: =C93-D93 -> 0
B94: =Categorias!B92 -> - | C94: 0 | D94: =SUM(Febrero!$H94:$AL94) -> 0 | E94: =C94-D94 -> 0
B95: =Categorias!B93 -> - | C95: 0 | D95: =SUM(Febrero!$H95:$AL95) -> 0 | E95: =C95-D95 -> 0
B97: =Categorias!B95 -> NIÑOS | C97: =SUM(C98:C105) -> 1600 | D97: =SUM(D98:D105) -> 800 | E97: =SUM(E98:E105) -> 800 | H97: 1 | I97: 2 | J97: 3 | K97: 4 | L97: 5 | M97: 6 | N97: 7 | O97: 8 | P97: 9 | Q97: 10 | R97: 11 | S97: 12 | T97: 13 | U97: 14 | V97: 15 | W97: 16 | X97: 17 | Y97: 18 | Z97: 19 | AA97: 20 | AB97: 21 | AC97: 22 | AD97: 23 | AE97: 24 | AF97: 25 | AG97: 26 | AH97: 27 | AI97: 28 | AJ97: 29 | AK97: 30 | AL97: 31
B98: =Categorias!B96 -> Jugetes/juegos | C98: 0 | D98: =SUM(Febrero!$H98:$AL98) -> 0 | E98: =C98-D98 -> 0
B99: =Categorias!B97 -> - | C99: 1600 | D99: =SUM(Febrero!$H99:$AL99) -> 800 | E99: =C99-D99 -> 800 | N99: 400 | U99: 400
B100: =Categorias!B98 -> - | C100: 0 | D100: =SUM(Febrero!$H100:$AL100) -> 0 | E100: =C100-D100 -> 0
B101: =Categorias!B99 -> - | C101: 0 | D101: =SUM(Febrero!$H101:$AL101) -> 0 | E101: =C101-D101 -> 0
B102: =Categorias!B100 -> - | C102: 0 | D102: =SUM(Febrero!$H102:$AL102) -> 0 | E102: =C102-D102 -> 0
B103: =Categorias!B101 -> - | C103: 0 | D103: =SUM(Febrero!$H103:$AL103) -> 0 | E103: =C103-D103 -> 0
B104: =Categorias!B102 -> - | C104: 0 | D104: =SUM(Febrero!$H104:$AL104) -> 0 | E104: =C104-D104 -> 0
B105: =Categorias!B103 -> - | C105: 0 | D105: =SUM(Febrero!$H105:$AL105) -> 0 | E105: =C105-D105 -> 0
B107: =Categorias!B105 -> DESARROLLO PERSONAL | C107: =SUM(C108:C113) -> 0 | D107: =SUM(D108:D113) -> 0 | E107: =SUM(E108:E113) -> 0 | H107: 1 | I107: 2 | J107: 3 | K107: 4 | L107: 5 | M107: 6 | N107: 7 | O107: 8 | P107: 9 | Q107: 10 | R107: 11 | S107: 12 | T107: 13 | U107: 14 | V107: 15 | W107: 16 | X107: 17 | Y107: 18 | Z107: 19 | AA107: 20 | AB107: 21 | AC107: 22 | AD107: 23 | AE107: 24 | AF107: 25 | AG107: 26 | AH107: 27 | AI107: 28 | AJ107: 29 | AK107: 30 | AL107: 31
B108: =Categorias!B106 -> Libros | C108: 0 | D108: =SUM(Febrero!$H108:$AL108) -> 0 | E108: =C108-D108 -> 0
B109: =Categorias!B107 -> Platzi | C109: 0 | D109: =SUM(Febrero!$H109:$AL109) -> 0 | E109: =C109-D109 -> 0
B110: =Categorias!B108 -> Papeleria | C110: 0 | D110: =SUM(Febrero!$H110:$AL110) -> 0 | E110: =C110-D110 -> 0
B111: =Categorias!B109 -> Inglés Thiago | C111: 0 | D111: =SUM(Febrero!$H111:$AL111) -> 0 | E111: =C111-D111 -> 0
B112: =Categorias!B110 -> Arte Thiago | C112: 0 | D112: =SUM(Febrero!$H112:$AL112) -> 0 | E112: =C112-D112 -> 0
B113: =Categorias!B111 -> Escuela kary | C113: 0 | D113: =SUM(Febrero!$H113:$AL113) -> 0 | E113: =C113-D113 -> 0
B115: =Categorias!B113 -> DIVERSIÓN | C115: =SUM(C116:C124) -> 500 | D115: =SUM(D116:D124) -> 0 | E115: =SUM(E116:E124) -> 500 | H115: 1 | I115: 2 | J115: 3 | K115: 4 | L115: 5 | M115: 6 | N115: 7 | O115: 8 | P115: 9 | Q115: 10 | R115: 11 | S115: 12 | T115: 13 | U115: 14 | V115: 15 | W115: 16 | X115: 17 | Y115: 18 | Z115: 19 | AA115: 20 | AB115: 21 | AC115: 22 | AD115: 23 | AE115: 24 | AF115: 25 | AG115: 26 | AH115: 27 | AI115: 28 | AJ115: 29 | AK115: 30 | AL115: 31
B116: =Categorias!B114 -> Cine/teatro | C116: 0 | D116: =SUM(Febrero!$H116:$AL116) -> 0 | E116: =C116-D116 -> 0
B117: =Categorias!B115 -> Gimnasio/piscina | C117: 500 | D117: =SUM(Febrero!$H117:$AL117) -> 0 | E117: =C117-D117 -> 500
...

Sheet Marzo
B2: Presupuesto | C2: 44256
C4: Para crear un presupuesto: - A principios de este mes, rellene los campos en amarillo, despues de forma regular registre los gastos de cada dia en la tabla a la derecha - Todos los otros datos se convertirá automáticamente
C5: Fuente: | D5: =HYPERLINK("http://www.aprendizfinanciero.com/","http://www.aprendizfinanciero.com") -> http://www.aprendizfinanciero.com
B6: Ingresos
B8: Categoría | C8: Ingresos previstos | D8: Ingresos reales | E8: Diferencia | F8: Notas
B9: SUMA | C9: =C11 -> 62000 | D9: =D11 -> 51000 | E9: =E11 -> -11000
B11: =Categorias!B11 -> INGRESOS TOTALES | C11: =SUM(C12:C20) -> 62000 | D11: =SUM(D12:D20) -> 51000 | E11: =SUM(E12:E20) -> -11000 | H11: 1 | I11: 2 | J11: 3 | K11: 4 | L11: 5 | M11: 6 | N11: 7 | O11: 8 | P11: 9 | Q11: 10 | R11: 11 | S11: 12 | T11: 13 | U11: 14 | V11: 15 | W11: 16 | X11: 17 | Y11: 18 | Z11: 19 | AA11: 20 | AB11: 21 | AC11: 22 | AD11: 23 | AE11: 24 | AF11: 25 | AG11: 26 | AH11: 27 | AI11: 28 | AJ11: 29 | AK11: 30 | AL11: 31
B12: =Categorias!B12 -> Nomina | C12: 52000 | D12: =SUM(Marzo!$H12:$AL12) -> 51000 | E12: =D12-C12 -> -1000 | V12: 21000 | AL12: 30000
B13: =Categorias!B13 -> Aguinaldo | C13: 10000 | D13: =SUM(Marzo!$H13:$AL13) -> 0 | E13: =D13-C13 -> -10000
B14: =Categorias!B14 -> Fondo de ahorro | C14: 0 | D14: =SUM(Marzo!$H14:$AL14) -> 0 | E14: =D14-C14 -> 0
B15: =Categorias!B15 -> Vales despensa | C15: 0 | D15: =SUM(Marzo!$H15:$AL15) -> 0 | E15: =D15-C15 -> 0
B16: =Categorias!B16 -> Vales comedor | C16: 0 | D16: =SUM(Marzo!$H16:$AL16) -> 0 | E16: =D16-C16 -> 0
B17: =Categorias!B17 -> - | C17: 0 | D17: =SUM(Marzo!$H17:$AL17) -> 0 | E17: =D17-C17 -> 0
B18: =Categorias!B18 -> - | C18: 0 | D18: =SUM(Marzo!$H18:$AL18) -> 0 | E18: =D18-C18 -> 0
B19: =Categorias!B19 -> - | C19: 0 | D19: =SUM(Marzo!$H19:$AL19) -> 0 | E19: =D19-C19 -> 0
B20: =Categorias!B20 -> - | C20: 0 | D20: =SUM(Marzo!$H20:$AL20) -> 0 | E20: =D20-C20 -> 0
B23: Gastos | H23: Registre de gastos diarios
B25: Categoría | C25: Gastos previstos | D25: Gastos reales | E25: Diferencia | F25: Notas | H25: Los campos siguientes son para un registro diario de gastos en cada categoría.
B26: SUMA | C26: =C28+C37+C45+C58+C68+C77+C88+C97+C107+C115+C126+C136+C146+C158 -> 27988 | D26: =D28+D37+D45+D58+D68+D77+D88+D97+D107+D115+D126+D136+D146+D158 -> 28329 | E26: =E28+E37+E45+E58+E68+E77+E88+E97+E107+E115+E126+E136+E146+E158 -> -341 | H26: Si quieres incluir mas gastos en una celda, por el mismo dia, ingresa "=" y sigue la ecuación, por ejemplo:. = 25 + 20.5
B28: =Categorias!B24 -> ALIMENTOS Y BEBIDAS | C28: =SUM(C29:C35) -> 3000 | D28: =SUM(D29:D35) -> 4484 | E28: =SUM(E29:E35) -> -1484 | H28: 1 | I28: 2 | J28: 3 | K28: 4 | L28: 5 | M28: 6 | N28: 7 | O28: 8 | P28: 9 | Q28: 10 | R28: 11 | S28: 12 | T28: 13 | U28: 14 | V28: 15 | W28: 16 | X28: 17 | Y28: 18 | Z28: 19 | AA28: 20 | AB28: 21 | AC28: 22 | AD28: 23 | AE28: 24 | AF28: 25 | AG28: 26 | AH28: 27 | AI28: 28 | AJ28: 29 | AK28: 30 | AL28: 31
B29: =Categorias!B25 -> Restaurantes | C29: 2500 | D29: =SUM(Marzo!$H29:$AL29) -> 4054 | E29: =C29-D29 -> -1554 | I29: 210 | K29: 1200 | V29: 760 | Y29: 1304 | AA29: 580
B30: =Categorias!B26 -> Comida Carlos | C30: 500 | D30: =SUM(Marzo!$H30:$AL30) -> 430 | E30: =C30-D30 -> 70 | O30: 50 | R30: 180 | S30: 200
B31: =Categorias!B27 -> - | C31: 0 | D31: =SUM(Marzo!$H31:$AL31) -> 0 | E31: =C31-D31 -> 0
B32: =Categorias!B28 -> - | C32: 0 | D32: =SUM(Marzo!$H32:$AL32) -> 0 | E32: =C32-D32 -> 0
B33: =Categorias!B29 -> - | C33: 0 | D33: =SUM(Marzo!$H33:$AL33) -> 0 | E33: =C33-D33 -> 0
B34: =Categorias!B30 -> - | C34: 0 | D34: =SUM(Marzo!$H34:$AL34) -> 0 | E34: =C34-D34 -> 0
B35: =Categorias!B31 -> - | C35: 0 | D35: =SUM(Marzo!$H35:$AL35) -> 0 | E35: =C35-D35 -> 0
B37: =Categorias!B33 -> SALUD | C37: =SUM(C38:C43) -> 0 | D37: =SUM(D38:D43) -> 2492 | E37: =SUM(E38:E43) -> -2492 | H37: 1 | I37: 2 | J37: 3 | K37: 4 | L37: 5 | M37: 6 | N37: 7 | O37: 8 | P37: 9 | Q37: 10 | R37: 11 | S37: 12 | T37: 13 | U37: 14 | V37: 15 | W37: 16 | X37: 17 | Y37: 18 | Z37: 19 | AA37: 20 | AB37: 21 | AC37: 22 | AD37: 23 | AE37: 24 | AF37: 25 | AG37: 26 | AH37: 27 | AI37: 28 | AJ37: 29 | AK37: 30 | AL37: 31
B38: =Categorias!B34 -> Gastos en médicos | C38: 0 | D38: =SUM(Marzo!$H38:$AL38) -> 0 | E38: =C38-D38 -> 0
B39: =Categorias!B35 -> Medicamentos | C39: 0 | D39: =SUM(Marzo!$H39:$AL39) -> 2492 | E39: =C39-D39 -> -2492 | O39: 570 | P39: 1372 | V39: 190 | W39: 360
B40: =Categorias!B36 -> Dentista Kary | C40: 0 | D40: =SUM(Marzo!$H40:$AL40) -> 0 | E40: =C40-D40 -> 0
B41: =Categorias!B37 -> Dentista Thiago | C41: 0 | D41: =SUM(Marzo!$H41:$AL41) -> 0 | E41: =C41-D41 -> 0
B42: =Categorias!B38 -> - | C42: 0 | D42: =SUM(Marzo!$H42:$AL42) -> 0 | E42: =C42-D42 -> 0
B43: =Categorias!B39 -> - | C43: 0 | D43: =SUM(Marzo!$H43:$AL43) -> 0 | E43: =C43-D43 -> 0
B45: =Categorias!B41 -> CASA | C45: =SUM(C46:C56) -> 14400 | D45: =SUM(D46:D56) -> 16730 | E45: =SUM(E46:E56) -> -2330 | H45: 1 | I45: 2 | J45: 3 | K45: 4 | L45: 5 | M45: 6 | N45: 7 | O45: 8 | P45: 9 | Q45: 10 | R45: 11 | S45: 12 | T45: 13 | U45: 14 | V45: 15 | W45: 16 | X45: 17 | Y45: 18 | Z45: 19 | AA45: 20 | AB45: 21 | AC45: 22 | AD45: 23 | AE45: 24 | AF45: 25 | AG45: 26 | AH45: 27 | AI45: 28 | AJ45: 29 | AK45: 30 | AL45: 31
B46: =Categorias!B42 -> Reparación | C46: 0 | D46: =SUM(Marzo!$H46:$AL46) -> 8730 | E46: =C46-D46 -> -8730 | I46: 7500 | AL46: 1230
B47: =Categorias!B43 -> Electricidad | C47: 1200 | D47: =SUM(Marzo!$H47:$AL47) -> 0 | E47: =C47-D47 -> 1200
B48: =Categorias!B44 -> Gas | C48: 200 | D48: =SUM(Marzo!$H48:$AL48) -> 0 | E48: =C48-D48 -> 200
B49: =Categorias!B45 -> Casa Claudia | C49: 0 | D49: =SUM(Marzo!$H49:$AL49) -> 0 | E49: =C49-D49 -> 0
B50: =Categorias!B46 -> Muebles/electrodomésticos | C50: 0 | D50: =SUM(Marzo!$H50:$AL50) -> 0 | E50: =C50-D50 -> 0
B51: =Categorias!B47 -> Predial | C51: 10000 | D51: =SUM(Marzo!$H51:$AL51) -> 5000 | E51: =C51-D51 -> 5000 | H51: 5000
B52: =Categorias!B48 -> Renta Cuarto | C52: 3000 | D52: =SUM(Marzo!$H52:$AL52) -> 3000 | E52: =C52-D52 -> 0 | H52: 3000
B53: =Categorias!B49 -> - | C53: 0 | D53: =SUM(Marzo!$H53:$AL53) -> 0 | E53: =C53-D53 -> 0
B54: =Categorias!B50 -> - | C54: 0 | D54: =SUM(Marzo!$H54:$AL54) -> 0 | E54: =C54-D54 -> 0
B55: =Categorias!B51 -> - | C55: 0 | D55: =SUM(Marzo!$H55:$AL55) -> 0 | E55: =C55-D55 -> 0
B56: =Categorias!B52 -> - | C56: 0 | D56: =SUM(Marzo!$H56:$AL56) -> 0 | E56: =C56-D56 -> 0
B58: =Categorias!B54 -> ROPA Y CALZADO | C58: =SUM(C59:C66) -> 0 | D58: =SUM(D59:D66) -> 2053 | E58: =SUM(E59:E66) -> -2053 | H58: 1 | I58: 2 | J58: 3 | K58: 4 | L58: 5 | M58: 6 | N58: 7 | O58: 8 | P58: 9 | Q58: 10 | R58: 11 | S58: 12 | T58: 13 | U58: 14 | V58: 15 | W58: 16 | X58: 17 | Y58: 18 | Z58: 19 | AA58: 20 | AB58: 21 | AC58: 22 | AD58: 23 | AE58: 24 | AF58: 25 | AG58: 26 | AH58: 27 | AI58: 28 | AJ58: 29 | AK58: 30 | AL58: 31
B59: =Categorias!B55 -> Ropa de adultos | C59: 0 | D59: =SUM(Marzo!$H59:$AL59) -> 1600 | E59: =C59-D59 -> -1600 | AL59: 1600
B60: =Categorias!B56 -> Ropa de niños | C60: 0 | D60: =SUM(Marzo!$H60:$AL60) -> 0 | E60: =C60-D60 -> 0
B61: =Categorias!B57 -> Calzado | C61: 0 | D61: =SUM(Marzo!$H61:$AL61) -> 380 | E61: =C61-D61 -> -380 | W61: 380
B62: =Categorias!B58 -> Acessorios | C62: 0 | D62: =SUM(Marzo!$H62:$AL62) -> 73 | E62: =C62-D62 -> -73 | O62: 73
B63: =Categorias!B59 -> Joyería | C63: 0 | D63: =SUM(Marzo!$H63:$AL63) -> 0 | E63: =C63-D63 -> 0
B64: =Categorias!B60 -> Otros | C64: 0 | D64: =SUM(Marzo!$H64:$AL64) -> 0 | E64: =C64-D64 -> 0
B65: =Categorias!B61 -> - | C65: 0 | D65: =SUM(Marzo!$H65:$AL65) -> 0 | E65: =C65-D65 -> 0
B66: =Categorias!B62 -> - | C66: 0 | D66: =SUM(Marzo!$H66:$AL66) -> 0 | E66: =C66-D66 -> 0
B68: =Categorias!B64 -> COMUNICACIÓN | C68: =SUM(C69:C75) -> 738 | D68: =SUM(D69:D75) -> 330 | E68: =SUM(E69:E75) -> 408 | H68: 1 | I68: 2 | J68: 3 | K68: 4 | L68: 5 | M68: 6 | N68: 7 | O68: 8 | P68: 9 | Q68: 10 | R68: 11 | S68: 12 | T68: 13 | U68: 14 | V68: 15 | W68: 16 | X68: 17 | Y68: 18 | Z68: 19 | AA68: 20 | AB68: 21 | AC68: 22 | AD68: 23 | AE68: 24 | AF68: 25 | AG68: 26 | AH68: 27 | AI68: 28 | AJ68: 29 | AK68: 30 | AL68: 31
B69: =Categorias!B65 -> Cel. Claudia | C69: 289 | D69: =SUM(Marzo!$H69:$AL69) -> 280 | E69: =C69-D69 -> 9 | V69: 280
B70: =Categorias!B66 -> Cel. Carlos | C70: 249 | D70: =SUM(Marzo!$H70:$AL70) -> 0 | E70: =C70-D70 -> 249
B71: =Categorias!B67 -> Cel.Kary | C71: 200 | D71: =SUM(Marzo!$H71:$AL71) -> 50 | E71: =C71-D71 -> 150 | N71: 50
B72: =Categorias!B68 -> - | C72: 0 | D72: =SUM(Marzo!$H72:$AL72) -> 0 | E72: =C72-D72 -> 0
B73: =Categorias!B69 -> - | C73: 0 | D73: =SUM(Marzo!$H73:$AL73) -> 0 | E73: =C73-D73 -> 0
B74: =Categorias!B70 -> - | C74: 0 | D74: =SUM(Marzo!$H74:$AL74) -> 0 | E74: =C74-D74 -> 0
B75: =Categorias!B73 -> - | C75: 0 | D75: =SUM(Marzo!$H75:$AL75) -> 0 | E75: =C75-D75 -> 0
B77: =Categorias!B75 -> TRANSPORTE | C77: =SUM(C78:C86) -> 3500 | D77: =SUM(D78:D86) -> 150 | E77: =SUM(E78:E86) -> 3350 | H77: 1 | I77: 2 | J77: 3 | K77: 4 | L77: 5 | M77: 6 | N77: 7 | O77: 8 | P77: 9 | Q77: 10 | R77: 11 | S77: 12 | T77: 13 | U77: 14 | V77: 15 | W77: 16 | X77: 17 | Y77: 18 | Z77: 19 | AA77: 20 | AB77: 21 | AC77: 22 | AD77: 23 | AE77: 24 | AF77: 25 | AG77: 26 | AH77: 27 | AI77: 28 | AJ77: 29 | AK77: 30 | AL77: 31
B78: =Categorias!B76 -> Combustible Fusion | C78: 0 | D78: =SUM(Marzo!$H78:$AL78) -> 0 | E78: =C78-D78 -> 0
B79: =Categorias!B77 -> Seguro Fusion | C79: 0 | D79: =SUM(Marzo!$H79:$AL79) -> 150 | E79: =C79-D79 -> -150 | H79: 150
B80: =Categorias!B78 -> Mantenimiento Fusion | C80: 1000 | D80: =SUM(Marzo!$H80:$AL80) -> 0 | E80: =C80-D80 -> 1000
B81: =Categorias!B79 -> Derecho vehicular Fusion | C81: 2500 | D81: =SUM(Marzo!$H81:$AL81) -> 0 | E81: =C81-D81 -> 2500
B82: =Categorias!B80 -> Casetas | C82: 0 | D82: =SUM(Marzo!$H82:$AL82) -> 0 | E82: =C82-D82 -> 0
B83: =Categorias!B81 -> ADO | C83: 0 | D83: =SUM(Marzo!$H83:$AL83) -> 0 | E83: =C83-D83 -> 0
B84: =Categorias!B82 -> - | C84: 0 | D84: =SUM(Marzo!$H84:$AL84) -> 0 | E84: =C84-D84 -> 0
B85: =Categorias!B83 -> - | C85: 0 | D85: =SUM(Marzo!$H85:$AL85) -> 0 | E85: =C85-D85 -> 0
B86: =Categorias!B84 -> - | C86: 0 | D86: =SUM(Marzo!$H86:$AL86) -> 0 | E86: =C86-D86 -> 0
B88: =Categorias!B86 -> HIGIENE | C88: =SUM(C89:C95) -> 250 | D88: =SUM(D89:D95) -> 0 | E88: =SUM(E89:E95) -> 250 | H88: 1 | I88: 2 | J88: 3 | K88: 4 | L88: 5 | M88: 6 | N88: 7 | O88: 8 | P88: 9 | Q88: 10 | R88: 11 | S88: 12 | T88: 13 | U88: 14 | V88: 15 | W88: 16 | X88: 17 | Y88: 18 | Z88: 19 | AA88: 20 | AB88: 21 | AC88: 22 | AD88: 23 | AE88: 24 | AF88: 25 | AG88: 26 | AH88: 27 | AI88: 28 | AJ88: 29 | AK88: 30 | AL88: 31
B89: =Categorias!B87 -> Cosmeticos | C89: 0 | D89: =SUM(Marzo!$H89:$AL89) -> 0 | E89: =C89-D89 -> 0
B90: =Categorias!B88 -> Peluquería / S. Belleza | C90: 250 | D90: =SUM(Marzo!$H90:$AL90) -> 0 | E90: =C90-D90 -> 250
B91: =Categorias!B89 -> Lavanderia | C91: 0 | D91: =SUM(Marzo!$H91:$AL91) -> 0 | E91: =C91-D91 -> 0
B92: =Categorias!B90 -> Productos de limpieza | C92: 0 | D92: =SUM(Marzo!$H92:$AL92) -> 0 | E92: =C92-D92 -> 0
B93: =Categorias!B91 -> Otros | C93: 0 | D93: =SUM(Marzo!$H93:$AL93) -> 0 | E93: =C93-D93 -> 0
B94: =Categorias!B92 -> - | C94: 0 | D94: =SUM(Marzo!$H94:$AL94) -> 0 | E94: =C94-D94 -> 0
B95: =Categorias!B93 -> - | C95: 0 | D95: =SUM(Marzo!$H95:$AL95) -> 0 | E95: =C95-D95 -> 0
B97: =Categorias!B95 -> NIÑOS | C97: =SUM(C98:C105) -> 1000 | D97: =SUM(D98:D105) -> 990 | E97: =SUM(E98:E105) -> 10 | H97: 1 | I97: 2 | J97: 3 | K97: 4 | L97: 5 | M97: 6 | N97: 7 | O97: 8 | P97: 9 | Q97: 10 | R97: 11 | S97: 12 | T97: 13 | U97: 14 | V97: 15 | W97: 16 | X97: 17 | Y97: 18 | Z97: 19 | AA97: 20 | AB97: 21 | AC97: 22 | AD97: 23 | AE97: 24 | AF97: 25 | AG97: 26 | AH97: 27 | AI97: 28 | AJ97: 29 | AK97: 30 | AL97: 31
B98: =Categorias!B96 -> Jugetes/juegos | C98: 0 | D98: =SUM(Marzo!$H98:$AL98) -> 0 | E98: =C98-D98 -> 0
B99: =Categorias!B97 -> - | C99: 1000 | D99: =SUM(Marzo!$H99:$AL99) -> 990 | E99: =C99-D99 -> 10 | I99: 790 | N99: 200
B100: =Categorias!B98 -> - | C100: 0 | D100: =SUM(Marzo!$H100:$AL100) -> 0 | E100: =C100-D100 -> 0
B101: =Categorias!B99 -> - | C101: 0 | D101: =SUM(Marzo!$H101:$AL101) -> 0 | E101: =C101-D101 -> 0
B102: =Categorias!B100 -> - | C102: 0 | D102: =SUM(Marzo!$H102:$AL102) -> 0 | E102: =C102-D102 -> 0
B103: =Categorias!B101 -> - | C103: 0 | D103: =SUM(Marzo!$H103:$AL103) -> 0 | E103: =C103-D103 -> 0
B104: =Categorias!B102 -> - | C104: 0 | D104: =SUM(Marzo!$H104:$AL104) -> 0 | E104: =C104-D104 -> 0
B105: =Categorias!B103 -> - | C105: 0 | D105: =SUM(Marzo!$H105:$AL105) -> 0 | E105: =C105-D105 -> 0
B107: =Categorias!B105 -> DESARROLLO PERSONAL | C107: =SUM(C108:C113) -> 0 | D107: =SUM(D108:D113) -> 0 | E107: =SUM(E108:E113) -> 0 | H107: 1 | I107: 2 | J107: 3 | K107: 4 | L107: 5 | M107: 6 | N107: 7 | O107: 8 | P107: 9 | Q107: 10 | R107: 11 | S107: 12 | T107: 13 | U107: 14 | V107: 15 | W107: 16 | X107: 17 | Y107: 18 | Z107: 19 | AA107: 20 | AB107: 21 | AC107: 22 | AD107: 23 | AE107: 24 | AF107: 25 | AG107: 26 | AH107: 27 | AI107: 28 | AJ107: 29 | AK107: 30 | AL107: 31
B108: =Categorias!B106 -> Libros | C108: 0 | D108: =SUM(Marzo!$H108:$AL108) -> 0 | E108: =C108-D108 -> 0
B109: =Categorias!B107 -> Platzi | C109: 0 | D109: =SUM(Marzo!$H109:$AL109) -> 0 | E109: =C109-D109 -> 0
B110: =Categorias!B108 -> Papeleria | C110: 0 | D110: =SUM(Marzo!$H110:$AL110) -> 0 | E110: =C110-D110 -> 0
B111: =Categorias!B109 -> Inglés Thiago | C111: 0 | D111: =SUM(Marzo!$H111:$AL111) -> 0 | E111: =C111-D111 -> 0
B112: Lapices | C112: 0 | D112: =SUM(Marzo!$H112:$AL112) -> 0 | E112: =C112-D112 -> 0
B113: =Categorias!B111 -> Escuela kary | C113: 0 | D113: =SUM(Marzo!$H113:$AL113) -> 0 | E113: =C113-D113 -> 0
B115: =Categorias!B113 -> DIVERSIÓN | C115: =SUM(C116:C124) -> 1000 | D115: =SUM(D116:D124) -> 700 | E115: =SUM(E116:E124) -> 300 | H115: 1 | I115: 2 | J115: 3 | K115: 4 | L115: 5 | M115: 6 | N115: 7 | O115: 8 | P115: 9 | Q115: 10 | R115: 11 | S115: 12 | T115: 13 | U115: 14 | V115: 15 | W115: 16 | X115: 17 | Y115: 18 | Z115: 19 | AA115: 20 | AB115: 21 | AC115: 22 | AD115: 23 | AE115: 24 | AF115: 25 | AG115: 26 | AH115: 27 | AI115: 28 | AJ115: 29 | AK115: 30 | AL115: 31
B116: =Categorias!B114 -> Cine/teatro | C116: 0 | D116: =SUM(Marzo!$H116:$AL116) -> 700 | E116: =C116-D116 -> -700 | Y116: 700
B117: =Categorias!B115 -> Gimnasio/piscina | C117: 1000 | D117: =SUM(Marzo!$H117:$AL117) -> 0 | E117: =C117-D117 -> 1000
...

Sheet Abril
B2: Presupuesto | C2: 44287
C4: Para crear un presupuesto: - A principios de este mes, rellene los campos en amarillo, despues de forma regular registre los gastos de cada dia en la tabla a la derecha - Todos los otros datos se convertirá automáticamente
C5: Fuente: | D5: =HYPERLINK("http://www.aprendizfinanciero.com/","http://www.aprendizfinanciero.com") -> http://www.aprendizfinanciero.com
B6: Ingresos
B8: Categoría | C8: Ingresos previstos | D8: Ingresos reales | E8: Diferencia | F8: Notas
B9: SUMA | C9: =C11 -> 0 | D9: =D11 -> 52000 | E9: =E11 -> 52000
B11: =Categorias!B11 -> INGRESOS TOTALES | C11: =SUM(C12:C20) -> 0 | D11: =SUM(D12:D20) -> 52000 | E11: =SUM(E12:E20) -> 52000 | H11: 1 | I11: 2 | J11: 3 | K11: 4 | L11: 5 | M11: 6 | N11: 7 | O11: 8 | P11: 9 | Q11: 10 | R11: 11 | S11: 12 | T11: 13 | U11: 14 | V11: 15 | W11: 16 | X11: 17 | Y11: 18 | Z11: 19 | AA11: 20 | AB11: 21 | AC11: 22 | AD11: 23 | AE11: 24 | AF11: 25 | AG11: 26 | AH11: 27 | AI11: 28 | AJ11: 29 | AK11: 30 | AL11: 31
B12: =Categorias!B12 -> Nomina | C12: 0 | D12: =SUM(Abril!$H12:$AL12) -> 42000 | E12: =D12-C12 -> 42000 | V12: 21000 | AL12: 21000
B13: =Categorias!B13 -> Aguinaldo | C13: 0 | D13: =SUM(Abril!$H13:$AL13) -> 10000 | E13: =D13-C13 -> 10000 | AL13: 10000
B14: =Categorias!B14 -> Fondo de ahorro | C14: 0 | D14: =SUM(Abril!$H14:$AL14) -> 0 | E14: =D14-C14 -> 0
B15: =Categorias!B15 -> Vales despensa | C15: 0 | D15: =SUM(Abril!$H15:$AL15) -> 0 | E15: =D15-C15 -> 0
B16: =Categorias!B16 -> Vales comedor | C16: 0 | D16: =SUM(Abril!$H16:$AL16) -> 0 | E16: =D16-C16 -> 0
B17: =Categorias!B17 -> - | C17: 0 | D17: =SUM(Abril!$H17:$AL17) -> 0 | E17: =D17-C17 -> 0
B18: =Categorias!B18 -> - | C18: 0 | D18: =SUM(Abril!$H18:$AL18) -> 0 | E18: =D18-C18 -> 0
B19: =Categorias!B19 -> - | C19: 0 | D19: =SUM(Abril!$H19:$AL19) -> 0 | E19: =D19-C19 -> 0
B20: =Categorias!B20 -> - | C20: 0 | D20: =SUM(Abril!$H20:$AL20) -> 0 | E20: =D20-C20 -> 0
B23: Gastos | H23: Registre de gastos diarios
B25: Categoría | C25: Gastos previstos | D25: Gastos reales | E25: Diferencia | F25: Notas | H25: Los campos siguientes son para un registro diario de gastos en cada categoría.
B26: SUMA | C26: =C28+C37+C45+C58+C68+C77+C88+C97+C107+C115+C126+C136+C146+C158 -> 0 | D26: =D28+D37+D45+D58+D68+D77+D88+D97+D107+D115+D126+D136+D146+D158 -> 25574 | E26: =E28+E37+E45+E58+E68+E77+E88+E97+E107+E115+E126+E136+E146+E158 -> -25574 | H26: Si quieres incluir mas gastos en una celda, por el mismo dia, ingresa "=" y sigue la ecuación, por ejemplo:. = 25 + 20.5
B28: =Categorias!B24 -> ALIMENTOS Y BEBIDAS | C28: =SUM(C29:C35) -> 0 | D28: =SUM(D29:D35) -> 2602 | E28: =SUM(E29:E35) -> -2602 | H28: 1 | I28: 2 | J28: 3 | K28: 4 | L28: 5 | M28: 6 | N28: 7 | O28: 8 | P28: 9 | Q28: 10 | R28: 11 | S28: 12 | T28: 13 | U28: 14 | V28: 15 | W28: 16 | X28: 17 | Y28: 18 | Z28: 19 | AA28: 20 | AB28: 21 | AC28: 22 | AD28: 23 | AE28: 24 | AF28: 25 | AG28: 26 | AH28: 27 | AI28: 28 | AJ28: 29 | AK28: 30 | AL28: 31
B29: =Categorias!B25 -> Restaurantes | C29: 0 | D29: =SUM(Abril!$H29:$AL29) -> 2015 | E29: =C29-D29 -> -2015 | I29: 1029 | L29: 40 | M29: 218 | N29: 60 | Q29: 555 | AD29: 33 | AG29: 80
B30: =Categorias!B26 -> Comida Carlos | C30: 0 | D30: =SUM(Abril!$H30:$AL30) -> 587 | E30: =C30-D30 -> -587 | AA30: 287 | AK30: 300
B31: =Categorias!B27 -> - | C31: 0 | D31: =SUM(Abril!$H31:$AL31) -> 0 | E31: =C31-D31 -> 0
B32: =Categorias!B28 -> - | C32: 0 | D32: =SUM(Abril!$H32:$AL32) -> 0 | E32: =C32-D32 -> 0
B33: =Categorias!B29 -> - | C33: 0 | D33: =SUM(Abril!$H33:$AL33) -> 0 | E33: =C33-D33 -> 0
B34: =Categorias!B30 -> - | C34: 0 | D34: =SUM(Abril!$H34:$AL34) -> 0 | E34: =C34-D34 -> 0
B35: =Categorias!B31 -> - | C35: 0 | D35: =SUM(Abril!$H35:$AL35) -> 0 | E35: =C35-D35 -> 0
B37: =Categorias!B33 -> SALUD | C37: =SUM(C38:C43) -> 0 | D37: =SUM(D38:D43) -> 4070 | E37: =SUM(E38:E43) -> -4070 | H37: 1 | I37: 2 | J37: 3 | K37: 4 | L37: 5 | M37: 6 | N37: 7 | O37: 8 | P37: 9 | Q37: 10 | R37: 11 | S37: 12 | T37: 13 | U37: 14 | V37: 15 | W37: 16 | X37: 17 | Y37: 18 | Z37: 19 | AA37: 20 | AB37: 21 | AC37: 22 | AD37: 23 | AE37: 24 | AF37: 25 | AG37: 26 | AH37: 27 | AI37: 28 | AJ37: 29 | AK37: 30 | AL37: 31
B38: =Categorias!B34 -> Gastos en médicos | C38: 0 | D38: =SUM(Abril!$H38:$AL38) -> 2400 | E38: =C38-D38 -> -2400 | AD38: 2400
B39: =Categorias!B35 -> Medicamentos | C39: 0 | D39: =SUM(Abril!$H39:$AL39) -> 1670 | E39: =C39-D39 -> -1670 | Y39: 470 | AC39: 950 | AD39: 250
B40: =Categorias!B36 -> Dentista Kary | C40: 0 | D40: =SUM(Abril!$H40:$AL40) -> 0 | E40: =C40-D40 -> 0
B41: =Categorias!B37 -> Dentista Thiago | C41: 0 | D41: =SUM(Abril!$H41:$AL41) -> 0 | E41: =C41-D41 -> 0
B42: =Categorias!B38 -> - | C42: 0 | D42: =SUM(Abril!$H42:$AL42) -> 0 | E42: =C42-D42 -> 0
B43: =Categorias!B39 -> - | C43: 0 | D43: =SUM(Abril!$H43:$AL43) -> 0 | E43: =C43-D43 -> 0
B45: =Categorias!B41 -> CASA | C45: =SUM(C46:C56) -> 0 | D45: =SUM(D46:D56) -> 12559 | E45: =SUM(E46:E56) -> -12559 | H45: 1 | I45: 2 | J45: 3 | K45: 4 | L45: 5 | M45: 6 | N45: 7 | O45: 8 | P45: 9 | Q45: 10 | R45: 11 | S45: 12 | T45: 13 | U45: 14 | V45: 15 | W45: 16 | X45: 17 | Y45: 18 | Z45: 19 | AA45: 20 | AB45: 21 | AC45: 22 | AD45: 23 | AE45: 24 | AF45: 25 | AG45: 26 | AH45: 27 | AI45: 28 | AJ45: 29 | AK45: 30 | AL45: 31
B46: =Categorias!B42 -> Reparación | C46: 0 | D46: =SUM(Abril!$H46:$AL46) -> 12236 | E46: =C46-D46 -> -12236 | H46: 2645 | I46: 591 | K46: 200 | L46: 8000 | O46: 800
B47: =Categorias!B43 -> Electricidad | C47: 0 | D47: =SUM(Abril!$H47:$AL47) -> 0 | E47: =C47-D47 -> 0
B48: =Categorias!B44 -> Gas | C48: 0 | D48: =SUM(Abril!$H48:$AL48) -> 200 | E48: =C48-D48 -> -200 | K48: 200
B49: =Categorias!B45 -> Casa Claudia | C49: 0 | D49: =SUM(Abril!$H49:$AL49) -> 123 | E49: =C49-D49 -> -123 | L49: 123
B50: =Categorias!B46 -> Muebles/electrodomésticos | C50: 0 | D50: =SUM(Abril!$H50:$AL50) -> 0 | E50: =C50-D50 -> 0
B51: =Categorias!B47 -> Predial | C51: 0 | D51: =SUM(Abril!$H51:$AL51) -> 0 | E51: =C51-D51 -> 0
B52: =Categorias!B48 -> Renta Cuarto | C52: 0 | D52: =SUM(Abril!$H52:$AL52) -> 0 | E52: =C52-D52 -> 0
B53: =Categorias!B49 -> - | C53: 0 | D53: =SUM(Abril!$H53:$AL53) -> 0 | E53: =C53-D53 -> 0
B54: =Categorias!B50 -> - | C54: 0 | D54: =SUM(Abril!$H54:$AL54) -> 0 | E54: =C54-D54 -> 0
B55: =Categorias!B51 -> - | C55: 0 | D55: =SUM(Abril!$H55:$AL55) -> 0 | E55: =C55-D55 -> 0
B56: =Categorias!B52 -> - | C56: 0 | D56: =SUM(Abril!$H56:$AL56) -> 0 | E56: =C56-D56 -> 0
B58: =Categorias!B54 -> ROPA Y CALZADO | C58: =SUM(C59:C66) -> 0 | D58: =SUM(D59:D66) -> 2400 | E58: =SUM(E59:E66) -> -2400 | H58: 1 | I58: 2 | J58: 3 | K58: 4 | L58: 5 | M58: 6 | N58: 7 | O58: 8 | P58: 9 | Q58: 10 | R58: 11 | S58: 12 | T58: 13 | U58: 14 | V58: 15 | W58: 16 | X58: 17 | Y58: 18 | Z58: 19 | AA58: 20 | AB58: 21 | AC58: 22 | AD58: 23 | AE58: 24 | AF58: 25 | AG58: 26 | AH58: 27 | AI58: 28 | AJ58: 29 | AK58: 30 | AL58: 31
B59: =Categorias!B55 -> Ropa de adultos | C59: 0 | D59: =SUM(Abril!$H59:$AL59) -> 0 | E59: =C59-D59 -> 0
B60: =Categorias!B56 -> Ropa de niños | C60: 0 | D60: =SUM(Abril!$H60:$AL60) -> 2000 | E60: =C60-D60 -> -2000 | AH60: 2000
B61: =Categorias!B57 -> Calzado | C61: 0 | D61: =SUM(Abril!$H61:$AL61) -> 400 | E61: =C61-D61 -> -400 | L61: 400
B62: =Categorias!B58 -> Acessorios | C62: 0 | D62: =SUM(Abril!$H62:$AL62) -> 0 | E62: =C62-D62 -> 0
B63: =Categorias!B59 -> Joyería | C63: 0 | D63: =SUM(Abril!$H63:$AL63) -> 0 | E63: =C63-D63 -> 0
B64: =Categorias!B60 -> Otros | C64: 0 | D64: =SUM(Abril!$H64:$AL64) -> 0 | E64: =C64-D64 -> 0
B65: =Categorias!B61 -> - | C65: 0 | D65: =SUM(Abril!$H65:$AL65) -> 0 | E65: =C65-D65 -> 0
B66: =Categorias!B62 -> - | C66: 0 | D66: =SUM(Abril!$H66:$AL66) -> 0 | E66: =C66-D66 -> 0
B68: =Categorias!B64 -> COMUNICACIÓN | C68: =SUM(C69:C75) -> 0 | D68: =SUM(D69:D75) -> 0 | E68: =SUM(E69:E75) -> 0 | H68: 1 | I68: 2 | J68: 3 | K68: 4 | L68: 5 | M68: 6 | N68: 7 | O68: 8 | P68: 9 | Q68: 10 | R68: 11 | S68: 12 | T68: 13 | U68: 14 | V68: 15 | W68: 16 | X68: 17 | Y68: 18 | Z68: 19 | AA68: 20 | AB68: 21 | AC68: 22 | AD68: 23 | AE68: 24 | AF68: 25 | AG68: 26 | AH68: 27 | AI68: 28 | AJ68: 29 | AK68: 30 | AL68: 31
B69: =Categorias!B65 -> Cel. Claudia | C69: 0 | D69: =SUM(Abril!$H69:$AL69) -> 0 | E69: =C69-D69 -> 0
B70: =Categorias!B66 -> Cel. Carlos | C70: 0 | D70: =SUM(Abril!$H70:$AL70) -> 0 | E70: =C70-D70 -> 0
B71: =Categorias!B67 -> Cel.Kary | C71: 0 | D71: =SUM(Abril!$H71:$AL71) -> 0 | E71: =C71-D71 -> 0
B72: =Categorias!B68 -> - | C72: 0 | D72: =SUM(Abril!$H72:$AL72) -> 0 | E72: =C72-D72 -> 0
B73: =Categorias!B69 -> - | C73: 0 | D73: =SUM(Abril!$H73:$AL73) -> 0 | E73: =C73-D73 -> 0
B74: =Categorias!B70 -> - | C74: 0 | D74: =SUM(Abril!$H74:$AL74) -> 0 | E74: =C74-D74 -> 0
B75: =Categorias!B73 -> - | C75: 0 | D75: =SUM(Abril!$H75:$AL75) -> 0 | E75: =C75-D75 -> 0
B77: =Categorias!B75 -> TRANSPORTE | C77: =SUM(C78:C86) -> 0 | D77: =SUM(D78:D86) -> 1000 | E77: =SUM(E78:E86) -> -1000 | H77: 1 | I77: 2 | J77: 3 | K77: 4 | L77: 5 | M77: 6 | N77: 7 | O77: 8 | P77: 9 | Q77: 10 | R77: 11 | S77: 12 | T77: 13 | U77: 14 | V77: 15 | W77: 16 | X77: 17 | Y77: 18 | Z77: 19 | AA77: 20 | AB77: 21 | AC77: 22 | AD77: 23 | AE77: 24 | AF77: 25 | AG77: 26 | AH77: 27 | AI77: 28 | AJ77: 29 | AK77: 30 | AL77: 31
B78: =Categorias!B76 -> Combustible Fusion | C78: 0 | D78: =SUM(Abril!$H78:$AL78) -> 1000 | E78: =C78-D78 -> -1000 | R78: 1000
B79: =Categorias!B77 -> Seguro Fusion | C79: 0 | D79: =SUM(Abril!$H79:$AL79) -> 0 | E79: =C79-D79 -> 0
B80: =Categorias!B78 -> Mantenimiento Fusion | C80: 0 | D80: =SUM(Abril!$H80:$AL80) -> 0 | E80: =C80-D80 -> 0
B81: =Categorias!B79 -> Derecho vehicular Fusion | C81: 0 | D81: =SUM(Abril!$H81:$AL81) -> 0 | E81: =C81-D81 -> 0
B82: =Categorias!B80 -> Casetas | C82: 0 | D82: =SUM(Abril!$H82:$AL82) -> 0 | E82: =C82-D82 -> 0
B83: =Categorias!B81 -> ADO | C83: 0 | D83: =SUM(Abril!$H83:$AL83) -> 0 | E83: =C83-D83 -> 0
B84: =Categorias!B82 -> - | C84: 0 | D84: =SUM(Abril!$H84:$AL84) -> 0 | E84: =C84-D84 -> 0
B85: =Categorias!B83 -> - | C85: 0 | D85: =SUM(Abril!$H85:$AL85) -> 0 | E85: =C85-D85 -> 0
B86: =Categorias!B84 -> - | C86: 0 | D86: =SUM(Abril!$H86:$AL86) -> 0 | E86: =C86-D86 -> 0
B88: =Categorias!B86 -> HIGIENE | C88: =SUM(C89:C95) -> 0 | D88: =SUM(D89:D95) -> 0 | E88: =SUM(E89:E95) -> 0 | H88: 1 | I88: 2 | J88: 3 | K88: 4 | L88: 5 | M88: 6 | N88: 7 | O88: 8 | P88: 9 | Q88: 10 | R88: 11 | S88: 12 | T88: 13 | U88: 14 | V88: 15 | W88: 16 | X88: 17 | Y88: 18 | Z88: 19 | AA88: 20 | AB88: 21 | AC88: 22 | AD88: 23 | AE88: 24 | AF88: 25 | AG88: 26 | AH88: 27 | AI88: 28 | AJ88: 29 | AK88: 30 | AL88: 31
B89: =Categorias!B87 -> Cosmeticos | C89: 0 | D89: =SUM(Abril!$H89:$AL89) -> 0 | E89: =C89-D89 -> 0
B90: =Categorias!B88 -> Peluquería / S. Belleza | C90: 0 | D90: =SUM(Abril!$H90:$AL90) -> 0 | E90: =C90-D90 -> 0
B91: =Categorias!B89 -> Lavanderia | C91: 0 | D91: =SUM(Abril!$H91:$AL91) -> 0 | E91: =C91-D91 -> 0
B92: =Categorias!B90 -> Productos de limpieza | C92: 0 | D92: =SUM(Abril!$H92:$AL92) -> 0 | E92: =C92-D92 -> 0
B93: =Categorias!B91 -> Otros | C93: 0 | D93: =SUM(Abril!$H93:$AL93) -> 0 | E93: =C93-D93 -> 0
B94: =Categorias!B92 -> - | C94: 0 | D94: =SUM(Abril!$H94:$AL94) -> 0 | E94: =C94-D94 -> 0
B95: =Categorias!B93 -> - | C95: 0 | D95: =SUM(Abril!$H95:$AL95) -> 0 | E95: =C95-D95 -> 0
B97: =Categorias!B95 -> NIÑOS | C97: =SUM(C98:C105) -> 0 | D97: =SUM(D98:D105) -> 0 | E97: =SUM(E98:E105) -> 0 | H97: 1 | I97: 2 | J97: 3 | K97: 4 | L97: 5 | M97: 6 | N97: 7 | O97: 8 | P97: 9 | Q97: 10 | R97: 11 | S97: 12 | T97: 13 | U97: 14 | V97: 15 | W97: 16 | X97: 17 | Y97: 18 | Z97: 19 | AA97: 20 | AB97: 21 | AC97: 22 | AD97: 23 | AE97: 24 | AF97: 25 | AG97: 26 | AH97: 27 | AI97: 28 | AJ97: 29 | AK97: 30 | AL97: 31
B98: =Categorias!B96 -> Jugetes/juegos | C98: 0 | D98: =SUM(Abril!$H98:$AL98) -> 0 | E98: =C98-D98 -> 0
B99: =Categorias!B97 -> - | C99: 0 | D99: =SUM(Abril!$H99:$AL99) -> 0 | E99: =C99-D99 -> 0
B100: =Categorias!B98 -> - | C100: 0 | D100: =SUM(Abril!$H100:$AL100) -> 0 | E100: =C100-D100 -> 0
B101: =Categorias!B99 -> - | C101: 0 | D101: =SUM(Abril!$H101:$AL101) -> 0 | E101: =C101-D101 -> 0
B102: =Categorias!B100 -> - | C102: 0 | D102: =SUM(Abril!$H102:$AL102) -> 0 | E102: =C102-D102 -> 0
B103: =Categorias!B101 -> - | C103: 0 | D103: =SUM(Abril!$H103:$AL103) -> 0 | E103: =C103-D103 -> 0
B104: =Categorias!B102 -> - | C104: 0 | D104: =SUM(Abril!$H104:$AL104) -> 0 | E104: =C104-D104 -> 0
B105: =Categorias!B103 -> - | C105: 0 | D105: =SUM(Abril!$H105:$AL105) -> 0 | E105: =C105-D105 -> 0
B107: =Categorias!B105 -> DESARROLLO PERSONAL | C107: =SUM(C108:C113) -> 0 | D107: =SUM(D108:D113) -> 0 | E107: =SUM(E108:E113) -> 0 | H107: 1 | I107: 2 | J107: 3 | K107: 4 | L107: 5 | M107: 6 | N107: 7 | O107: 8 | P107: 9 | Q107: 10 | R107: 11 | S107: 12 | T107: 13 | U107: 14 | V107: 15 | W107: 16 | X107: 17 | Y107: 18 | Z107: 19 | AA107: 20 | AB107: 21 | AC107: 22 | AD107: 23 | AE107: 24 | AF107: 25 | AG107: 26 | AH107: 27 | AI107: 28 | AJ107: 29 | AK107: 30 | AL107: 31
B108: =Categorias!B106 -> Libros | C108: 0 | D108: =SUM(Abril!$H108:$AL108) -> 0 | E108: =C108-D108 -> 0
B109: =Categorias!B107 -> Platzi | C109: 0 | D109: =SUM(Abril!$H109:$AL109) -> 0 | E109: =C109-D109 -> 0
B110: =Categorias!B108 -> Papeleria | C110: 0 | D110: =SUM(Abril!$H110:$AL110) -> 0 | E110: =C110-D110 -> 0
B111: =Categorias!B109 -> Inglés Thiago | C111: 0 | D111: =SUM(Abril!$H111:$AL111) -> 0 | E111: =C111-D111 -> 0
B112: =Categorias!B110 -> Arte Thiago | C112: 0 | D112: =SUM(Abril!$H112:$AL112) -> 0 | E112: =C112-D112 -> 0
B113: =Categorias!B111 -> Escuela kary | C113: 0 | D113: =SUM(Abril!$H113:$AL113) -> 0 | E113: =C113-D113 -> 0
B115: =Categorias!B113 -> DIVERSIÓN | C115: =SUM(C116:C124) -> 0 | D115: =SUM(D116:D124) -> 1000 | E115: =SUM(E116:E124) -> -1000 | H115: 1 | I115: 2 | J115: 3 | K115: 4 | L115: 5 | M115: 6 | N115: 7 | O115: 8 | P115: 9 | Q115: 10 | R115: 11 | S115: 12 | T115: 13 | U115: 14 | V115: 15 | W115: 16 | X115: 17 | Y115: 18 | Z115: 19 | AA115: 20 | AB115: 21 | AC115: 22 | AD115: 23 | AE115: 24 | AF115: 25 | AG115: 26 | AH115: 27 | AI115: 28 | AJ115: 29 | AK115: 30 | AL115: 31
B116: =Categorias!B114 -> Cine/teatro | C116: 0 | D116: =SUM(Abril!$H116:$AL116) -> 1000 | E116: =C116-D116 -> -1000 | L116: 1000
B117: =Categorias!B115 -> Gimnasio/piscina | C117: 0 | D117: =SUM(Abril!$H117:$AL117) -> 0 | E117: =C117-D117 -> 0
...

Sheet Mayo
B2: Presupuesto | C2: 44317
C4: Para crear un presupuesto: - A principios de este mes, rellene los campos en amarillo, despues de forma regular registre los gastos de cada dia en la tabla a la derecha - Todos los otros datos se convertirá automáticamente
C5: Fuente: | D5: =HYPERLINK("http://www.aprendizfinanciero.com/","http://www.aprendizfinanciero.com") -> http://www.aprendizfinanciero.com
B6: Ingresos
B8: Categoría | C8: Ingresos previstos | D8: Ingresos reales | E8: Diferencia | F8: Notas
B9: SUMA | C9: =C11 -> 41720.4 | D9: =D11 -> 42720.4 | E9: =E11 -> 1000
B11: =Categorias!B11 -> INGRESOS TOTALES | C11: =SUM(C12:C20) -> 41720.4 | D11: =SUM(D12:D20) -> 42720.4 | E11: =SUM(E12:E20) -> 1000 | H11: 1 | I11: 2 | J11: 3 | K11: 4 | L11: 5 | M11: 6 | N11: 7 | O11: 8 | P11: 9 | Q11: 10 | R11: 11 | S11: 12 | T11: 13 | U11: 14 | V11: 15 | W11: 16 | X11: 17 | Y11: 18 | Z11: 19 | AA11: 20 | AB11: 21 | AC11: 22 | AD11: 23 | AE11: 24 | AF11: 25 | AG11: 26 | AH11: 27 | AI11: 28 | AJ11: 29 | AK11: 30 | AL11: 31
B12: =Categorias!B12 -> Nomina | C12: 41720.4 | D12: =SUM(Mayo!$H12:$AL12) -> 42720.4 | E12: =D12-C12 -> 1000 | T12: 20860.2 | AL12: 21860.2
B13: =Categorias!B13 -> Aguinaldo | C13: 0 | D13: =SUM(Mayo!$H13:$AL13) -> 0 | E13: =D13-C13 -> 0
B14: =Categorias!B14 -> Fondo de ahorro | C14: 0 | D14: =SUM(Mayo!$H14:$AL14) -> 0 | E14: =D14-C14 -> 0
B15: =Categorias!B15 -> Vales despensa | C15: 0 | D15: =SUM(Mayo!$H15:$AL15) -> 0 | E15: =D15-C15 -> 0
B16: =Categorias!B16 -> Vales comedor | C16: 0 | D16: =SUM(Mayo!$H16:$AL16) -> 0 | E16: =D16-C16 -> 0
B17: =Categorias!B17 -> - | C17: 0 | D17: =SUM(Mayo!$H17:$AL17) -> 0 | E17: =D17-C17 -> 0
B18: =Categorias!B18 -> - | C18: 0 | D18: =SUM(Mayo!$H18:$AL18) -> 0 | E18: =D18-C18 -> 0
B19: =Categorias!B19 -> - | C19: 0 | D19: =SUM(Mayo!$H19:$AL19) -> 0 | E19: =D19-C19 -> 0
B20: =Categorias!B20 -> - | C20: 0 | D20: =SUM(Mayo!$H20:$AL20) -> 0 | E20: =D20-C20 -> 0
B23: Gastos | H23: Registre de gastos diarios
B25: Categoría | C25: Gastos previstos | D25: Gastos reales | E25: Diferencia | F25: Notas | H25: Los campos siguientes son para un registro diario de gastos en cada categoría.
B26: SUMA | C26: =C28+C37+C45+C58+C68+C77+C88+C97+C107+C115+C126+C136+C146+C158 -> 24954.85 | D26: =D28+D37+D45+D58+D68+D77+D88+D97+D107+D115+D126+D136+D146+D158 -> 26612 | E26: =E28+E37+E45+E58+E68+E77+E88+E97+E107+E115+E126+E136+E146+E158 -> -1657.15 | H26: Si quieres incluir mas gastos en una celda, por el mismo dia, ingresa "=" y sigue la ecuación, por ejemplo:. = 25 + 20.5
B28: =Categorias!B24 -> ALIMENTOS Y BEBIDAS | C28: =SUM(C29:C35) -> 2000 | D28: =SUM(D29:D35) -> 1898 | E28: =SUM(E29:E35) -> 102 | H28: 1 | I28: 2 | J28: 3 | K28: 4 | L28: 5 | M28: 6 | N28: 7 | O28: 8 | P28: 9 | Q28: 10 | R28: 11 | S28: 12 | T28: 13 | U28: 14 | V28: 15 | W28: 16 | X28: 17 | Y28: 18 | Z28: 19 | AA28: 20 | AB28: 21 | AC28: 22 | AD28: 23 | AE28: 24 | AF28: 25 | AG28: 26 | AH28: 27 | AI28: 28 | AJ28: 29 | AK28: 30 | AL28: 31
B29: =Categorias!B25 -> Restaurantes | C29: 2000 | D29: =SUM(Mayo!$H29:$AL29) -> 1380 | E29: =C29-D29 -> 620 | H29: 380 | P29: 1000
B30: =Categorias!B26 -> Comida Carlos | C30: 0 | D30: =SUM(Mayo!$H30:$AL30) -> 518 | E30: =C30-D30 -> -518 | P30: 310 | Q30: 16 | T30: 66 | W30: 126
B31: =Categorias!B27 -> - | C31: 0 | D31: =SUM(Mayo!$H31:$AL31) -> 0 | E31: =C31-D31 -> 0
B32: =Categorias!B28 -> - | C32: 0 | D32: =SUM(Mayo!$H32:$AL32) -> 0 | E32: =C32-D32 -> 0
B33: =Categorias!B29 -> - | C33: 0 | D33: =SUM(Mayo!$H33:$AL33) -> 0 | E33: =C33-D33 -> 0
B34: =Categorias!B30 -> - | C34: 0 | D34: =SUM(Mayo!$H34:$AL34) -> 0 | E34: =C34-D34 -> 0
B35: =Categorias!B31 -> - | C35: 0 | D35: =SUM(Mayo!$H35:$AL35) -> 0 | E35: =C35-D35 -> 0
B37: =Categorias!B33 -> SALUD | C37: =SUM(C38:C43) -> 600 | D37: =SUM(D38:D43) -> 1055 | E37: =SUM(E38:E43) -> -455 | H37: 1 | I37: 2 | J37: 3 | K37: 4 | L37: 5 | M37: 6 | N37: 7 | O37: 8 | P37: 9 | Q37: 10 | R37: 11 | S37: 12 | T37: 13 | U37: 14 | V37: 15 | W37: 16 | X37: 17 | Y37: 18 | Z37: 19 | AA37: 20 | AB37: 21 | AC37: 22 | AD37: 23 | AE37: 24 | AF37: 25 | AG37: 26 | AH37: 27 | AI37: 28 | AJ37: 29 | AK37: 30 | AL37: 31
B38: =Categorias!B34 -> Gastos en médicos | C38: 0 | D38: =SUM(Mayo!$H38:$AL38) -> 170 | E38: =C38-D38 -> -170 | AB38: 170
B39: =Categorias!B35 -> Medicamentos | C39: 0 | D39: =SUM(Mayo!$H39:$AL39) -> 885 | E39: =C39-D39 -> -885 | H39: 600 | J39: 285
B40: =Categorias!B36 -> Dentista Kary | C40: 600 | D40: =SUM(Mayo!$H40:$AL40) -> 0 | E40: =C40-D40 -> 600
B41: =Categorias!B37 -> Dentista Thiago | C41: 0 | D41: =SUM(Mayo!$H41:$AL41) -> 0 | E41: =C41-D41 -> 0
B42: =Categorias!B38 -> - | C42: 0 | D42: =SUM(Mayo!$H42:$AL42) -> 0 | E42: =C42-D42 -> 0
B43: =Categorias!B39 -> - | C43: 0 | D43: =SUM(Mayo!$H43:$AL43) -> 0 | E43: =C43-D43 -> 0
B45: =Categorias!B41 -> CASA | C45: =SUM(C46:C56) -> 8400 | D45: =SUM(D46:D56) -> 1510 | E45: =SUM(E46:E56) -> 6890 | H45: 1 | I45: 2 | J45: 3 | K45: 4 | L45: 5 | M45: 6 | N45: 7 | O45: 8 | P45: 9 | Q45: 10 | R45: 11 | S45: 12 | T45: 13 | U45: 14 | V45: 15 | W45: 16 | X45: 17 | Y45: 18 | Z45: 19 | AA45: 20 | AB45: 21 | AC45: 22 | AD45: 23 | AE45: 24 | AF45: 25 | AG45: 26 | AH45: 27 | AI45: 28 | AJ45: 29 | AK45: 30 | AL45: 31
B46: =Categorias!B42 -> Reparación | C46: 0 | D46: =SUM(Mayo!$H46:$AL46) -> 1510 | E46: =C46-D46 -> -1510 | N46: 1510
B47: =Categorias!B43 -> Electricidad | C47: 1000 | D47: =SUM(Mayo!$H47:$AL47) -> 0 | E47: =C47-D47 -> 1000
B48: =Categorias!B44 -> Gas | C48: 300 | D48: =SUM(Mayo!$H48:$AL48) -> 0 | E48: =C48-D48 -> 300
B49: =Categorias!B45 -> Casa Claudia | C49: 100 | D49: =SUM(Mayo!$H49:$AL49) -> 0 | E49: =C49-D49 -> 100
B50: =Categorias!B46 -> Muebles/electrodomésticos | C50: 0 | D50: =SUM(Mayo!$H50:$AL50) -> 0 | E50: =C50-D50 -> 0
B51: =Categorias!B47 -> Predial | C51: 5000 | D51: =SUM(Mayo!$H51:$AL51) -> 0 | E51: =C51-D51 -> 5000
B52: =Categorias!B48 -> Renta Cuarto | C52: 2000 | D52: =SUM(Mayo!$H52:$AL52) -> 0 | E52: =C52-D52 -> 2000
B53: =Categorias!B49 -> - | C53: 0 | D53: =SUM(Mayo!$H53:$AL53) -> 0 | E53: =C53-D53 -> 0
B54: =Categorias!B50 -> - | C54: 0 | D54: =SUM(Mayo!$H54:$AL54) -> 0 | E54: =C54-D54 -> 0
B55: =Categorias!B51 -> - | C55: 0 | D55: =SUM(Mayo!$H55:$AL55) -> 0 | E55: =C55-D55 -> 0
B56: =Categorias!B52 -> - | C56: 0 | D56: =SUM(Mayo!$H56:$AL56) -> 0 | E56: =C56-D56 -> 0
B58: =Categorias!B54 -> ROPA Y CALZADO | C58: =SUM(C59:C66) -> 400 | D58: =SUM(D59:D66) -> 1180 | E58: =SUM(E59:E66) -> -780 | H58: 1 | I58: 2 | J58: 3 | K58: 4 | L58: 5 | M58: 6 | N58: 7 | O58: 8 | P58: 9 | Q58: 10 | R58: 11 | S58: 12 | T58: 13 | U58: 14 | V58: 15 | W58: 16 | X58: 17 | Y58: 18 | Z58: 19 | AA58: 20 | AB58: 21 | AC58: 22 | AD58: 23 | AE58: 24 | AF58: 25 | AG58: 26 | AH58: 27 | AI58: 28 | AJ58: 29 | AK58: 30 | AL58: 31
B59: =Categorias!B55 -> Ropa de adultos | C59: 0 | D59: =SUM(Mayo!$H59:$AL59) -> 1000 | E59: =C59-D59 -> -1000 | AA59: 1000
B60: =Categorias!B56 -> Ropa de niños | C60: 400 | D60: =SUM(Mayo!$H60:$AL60) -> 180 | E60: =C60-D60 -> 220 | X60: 180
B61: =Categorias!B57 -> Calzado | C61: 0 | D61: =SUM(Mayo!$H61:$AL61) -> 0 | E61: =C61-D61 -> 0
B62: =Categorias!B58 -> Acessorios | C62: 0 | D62: =SUM(Mayo!$H62:$AL62) -> 0 | E62: =C62-D62 -> 0
B63: =Categorias!B59 -> Joyería | C63: 0 | D63: =SUM(Mayo!$H63:$AL63) -> 0 | E63: =C63-D63 -> 0
B64: =Categorias!B60 -> Otros | C64: 0 | D64: =SUM(Mayo!$H64:$AL64) -> 0 | E64: =C64-D64 -> 0
B65: =Categorias!B61 -> - | C65: 0 | D65: =SUM(Mayo!$H65:$AL65) -> 0 | E65: =C65-D65 -> 0
B66: =Categorias!B62 -> - | C66: 0 | D66: =SUM(Mayo!$H66:$AL66) -> 0 | E66: =C66-D66 -> 0
B68: =Categorias!B64 -> COMUNICACIÓN | C68: =SUM(C69:C75) -> 1385 | D68: =SUM(D69:D75) -> 0 | E68: =SUM(E69:E75) -> 1385 | H68: 1 | I68: 2 | J68: 3 | K68: 4 | L68: 5 | M68: 6 | N68: 7 | O68: 8 | P68: 9 | Q68: 10 | R68: 11 | S68: 12 | T68: 13 | U68: 14 | V68: 15 | W68: 16 | X68: 17 | Y68: 18 | Z68: 19 | AA68: 20 | AB68: 21 | AC68: 22 | AD68: 23 | AE68: 24 | AF68: 25 | AG68: 26 | AH68: 27 | AI68: 28 | AJ68: 29 | AK68: 30 | AL68: 31
B69: =Categorias!B65 -> Cel. Claudia | C69: 289 | D69: =SUM(Mayo!$H69:$AL69) -> 0 | E69: =C69-D69 -> 289
B70: =Categorias!B66 -> Cel. Carlos | C70: 249 | D70: =SUM(Mayo!$H70:$AL70) -> 0 | E70: =C70-D70 -> 249
B71: =Categorias!B67 -> Cel.Kary | C71: 100 | D71: =SUM(Mayo!$H71:$AL71) -> 0 | E71: =C71-D71 -> 100
B72: =Categorias!B68 -> - | C72: 528 | D72: =SUM(Mayo!$H72:$AL72) -> 0 | E72: =C72-D72 -> 528
B73: =Categorias!B69 -> - | C73: 219 | D73: =SUM(Mayo!$H73:$AL73) -> 0 | E73: =C73-D73 -> 219
B74: =Categorias!B70 -> - | C74: 0 | D74: =SUM(Mayo!$H74:$AL74) -> 0 | E74: =C74-D74 -> 0
B75: =Categorias!B71 -> - | C75: 0 | D75: =SUM(Mayo!$H75:$AL75) -> 0 | E75: =C75-D75 -> 0
B77: =Categorias!B75 -> TRANSPORTE | C77: =SUM(C78:C86) -> 3550.68 | D77: =SUM(D78:D86) -> 0 | E77: =SUM(E78:E86) -> 3550.68 | H77: 1 | I77: 2 | J77: 3 | K77: 4 | L77: 5 | M77: 6 | N77: 7 | O77: 8 | P77: 9 | Q77: 10 | R77: 11 | S77: 12 | T77: 13 | U77: 14 | V77: 15 | W77: 16 | X77: 17 | Y77: 18 | Z77: 19 | AA77: 20 | AB77: 21 | AC77: 22 | AD77: 23 | AE77: 24 | AF77: 25 | AG77: 26 | AH77: 27 | AI77: 28 | AJ77: 29 | AK77: 30 | AL77: 31
B78: =Categorias!B76 -> Combustible Fusion | C78: 1600 | D78: =SUM(Mayo!$H78:$AL78) -> 0 | E78: =C78-D78 -> 1600
B79: =Categorias!B77 -> Seguro Fusion | C79: 0 | D79: =SUM(Mayo!$H79:$AL79) -> 0 | E79: =C79-D79 -> 0
B80: =Categorias!B78 -> Mantenimiento Fusion | C80: 1500 | D80: =SUM(Mayo!$H80:$AL80) -> 0 | E80: =C80-D80 -> 1500
B81: =Categorias!B79 -> Derecho vehicular Fusion | C81: 0 | D81: =SUM(Mayo!$H81:$AL81) -> 0 | E81: =C81-D81 -> 0
B82: =Categorias!B80 -> Casetas | C82: 0 | D82: =SUM(Mayo!$H82:$AL82) -> 0 | E82: =C82-D82 -> 0
B83: =Categorias!B81 -> ADO | C83: 0 | D83: =SUM(Mayo!$H83:$AL83) -> 0 | E83: =C83-D83 -> 0
B84: =Categorias!B82 -> - | C84: 450.68 | D84: =SUM(Mayo!$H84:$AL84) -> 0 | E84: =C84-D84 -> 450.68
B85: =Categorias!B83 -> - | C85: 0 | D85: =SUM(Mayo!$H85:$AL85) -> 0 | E85: =C85-D85 -> 0
B86: =Categorias!B84 -> - | C86: 0 | D86: =SUM(Mayo!$H86:$AL86) -> 0 | E86: =C86-D86 -> 0
B88: =Categorias!B86 -> HIGIENE | C88: =SUM(C89:C95) -> 0 | D88: =SUM(D89:D95) -> 420 | E88: =SUM(E89:E95) -> -420 | H88: 1 | I88: 2 | J88: 3 | K88: 4 | L88: 5 | M88: 6 | N88: 7 | O88: 8 | P88: 9 | Q88: 10 | R88: 11 | S88: 12 | T88: 13 | U88: 14 | V88: 15 | W88: 16 | X88: 17 | Y88: 18 | Z88: 19 | AA88: 20 | AB88: 21 | AC88: 22 | AD88: 23 | AE88: 24 | AF88: 25 | AG88: 26 | AH88: 27 | AI88: 28 | AJ88: 29 | AK88: 30 | AL88: 31
B89: =Categorias!B87 -> Cosmeticos | C89: 0 | D89: =SUM(Mayo!$H89:$AL89) -> 420 | E89: =C89-D89 -> -420 | Q89: 137 | X89: 283
B90: =Categorias!B88 -> Peluquería / S. Belleza | C90: 0 | D90: =SUM(Mayo!$H90:$AL90) -> 0 | E90: =C90-D90 -> 0
B91: =Categorias!B89 -> Lavanderia | C91: 0 | D91: =SUM(Mayo!$H91:$AL91) -> 0 | E91: =C91-D91 -> 0
B92: =Categorias!B90 -> Productos de limpieza | C92: 0 | D92: =SUM(Mayo!$H92:$AL92) -> 0 | E92: =C92-D92 -> 0
B93: =Categorias!B91 -> Otros | C93: 0 | D93: =SUM(Mayo!$H93:$AL93) -> 0 | E93: =C93-D93 -> 0
B94: =Categorias!B92 -> - | C94: 0 | D94: =SUM(Mayo!$H94:$AL94) -> 0 | E94: =C94-D94 -> 0
B95: =Categorias!B93 -> - | C95: 0 | D95: =SUM(Mayo!$H95:$AL95) -> 0 | E95: =C95-D95 -> 0
B97: =Categorias!B95 -> NIÑOS | C97: =SUM(C98:C105) -> 0 | D97: =SUM(D98:D105) -> 0 | E97: =SUM(E98:E105) -> 0 | H97: 1 | I97: 2 | J97: 3 | K97: 4 | L97: 5 | M97: 6 | N97: 7 | O97: 8 | P97: 9 | Q97: 10 | R97: 11 | S97: 12 | T97: 13 | U97: 14 | V97: 15 | W97: 16 | X97: 17 | Y97: 18 | Z97: 19 | AA97: 20 | AB97: 21 | AC97: 22 | AD97: 23 | AE97: 24 | AF97: 25 | AG97: 26 | AH97: 27 | AI97: 28 | AJ97: 29 | AK97: 30 | AL97: 31
B98: =Categorias!B96 -> Jugetes/juegos | C98: 0 | D98: =SUM(Mayo!$H98:$AL98) -> 0 | E98: =C98-D98 -> 0
B99: =Categorias!B97 -> - | C99: 0 | D99: =SUM(Mayo!$H99:$AL99) -> 0 | E99: =C99-D99 -> 0
B100: =Categorias!B98 -> - | C100: 0 | D100: =SUM(Mayo!$H100:$AL100) -> 0 | E100: =C100-D100 -> 0
B101: =Categorias!B99 -> - | C101: 0 | D101: =SUM(Mayo!$H101:$AL101) -> 0 | E101: =C101-D101 -> 0
B102: =Categorias!B100 -> - | C102: 0 | D102: =SUM(Mayo!$H102:$AL102) -> 0 | E102: =C102-D102 -> 0
B103: =Categorias!B101 -> - | C103: 0 | D103: =SUM(Mayo!$H103:$AL103) -> 0 | E103: =C103-D103 -> 0
B104: =Categorias!B102 -> - | C104: 0 | D104: =SUM(Mayo!$H104:$AL104) -> 0 | E104: =C104-D104 -> 0
B105: =Categorias!B103 -> - | C105: 0 | D105: =SUM(Mayo!$H105:$AL105) -> 0 | E105: =C105-D105 -> 0
B107: =Categorias!B105 -> DESARROLLO PERSONAL | C107: =SUM(C108:C113) -> 0 | D107: =SUM(D108:D113) -> 312 | E107: =SUM(E108:E113) -> -312 | H107: 1 | I107: 2 | J107: 3 | K107: 4 | L107: 5 | M107: 6 | N107: 7 | O107: 8 | P107: 9 | Q107: 10 | R107: 11 | S107: 12 | T107: 13 | U107: 14 | V107: 15 | W107: 16 | X107: 17 | Y107: 18 | Z107: 19 | AA107: 20 | AB107: 21 | AC107: 22 | AD107: 23 | AE107: 24 | AF107: 25 | AG107: 26 | AH107: 27 | AI107: 28 | AJ107: 29 | AK107: 30 | AL107: 31
B108: =Categorias!B106 -> Libros | C108: 0 | D108: =SUM(Mayo!$H108:$AL108) -> 312 | E108: =C108-D108 -> -312 | X108: 312
B109: =Categorias!B107 -> Platzi | C109: 0 | D109: =SUM(Mayo!$H109:$AL109) -> 0 | E109: =C109-D109 -> 0
B110: =Categorias!B108 -> Papeleria | C110: 0 | D110: =SUM(Mayo!$H110:$AL110) -> 0 | E110: =C110-D110 -> 0
B111: =Categorias!B109 -> Inglés Thiago | C111: 0 | D111: =SUM(Mayo!$H111:$AL111) -> 0 | E111: =C111-D111 -> 0
B112: =Categorias!B110 -> Arte Thiago | C112: 0 | D112: =SUM(Mayo!$H112:$AL112) -> 0 | E112: =C112-D112 -> 0
B113: =Categorias!B111 -> Escuela kary | C113: 0 | D113: =SUM(Mayo!$H113:$AL113) -> 0 | E113: =C113-D113 -> 0
B115: =Categorias!B113 -> DIVERSIÓN | C115: =SUM(C116:C124) -> 0 | D115: =SUM(D116:D124) -> 0 | E115: =SUM(E116:E124) -> 0 | H115: 1 | I115: 2 | J115: 3 | K115: 4 | L115: 5 | M115: 6 | N115: 7 | O115: 8 | P115: 9 | Q115: 10 | R115: 11 | S115: 12 | T115: 13 | U115: 14 | V115: 15 | W115: 16 | X115: 17 | Y115: 18 | Z115: 19 | AA115: 20 | AB115: 21 | AC115: 22 | AD115: 23 | AE115: 24 | AF115: 25 | AG115: 26 | AH115: 27 | AI115: 28 | AJ115: 29 | AK115: 30 | AL115: 31
B116: =Categorias!B114 -> Cine/teatro | C116: 0 | D116: =SUM(Mayo!$H116:$AL116) -> 0 | E116: =C116-D116 -> 0
B117: =Categorias!B115 -> Gimnasio/piscina | C117: 0 | D117: =SUM(Mayo!$H117:$AL117) -> 0 | E117: =C117-D117 -> 0
...

Sheet Junio
B2: Presupuesto | C2: 44348
C4: Para crear un presupuesto: - A principios de este mes, rellene los campos en amarillo, despues de forma regular registre los gastos de cada dia en la tabla a la derecha - Todos los otros datos se convertirá automáticamente
C5: Fuente: | D5: =HYPERLINK("http://www.aprendizfinanciero.com/","http://www.aprendizfinanciero.com") -> http://www.aprendizfinanciero.com
B6: Ingresos
B8: Categoría | C8: Ingresos previstos | D8: Ingresos reales | E8: Diferencia | F8: Notas
B9: SUMA | C9: =C11 -> 41720.4 | D9: =D11 -> 41720.4 | E9: =E11 -> 0
B11: =Categorias!B11 -> INGRESOS TOTALES | C11: =SUM(C12:C20) -> 41720.4 | D11: =SUM(D12:D20) -> 41720.4 | E11: =SUM(E12:E20) -> 0 | H11: 1 | I11: 2 | J11: 3 | K11: 4 | L11: 5 | M11: 6 | N11: 7 | O11: 8 | P11: 9 | Q11: 10 | R11: 11 | S11: 12 | T11: 13 | U11: 14 | V11: 15 | W11: 16 | X11: 17 | Y11: 18 | Z11: 19 | AA11: 20 | AB11: 21 | AC11: 22 | AD11: 23 | AE11: 24 | AF11: 25 | AG11: 26 | AH11: 27 | AI11: 28 | AJ11: 29 | AK11: 30 | AL11: 31
B12: =Categorias!B12 -> Nomina | C12: 41720.4 | D12: =SUM(Junio!$H12:$AL12) -> 41720.4 | E12: =D12-C12 -> 0 | V12: 20860.2 | AK12: 20860.2
B13: =Categorias!B13 -> Aguinaldo | C13: 0 | D13: =SUM(Junio!$H13:$AL13) -> 0 | E13: =D13-C13 -> 0
B14: =Categorias!B14 -> Fondo de ahorro | C14: 0 | D14: =SUM(Junio!$H14:$AL14) -> 0 | E14: =D14-C14 -> 0
B15: =Categorias!B15 -> Vales despensa | C15: 0 | D15: =SUM(Junio!$H15:$AL15) -> 0 | E15: =D15-C15 -> 0
B16: =Categorias!B16 -> Vales comedor | C16: 0 | D16: =SUM(Junio!$H16:$AL16) -> 0 | E16: =D16-C16 -> 0
B17: =Categorias!B17 -> - | C17: 0 | D17: =SUM(Junio!$H17:$AL17) -> 0 | E17: =D17-C17 -> 0
B18: =Categorias!B18 -> - | C18: 0 | D18: =SUM(Junio!$H18:$AL18) -> 0 | E18: =D18-C18 -> 0
B19: =Categorias!B19 -> - | C19: 0 | D19: =SUM(Junio!$H19:$AL19) -> 0 | E19: =D19-C19 -> 0
B20: =Categorias!B20 -> - | C20: 0 | D20: =SUM(Junio!$H20:$AL20) -> 0 | E20: =D20-C20 -> 0
B23: Gastos | H23: Registre de gastos diarios
B25: Categoría | C25: Gastos previstos | D25: Gastos reales | E25: Diferencia | F25: Notas | H25: Los campos siguientes son para un registro diario de gastos en cada categoría.
B26: SUMA | C26: =C28+C37+C45+C58+C68+C77+C88+C97+C107+C115+C126+C136+C146+C158 -> 27580.9 | D26: =D28+D37+D45+D58+D68+D77+D88+D97+D107+D115+D126+D136+D146+D158 -> 37985.34 | E26: =E28+E37+E45+E58+E68+E77+E88+E97+E107+E115+E126+E136+E146+E158 -> -10404.44 | H26: Si quieres incluir mas gastos en una celda, por el mismo dia, ingresa "=" y sigue la ecuación, por ejemplo:. = 25 + 20.5
B28: =Categorias!B24 -> ALIMENTOS Y BEBIDAS | C28: =SUM(C29:C35) -> 2000 | D28: =SUM(D29:D35) -> 3576.27 | E28: =SUM(E29:E35) -> -1576.27 | H28: 1 | I28: 2 | J28: 3 | K28: 4 | L28: 5 | M28: 6 | N28: 7 | O28: 8 | P28: 9 | Q28: 10 | R28: 11 | S28: 12 | T28: 13 | U28: 14 | V28: 15 | W28: 16 | X28: 17 | Y28: 18 | Z28: 19 | AA28: 20 | AB28: 21 | AC28: 22 | AD28: 23 | AE28: 24 | AF28: 25 | AG28: 26 | AH28: 27 | AI28: 28 | AJ28: 29 | AK28: 30 | AL28: 31
B29: =Categorias!B25 -> Restaurantes | C29: 500 | D29: =SUM(Junio!$H29:$AL29) -> 3169.27 | E29: =C29-D29 -> -2669.27 | N29: 600 | O29: 200 | S29: =140+795.27 -> 935.27 | U29: =123+28+14 -> 165 | W29: 600 | AC29: 300 | AD29: 75 | AG29: =135+159 -> 294
B30: =Categorias!B26 -> Comida Carlos | C30: 500 | D30: =SUM(Junio!$H30:$AL30) -> 407 | E30: =C30-D30 -> 93 | H30: 170 | I30: 55 | J30: 150 | AG30: 32
B31: =Categorias!B27 -> - | C31: 500 | D31: =SUM(Junio!$H31:$AL31) -> 0 | E31: =C31-D31 -> 500
B32: =Categorias!B28 -> - | C32: 500 | D32: =SUM(Junio!$H32:$AL32) -> 0 | E32: =C32-D32 -> 500
B33: =Categorias!B29 -> - | C33: 0 | D33: =SUM(Junio!$H33:$AL33) -> 0 | E33: =C33-D33 -> 0
B34: =Categorias!B30 -> - | C34: 0 | D34: =SUM(Junio!$H34:$AL34) -> 0 | E34: =C34-D34 -> 0
B35: =Categorias!B31 -> - | C35: 0 | D35: =SUM(Junio!$H35:$AL35) -> 0 | E35: =C35-D35 -> 0
B37: =Categorias!B33 -> SALUD | C37: =SUM(C38:C43) -> 1100 | D37: =SUM(D38:D43) -> 735 | E37: =SUM(E38:E43) -> 365 | H37: 1 | I37: 2 | J37: 3 | K37: 4 | L37: 5 | M37: 6 | N37: 7 | O37: 8 | P37: 9 | Q37: 10 | R37: 11 | S37: 12 | T37: 13 | U37: 14 | V37: 15 | W37: 16 | X37: 17 | Y37: 18 | Z37: 19 | AA37: 20 | AB37: 21 | AC37: 22 | AD37: 23 | AE37: 24 | AF37: 25 | AG37: 26 | AH37: 27 | AI37: 28 | AJ37: 29 | AK37: 30 | AL37: 31
B38: =Categorias!B34 -> Gastos en médicos | C38: 0 | D38: =SUM(Junio!$H38:$AL38) -> 0 | E38: =C38-D38 -> 0
B39: =Categorias!B35 -> Medicamentos | C39: 0 | D39: =SUM(Junio!$H39:$AL39) -> 235 | E39: =C39-D39 -> -235 | W39: 235
B40: =Categorias!B36 -> Dentista Kary | C40: 1100 | D40: =SUM(Junio!$H40:$AL40) -> 500 | E40: =C40-D40 -> 600 | J40: 500
B41: =Categorias!B37 -> Dentista Thiago | C41: 0 | D41: =SUM(Junio!$H41:$AL41) -> 0 | E41: =C41-D41 -> 0
B42: =Categorias!B38 -> - | C42: 0 | D42: =SUM(Junio!$H42:$AL42) -> 0 | E42: =C42-D42 -> 0
B43: =Categorias!B39 -> - | C43: 0 | D43: =SUM(Junio!$H43:$AL43) -> 0 | E43: =C43-D43 -> 0
B45: =Categorias!B41 -> CASA | C45: =SUM(C46:C56) -> 7240 | D45: =SUM(D46:D56) -> 12235 | E45: =SUM(E46:E56) -> -4995 | H45: 1 | I45: 2 | J45: 3 | K45: 4 | L45: 5 | M45: 6 | N45: 7 | O45: 8 | P45: 9 | Q45: 10 | R45: 11 | S45: 12 | T45: 13 | U45: 14 | V45: 15 | W45: 16 | X45: 17 | Y45: 18 | Z45: 19 | AA45: 20 | AB45: 21 | AC45: 22 | AD45: 23 | AE45: 24 | AF45: 25 | AG45: 26 | AH45: 27 | AI45: 28 | AJ45: 29 | AK45: 30 | AL45: 31
B46: =Categorias!B42 -> Reparación | C46: 0 | D46: =SUM(Junio!$H46:$AL46) -> 0 | E46: =C46-D46 -> 0
B47: =Categorias!B43 -> Electricidad | C47: 0 | D47: =SUM(Junio!$H47:$AL47) -> 0 | E47: =C47-D47 -> 0
B48: =Categorias!B44 -> Gas | C48: 240 | D48: =SUM(Junio!$H48:$AL48) -> 235 | E48: =C48-D48 -> 5 | H48: 235
B49: =Categorias!B45 -> Casa Claudia | C49: 0 | D49: =SUM(Junio!$H49:$AL49) -> 0 | E49: =C49-D49 -> 0
B50: =Categorias!B46 -> Muebles/electrodomésticos | C50: 0 | D50: =SUM(Junio!$H50:$AL50) -> 0 | E50: =C50-D50 -> 0
B51: =Categorias!B47 -> Predial | C51: 5000 | D51: =SUM(Junio!$H51:$AL51) -> 10000 | E51: =C51-D51 -> -5000 | H51: 5000 | V51: 5000
B52: =Categorias!B48 -> Renta Cuarto | C52: 2000 | D52: =SUM(Junio!$H52:$AL52) -> 2000 | E52: =C52-D52 -> 0 | H52: 2000
B53: =Categorias!B49 -> - | C53: 0 | D53: =SUM(Junio!$H53:$AL53) -> 0 | E53: =C53-D53 -> 0
B54: =Categorias!B50 -> - | C54: 0 | D54: =SUM(Junio!$H54:$AL54) -> 0 | E54: =C54-D54 -> 0
B55: =Categorias!B51 -> - | C55: 0 | D55: =SUM(Junio!$H55:$AL55) -> 0 | E55: =C55-D55 -> 0
B56: =Categorias!B52 -> - | C56: 0 | D56: =SUM(Junio!$H56:$AL56) -> 0 | E56: =C56-D56 -> 0
B58: =Categorias!B54 -> ROPA Y CALZADO | C58: =SUM(C59:C66) -> 0 | D58: =SUM(D59:D66) -> 279 | E58: =SUM(E59:E66) -> -279 | H58: 1 | I58: 2 | J58: 3 | K58: 4 | L58: 5 | M58: 6 | N58: 7 | O58: 8 | P58: 9 | Q58: 10 | R58: 11 | S58: 12 | T58: 13 | U58: 14 | V58: 15 | W58: 16 | X58: 17 | Y58: 18 | Z58: 19 | AA58: 20 | AB58: 21 | AC58: 22 | AD58: 23 | AE58: 24 | AF58: 25 | AG58: 26 | AH58: 27 | AI58: 28 | AJ58: 29 | AK58: 30 | AL58: 31
B59: =Categorias!B55 -> Ropa de adultos | C59: 0 | D59: =SUM(Junio!$H59:$AL59) -> 0 | E59: =C59-D59 -> 0
B60: =Categorias!B56 -> Ropa de niños | C60: 0 | D60: =SUM(Junio!$H60:$AL60) -> 279 | E60: =C60-D60 -> -279 | S60: 279
B61: =Categorias!B57 -> Calzado | C61: 0 | D61: =SUM(Junio!$H61:$AL61) -> 0 | E61: =C61-D61 -> 0
B62: =Categorias!B58 -> Acessorios | C62: 0 | D62: =SUM(Junio!$H62:$AL62) -> 0 | E62: =C62-D62 -> 0
B63: =Categorias!B59 -> Joyería | C63: 0 | D63: =SUM(Junio!$H63:$AL63) -> 0 | E63: =C63-D63 -> 0
B64: =Categorias!B60 -> Otros | C64: 0 | D64: =SUM(Junio!$H64:$AL64) -> 0 | E64: =C64-D64 -> 0
B65: =Categorias!B61 -> - | C65: 0 | D65: =SUM(Junio!$H65:$AL65) -> 0 | E65: =C65-D65 -> 0
B66: =Categorias!B62 -> - | C66: 0 | D66: =SUM(Junio!$H66:$AL66) -> 0 | E66: =C66-D66 -> 0
B68: =Categorias!B64 -> COMUNICACIÓN | C68: =SUM(C69:C75) -> 750 | D68: =SUM(D69:D75) -> 638 | E68: =SUM(E69:E75) -> 112 | H68: 1 | I68: 2 | J68: 3 | K68: 4 | L68: 5 | M68: 6 | N68: 7 | O68: 8 | P68: 9 | Q68: 10 | R68: 11 | S68: 12 | T68: 13 | U68: 14 | V68: 15 | W68: 16 | X68: 17 | Y68: 18 | Z68: 19 | AA68: 20 | AB68: 21 | AC68: 22 | AD68: 23 | AE68: 24 | AF68: 25 | AG68: 26 | AH68: 27 | AI68: 28 | AJ68: 29 | AK68: 30 | AL68: 31
B69: =Categorias!B65 -> Cel. Claudia | C69: 300 | D69: =SUM(Junio!$H69:$AL69) -> 289 | E69: =C69-D69 -> 11 | U69: 289
B70: =Categorias!B66 -> Cel. Carlos | C70: 250 | D70: =SUM(Junio!$H70:$AL70) -> 249 | E70: =C70-D70 -> 1 | S70: 249
B71: =Categorias!B67 -> Cel.Kary | C71: 200 | D71: =SUM(Junio!$H71:$AL71) -> 100 | E71: =C71-D71 -> 100 | U71: 100
B72: =Categorias!B68 -> - | C72: 0 | D72: =SUM(Junio!$H72:$AL72) -> 0 | E72: =C72-D72 -> 0
B73: =Categorias!B69 -> - | C73: 0 | D73: =SUM(Junio!$H73:$AL73) -> 0 | E73: =C73-D73 -> 0
B74: =Categorias!B70 -> - | C74: 0 | D74: =SUM(Junio!$H74:$AL74) -> 0 | E74: =C74-D74 -> 0
B75: =Categorias!B73 -> - | C75: 0 | D75: =SUM(Junio!$H75:$AL75) -> 0 | E75: =C75-D75 -> 0
B77: =Categorias!B75 -> TRANSPORTE | C77: =SUM(C78:C86) -> 2000 | D77: =SUM(D78:D86) -> 1880.05 | E77: =SUM(E78:E86) -> 119.95 | H77: 1 | I77: 2 | J77: 3 | K77: 4 | L77: 5 | M77: 6 | N77: 7 | O77: 8 | P77: 9 | Q77: 10 | R77: 11 | S77: 12 | T77: 13 | U77: 14 | V77: 15 | W77: 16 | X77: 17 | Y77: 18 | Z77: 19 | AA77: 20 | AB77: 21 | AC77: 22 | AD77: 23 | AE77: 24 | AF77: 25 | AG77: 26 | AH77: 27 | AI77: 28 | AJ77: 29 | AK77: 30 | AL77: 31
B78: =Categorias!B76 -> Combustible Fusion | C78: 2000 | D78: =SUM(Junio!$H78:$AL78) -> 1780.05 | E78: =C78-D78 -> 219.95 | S78: 961.32 | AG78: 818.73
B79: =Categorias!B77 -> Seguro Fusion | C79: 0 | D79: =SUM(Junio!$H79:$AL79) -> 0 | E79: =C79-D79 -> 0
B80: =Categorias!B78 -> Mantenimiento Fusion | C80: 0 | D80: =SUM(Junio!$H80:$AL80) -> 100 | E80: =C80-D80 -> -100 | AD80: 100
B81: =Categorias!B79 -> Derecho vehicular Fusion | C81: 0 | D81: =SUM(Junio!$H81:$AL81) -> 0 | E81: =C81-D81 -> 0
B82: =Categorias!B80 -> Casetas | C82: 0 | D82: =SUM(Junio!$H82:$AL82) -> 0 | E82: =C82-D82 -> 0
B83: =Categorias!B81 -> ADO | C83: 0 | D83: =SUM(Junio!$H83:$AL83) -> 0 | E83: =C83-D83 -> 0
B84: =Categorias!B82 -> - | C84: 0 | D84: =SUM(Junio!$H84:$AL84) -> 0 | E84: =C84-D84 -> 0
B85: =Categorias!B83 -> - | C85: 0 | D85: =SUM(Junio!$H85:$AL85) -> 0 | E85: =C85-D85 -> 0
B86: =Categorias!B84 -> - | C86: 0 | D86: =SUM(Junio!$H86:$AL86) -> 0 | E86: =C86-D86 -> 0
B88: =Categorias!B86 -> HIGIENE | C88: =SUM(C89:C95) -> 0 | D88: =SUM(D89:D95) -> 0 | E88: =SUM(E89:E95) -> 0 | H88: 1 | I88: 2 | J88: 3 | K88: 4 | L88: 5 | M88: 6 | N88: 7 | O88: 8 | P88: 9 | Q88: 10 | R88: 11 | S88: 12 | T88: 13 | U88: 14 | V88: 15 | W88: 16 | X88: 17 | Y88: 18 | Z88: 19 | AA88: 20 | AB88: 21 | AC88: 22 | AD88: 23 | AE88: 24 | AF88: 25 | AG88: 26 | AH88: 27 | AI88: 28 | AJ88: 29 | AK88: 30 | AL88: 31
B89: =Categorias!B87 -> Cosmeticos | C89: 0 | D89: =SUM(Junio!$H89:$AL89) -> 0 | E89: =C89-D89 -> 0
B90: =Categorias!B88 -> Peluquería / S. Belleza | C90: 0 | D90: =SUM(Junio!$H90:$AL90) -> 0 | E90: =C90-D90 -> 0
B91: =Categorias!B89 -> Lavanderia | C91: 0 | D91: =SUM(Junio!$H91:$AL91) -> 0 | E91: =C91-D91 -> 0
B92: =Categorias!B90 -> Productos de limpieza | C92: 0 | D92: =SUM(Junio!$H92:$AL92) -> 0 | E92: =C92-D92 -> 0
B93: =Categorias!B91 -> Otros | C93: 0 | D93: =SUM(Junio!$H93:$AL93) -> 0 | E93: =C93-D93 -> 0
B94: =Categorias!B92 -> - | C94: 0 | D94: =SUM(Junio!$H94:$AL94) -> 0 | E94: =C94-D94 -> 0
B95: =Categorias!B93 -> - | C95: 0 | D95: =SUM(Junio!$H95:$AL95) -> 0 | E95: =C95-D95 -> 0
B97: =Categorias!B95 -> NIÑOS | C97: =SUM(C98:C105) -> 400 | D97: =SUM(D98:D105) -> 0 | E97: =SUM(E98:E105) -> 400 | H97: 1 | I97: 2 | J97: 3 | K97: 4 | L97: 5 | M97: 6 | N97: 7 | O97: 8 | P97: 9 | Q97: 10 | R97: 11 | S97: 12 | T97: 13 | U97: 14 | V97: 15 | W97: 16 | X97: 17 | Y97: 18 | Z97: 19 | AA97: 20 | AB97: 21 | AC97: 22 | AD97: 23 | AE97: 24 | AF97: 25 | AG97: 26 | AH97: 27 | AI97: 28 | AJ97: 29 | AK97: 30 | AL97: 31
B98: =Categorias!B96 -> Jugetes/juegos | C98: 0 | D98: =SUM(Junio!$H98:$AL98) -> 0 | E98: =C98-D98 -> 0
B99: =Categorias!B97 -> - | C99: 0 | D99: =SUM(Junio!$H99:$AL99) -> 0 | E99: =C99-D99 -> 0
B100: =Categorias!B98 -> - | C100: 0 | D100: =SUM(Junio!$H100:$AL100) -> 0 | E100: =C100-D100 -> 0
B101: =Categorias!B99 -> - | C101: 0 | D101: =SUM(Junio!$H101:$AL101) -> 0 | E101: =C101-D101 -> 0
B102: =Categorias!B100 -> - | C102: 400 | D102: =SUM(Junio!$H102:$AL102) -> 0 | E102: =C102-D102 -> 400
B103: =Categorias!B101 -> - | C103: 0 | D103: =SUM(Junio!$H103:$AL103) -> 0 | E103: =C103-D103 -> 0
B104: =Categorias!B102 -> - | C104: 0 | D104: =SUM(Junio!$H104:$AL104) -> 0 | E104: =C104-D104 -> 0
B105: =Categorias!B103 -> - | C105: 0 | D105: =SUM(Junio!$H105:$AL105) -> 0 | E105: =C105-D105 -> 0
B107: =Categorias!B105 -> DESARROLLO PERSONAL | C107: =SUM(C108:C113) -> 0 | D107: =SUM(D108:D113) -> 0 | E107: =SUM(E108:E113) -> 0 | H107: 1 | I107: 2 | J107: 3 | K107: 4 | L107: 5 | M107: 6 | N107: 7 | O107: 8 | P107: 9 | Q107: 10 | R107: 11 | S107: 12 | T107: 13 | U107: 14 | V107: 15 | W107: 16 | X107: 17 | Y107: 18 | Z107: 19 | AA107: 20 | AB107: 21 | AC107: 22 | AD107: 23 | AE107: 24 | AF107: 25 | AG107: 26 | AH107: 27 | AI107: 28 | AJ107: 29 | AK107: 30 | AL107: 31
B108: =Categorias!B106 -> Libros | C108: 0 | D108: =SUM(Junio!$H108:$AL108) -> 0 | E108: =C108-D108 -> 0
B109: =Categorias!B107 -> Platzi | C109: 0 | D109: =SUM(Junio!$H109:$AL109) -> 0 | E109: =C109-D109 -> 0
B110: =Categorias!B108 -> Papeleria | C110: 0 | D110: =SUM(Junio!$H110:$AL110) -> 0 | E110: =C110-D110 -> 0
B111: =Categorias!B109 -> Inglés Thiago | C111: 0 | D111: =SUM(Junio!$H111:$AL111) -> 0 | E111: =C111-D111 -> 0
B112: =Categorias!B110 -> Arte Thiago | C112: 0 | D112: =SUM(Junio!$H112:$AL112) -> 0 | E112: =C112-D112 -> 0
B113: =Categorias!B111 -> Escuela kary | C113: 0 | D113: =SUM(Junio!$H113:$AL113) -> 0 | E113: =C113-D113 -> 0
B115: =Categorias!B113 -> DIVERSIÓN | C115: =SUM(C116:C124) -> 0 | D115: =SUM(D116:D124) -> 1632 | E115: =SUM(E116:E124) -> -1632 | H115: 1 | I115: 2 | J115: 3 | K115: 4 | L115: 5 | M115: 6 | N115: 7 | O115: 8 | P115: 9 | Q115: 10 | R115: 11 | S115: 12 | T115: 13 | U115: 14 | V115: 15 | W115: 16 | X115: 17 | Y115: 18 | Z115: 19 | AA115: 20 | AB115: 21 | AC115: 22 | AD115: 23 | AE115: 24 | AF115: 25 | AG115: 26 | AH115: 27 | AI115: 28 | AJ115: 29 | AK115: 30 | AL115: 31
B116: =Categorias!B114 -> Cine/teatro | C116: 0 | D116: =SUM(Junio!$H116:$AL116) -> 732 | E116: =C116-D116 -> -732 | L116: =262+470 -> 732
B117: =Categorias!B115 -> Gimnasio/piscina | C117: 0 | D117: =SUM(Junio!$H117:$AL117) -> 900 | E117: =C117-D117 -> -900 | AH117: 900
...

Sheet Julio
B2: Presupuesto | C2: 44378
C4: Para crear un presupuesto: - A principios de este mes, rellene los campos en amarillo, despues de forma regular registre los gastos de cada dia en la tabla a la derecha - Todos los otros datos se convertirá automáticamente
C5: Fuente: | D5: =HYPERLINK("http://www.aprendizfinanciero.com/","http://www.aprendizfinanciero.com") -> http://www.aprendizfinanciero.com
B6: Ingresos
B8: Categoría | C8: Ingresos previstos | D8: Ingresos reales | E8: Diferencia | F8: Notas
B9: SUMA | C9: =C11 -> 0 | D9: =D11 -> 0 | E9: =E11 -> 0
B11: =Categorias!B11 -> INGRESOS TOTALES | C11: =SUM(C12:C20) -> 0 | D11: =SUM(D12:D20) -> 0 | E11: =SUM(E12:E20) -> 0 | H11: 1 | I11: 2 | J11: 3 | K11: 4 | L11: 5 | M11: 6 | N11: 7 | O11: 8 | P11: 9 | Q11: 10 | R11: 11 | S11: 12 | T11: 13 | U11: 14 | V11: 15 | W11: 16 | X11: 17 | Y11: 18 | Z11: 19 | AA11: 20 | AB11: 21 | AC11: 22 | AD11: 23 | AE11: 24 | AF11: 25 | AG11: 26 | AH11: 27 | AI11: 28 | AJ11: 29 | AK11: 30 | AL11: 31
B12: =Categorias!B12 -> Nomina | C12: 0 | D12: =SUM(Julio!$H12:$AL12) -> 0 | E12: =D12-C12 -> 0
B13: =Categorias!B13 -> Aguinaldo | C13: 0 | D13: =SUM(Julio!$H13:$AL13) -> 0 | E13: =D13-C13 -> 0
B14: =Categorias!B14 -> Fondo de ahorro | C14: 0 | D14: =SUM(Julio!$H14:$AL14) -> 0 | E14: =D14-C14 -> 0
B15: =Categorias!B15 -> Vales despensa | C15: 0 | D15: =SUM(Julio!$H15:$AL15) -> 0 | E15: =D15-C15 -> 0
B16: =Categorias!B16 -> Vales comedor | C16: 0 | D16: =SUM(Julio!$H16:$AL16) -> 0 | E16: =D16-C16 -> 0
B17: =Categorias!B17 -> - | C17: 0 | D17: =SUM(Julio!$H17:$AL17) -> 0 | E17: =D17-C17 -> 0
B18: =Categorias!B18 -> - | C18: 0 | D18: =SUM(Julio!$H18:$AL18) -> 0 | E18: =D18-C18 -> 0
B19: =Categorias!B19 -> - | C19: 0 | D19: =SUM(Julio!$H19:$AL19) -> 0 | E19: =D19-C19 -> 0
B20: =Categorias!B20 -> - | C20: 0 | D20: =SUM(Julio!$H20:$AL20) -> 0 | E20: =D20-C20 -> 0
B23: Gastos | H23: Registre de gastos diarios
B25: Categoría | C25: Gastos previstos | D25: Gastos reales | E25: Diferencia | F25: Notas | H25: Los campos siguientes son para un registro diario de gastos en cada categoría.
B26: SUMA | C26: =C28+C37+C45+C58+C68+C77+C88+C97+C107+C115+C126+C136+C146+C158 -> 9970.7 | D26: =D28+D37+D45+D58+D68+D77+D88+D97+D107+D115+D126+D136+D146+D158 -> 12964 | E26: =E28+E37+E45+E58+E68+E77+E88+E97+E107+E115+E126+E136+E146+E158 -> -2993.3 | H26: Si quieres incluir mas gastos en una celda, por el mismo dia, ingresa "=" y sigue la ecuación, por ejemplo:. = 25 + 20.5
B28: =Categorias!B24 -> ALIMENTOS Y BEBIDAS | C28: =SUM(C29:C35) -> 0 | D28: =SUM(D29:D35) -> 3264 | E28: =SUM(E29:E35) -> -3264 | H28: 1 | I28: 2 | J28: 3 | K28: 4 | L28: 5 | M28: 6 | N28: 7 | O28: 8 | P28: 9 | Q28: 10 | R28: 11 | S28: 12 | T28: 13 | U28: 14 | V28: 15 | W28: 16 | X28: 17 | Y28: 18 | Z28: 19 | AA28: 20 | AB28: 21 | AC28: 22 | AD28: 23 | AE28: 24 | AF28: 25 | AG28: 26 | AH28: 27 | AI28: 28 | AJ28: 29 | AK28: 30 | AL28: 31
B29: =Categorias!B25 -> Restaurantes | C29: 0 | D29: =SUM(Julio!$H29:$AL29) -> 2804 | E29: =C29-D29 -> -2804 | H29: 285 | J29: 1448 | L29: 199 | M29: 300 | O29: 300 | AB29: 272
B30: =Categorias!B26 -> Comida Carlos | C30: 0 | D30: =SUM(Julio!$H30:$AL30) -> 370 | E30: =C30-D30 -> -370 | I30: 370
B31: =Categorias!B27 -> - | C31: 0 | D31: =SUM(Julio!$H31:$AL31) -> 0 | E31: =C31-D31 -> 0
B32: =Categorias!B28 -> - | C32: 0 | D32: =SUM(Julio!$H32:$AL32) -> 90 | E32: =C32-D32 -> -90 | H32: 90
B33: =Categorias!B29 -> - | C33: 0 | D33: =SUM(Julio!$H33:$AL33) -> 0 | E33: =C33-D33 -> 0
B34: =Categorias!B30 -> - | C34: 0 | D34: =SUM(Julio!$H34:$AL34) -> 0 | E34: =C34-D34 -> 0
B35: =Categorias!B31 -> - | C35: 0 | D35: =SUM(Julio!$H35:$AL35) -> 0 | E35: =C35-D35 -> 0
B37: =Categorias!B33 -> SALUD | C37: =SUM(C38:C43) -> 0 | D37: =SUM(D38:D43) -> 0 | E37: =SUM(E38:E43) -> 0 | H37: 1 | I37: 2 | J37: 3 | K37: 4 | L37: 5 | M37: 6 | N37: 7 | O37: 8 | P37: 9 | Q37: 10 | R37: 11 | S37: 12 | T37: 13 | U37: 14 | V37: 15 | W37: 16 | X37: 17 | Y37: 18 | Z37: 19 | AA37: 20 | AB37: 21 | AC37: 22 | AD37: 23 | AE37: 24 | AF37: 25 | AG37: 26 | AH37: 27 | AI37: 28 | AJ37: 29 | AK37: 30 | AL37: 31
B38: =Categorias!B34 -> Gastos en médicos | C38: 0 | D38: =SUM(Julio!$H38:$AL38) -> 0 | E38: =C38-D38 -> 0
B39: =Categorias!B35 -> Medicamentos | C39: 0 | D39: =SUM(Julio!$H39:$AL39) -> 0 | E39: =C39-D39 -> 0
B40: =Categorias!B36 -> Dentista Kary | C40: 0 | D40: =SUM(Julio!$H40:$AL40) -> 0 | E40: =C40-D40 -> 0
B41: =Categorias!B37 -> Dentista Thiago | C41: 0 | D41: =SUM(Julio!$H41:$AL41) -> 0 | E41: =C41-D41 -> 0
B42: =Categorias!B38 -> - | C42: 0 | D42: =SUM(Julio!$H42:$AL42) -> 0 | E42: =C42-D42 -> 0
B43: =Categorias!B39 -> - | C43: 0 | D43: =SUM(Julio!$H43:$AL43) -> 0 | E43: =C43-D43 -> 0
B45: =Categorias!B41 -> CASA | C45: =SUM(C46:C56) -> 0 | D45: =SUM(D46:D56) -> 7200 | E45: =SUM(E46:E56) -> -7200 | H45: 1 | I45: 2 | J45: 3 | K45: 4 | L45: 5 | M45: 6 | N45: 7 | O45: 8 | P45: 9 | Q45: 10 | R45: 11 | S45: 12 | T45: 13 | U45: 14 | V45: 15 | W45: 16 | X45: 17 | Y45: 18 | Z45: 19 | AA45: 20 | AB45: 21 | AC45: 22 | AD45: 23 | AE45: 24 | AF45: 25 | AG45: 26 | AH45: 27 | AI45: 28 | AJ45: 29 | AK45: 30 | AL45: 31
B46: =Categorias!B42 -> Reparación | C46: 0 | D46: =SUM(Julio!$H46:$AL46) -> 0 | E46: =C46-D46 -> 0
B47: =Categorias!B43 -> Electricidad | C47: 0 | D47: =SUM(Julio!$H47:$AL47) -> 0 | E47: =C47-D47 -> 0
B48: =Categorias!B44 -> Gas | C48: 0 | D48: =SUM(Julio!$H48:$AL48) -> 0 | E48: =C48-D48 -> 0
B49: =Categorias!B45 -> Casa Claudia | C49: 0 | D49: =SUM(Julio!$H49:$AL49) -> 0 | E49: =C49-D49 -> 0
B50: =Categorias!B46 -> Muebles/electrodomésticos | C50: 0 | D50: =SUM(Julio!$H50:$AL50) -> 200 | E50: =C50-D50 -> -200 | O50: 200
B51: =Categorias!B47 -> Predial | C51: 0 | D51: =SUM(Julio!$H51:$AL51) -> 5000 | E51: =C51-D51 -> -5000 | H51: 5000
B52: =Categorias!B48 -> Renta Cuarto | C52: 0 | D52: =SUM(Julio!$H52:$AL52) -> 2000 | E52: =C52-D52 -> -2000 | H52: 2000
B53: =Categorias!B49 -> - | C53: 0 | D53: =SUM(Julio!$H53:$AL53) -> 0 | E53: =C53-D53 -> 0
B54: =Categorias!B50 -> - | C54: 0 | D54: =SUM(Julio!$H54:$AL54) -> 0 | E54: =C54-D54 -> 0
B55: =Categorias!B51 -> - | C55: 0 | D55: =SUM(Julio!$H55:$AL55) -> 0 | E55: =C55-D55 -> 0
B56: =Categorias!B52 -> - | C56: 0 | D56: =SUM(Julio!$H56:$AL56) -> 0 | E56: =C56-D56 -> 0
B58: =Categorias!B54 -> ROPA Y CALZADO | C58: =SUM(C59:C66) -> 0 | D58: =SUM(D59:D66) -> 0 | E58: =SUM(E59:E66) -> 0 | H58: 1 | I58: 2 | J58: 3 | K58: 4 | L58: 5 | M58: 6 | N58: 7 | O58: 8 | P58: 9 | Q58: 10 | R58: 11 | S58: 12 | T58: 13 | U58: 14 | V58: 15 | W58: 16 | X58: 17 | Y58: 18 | Z58: 19 | AA58: 20 | AB58: 21 | AC58: 22 | AD58: 23 | AE58: 24 | AF58: 25 | AG58: 26 | AH58: 27 | AI58: 28 | AJ58: 29 | AK58: 30 | AL58: 31
B59: =Categorias!B55 -> Ropa de adultos | C59: 0 | D59: =SUM(Julio!$H59:$AL59) -> 0 | E59: =C59-D59 -> 0
B60: =Categorias!B56 -> Ropa de niños | C60: 0 | D60: =SUM(Julio!$H60:$AL60) -> 0 | E60: =C60-D60 -> 0
B61: =Categorias!B57 -> Calzado | C61: 0 | D61: =SUM(Julio!$H61:$AL61) -> 0 | E61: =C61-D61 -> 0
B62: =Categorias!B58 -> Acessorios | C62: 0 | D62: =SUM(Julio!$H62:$AL62) -> 0 | E62: =C62-D62 -> 0
B63: =Categorias!B59 -> Joyería | C63: 0 | D63: =SUM(Julio!$H63:$AL63) -> 0 | E63: =C63-D63 -> 0
B64: =Categorias!B60 -> Otros | C64: 0 | D64: =SUM(Julio!$H64:$AL64) -> 0 | E64: =C64-D64 -> 0
B65: =Categorias!B61 -> - | C65: 0 | D65: =SUM(Julio!$H65:$AL65) -> 0 | E65: =C65-D65 -> 0
B66: =Categorias!B62 -> - | C66: 0 | D66: =SUM(Julio!$H66:$AL66) -> 0 | E66: =C66-D66 -> 0
B68: =Categorias!B64 -> COMUNICACIÓN | C68: =SUM(C69:C75) -> 0 | D68: =SUM(D69:D75) -> 0 | E68: =SUM(E69:E75) -> 0 | H68: 1 | I68: 2 | J68: 3 | K68: 4 | L68: 5 | M68: 6 | N68: 7 | O68: 8 | P68: 9 | Q68: 10 | R68: 11 | S68: 12 | T68: 13 | U68: 14 | V68: 15 | W68: 16 | X68: 17 | Y68: 18 | Z68: 19 | AA68: 20 | AB68: 21 | AC68: 22 | AD68: 23 | AE68: 24 | AF68: 25 | AG68: 26 | AH68: 27 | AI68: 28 | AJ68: 29 | AK68: 30 | AL68: 31
B69: =Categorias!B65 -> Cel. Claudia | C69: 0 | D69: =SUM(Julio!$H69:$AL69) -> 0 | E69: =C69-D69 -> 0
B70: =Categorias!B66 -> Cel. Carlos | C70: 0 | D70: =SUM(Julio!$H70:$AL70) -> 0 | E70: =C70-D70 -> 0
B71: =Categorias!B67 -> Cel.Kary | C71: 0 | D71: =SUM(Julio!$H71:$AL71) -> 0 | E71: =C71-D71 -> 0
B72: =Categorias!B68 -> - | C72: 0 | D72: =SUM(Julio!$H72:$AL72) -> 0 | E72: =C72-D72 -> 0
B73: =Categorias!B69 -> - | C73: 0 | D73: =SUM(Julio!$H73:$AL73) -> 0 | E73: =C73-D73 -> 0
B74: =Categorias!B70 -> - | C74: 0 | D74: =SUM(Julio!$H74:$AL74) -> 0 | E74: =C74-D74 -> 0
B75: =Categorias!B73 -> - | C75: 0 | D75: =SUM(Julio!$H75:$AL75) -> 0 | E75: =C75-D75 -> 0
B77: =Categorias!B75 -> TRANSPORTE | C77: =SUM(C78:C86) -> 0 | D77: =SUM(D78:D86) -> 0 | E77: =SUM(E78:E86) -> 0 | H77: 1 | I77: 2 | J77: 3 | K77: 4 | L77: 5 | M77: 6 | N77: 7 | O77: 8 | P77: 9 | Q77: 10 | R77: 11 | S77: 12 | T77: 13 | U77: 14 | V77: 15 | W77: 16 | X77: 17 | Y77: 18 | Z77: 19 | AA77: 20 | AB77: 21 | AC77: 22 | AD77: 23 | AE77: 24 | AF77: 25 | AG77: 26 | AH77: 27 | AI77: 28 | AJ77: 29 | AK77: 30 | AL77: 31
B78: =Categorias!B76 -> Combustible Fusion | C78: 0 | D78: =SUM(Julio!$H78:$AL78) -> 0 | E78: =C78-D78 -> 0
B79: =Categorias!B77 -> Seguro Fusion | C79: 0 | D79: =SUM(Julio!$H79:$AL79) -> 0 | E79: =C79-D79 -> 0
B80: =Categorias!B78 -> Mantenimiento Fusion | C80: 0 | D80: =SUM(Julio!$H80:$AL80) -> 0 | E80: =C80-D80 -> 0
B81: =Categorias!B79 -> Derecho vehicular Fusion | C81: 0 | D81: =SUM(Julio!$H81:$AL81) -> 0 | E81: =C81-D81 -> 0
B82: =Categorias!B80 -> Casetas | C82: 0 | D82: =SUM(Julio!$H82:$AL82) -> 0 | E82: =C82-D82 -> 0
B83: =Categorias!B81 -> ADO | C83: 0 | D83: =SUM(Julio!$H83:$AL83) -> 0 | E83: =C83-D83 -> 0
B84: =Categorias!B82 -> - | C84: 0 | D84: =SUM(Julio!$H84:$AL84) -> 0 | E84: =C84-D84 -> 0
B85: =Categorias!B83 -> - | C85: 0 | D85: =SUM(Julio!$H85:$AL85) -> 0 | E85: =C85-D85 -> 0
B86: =Categorias!B84 -> - | C86: 0 | D86: =SUM(Julio!$H86:$AL86) -> 0 | E86: =C86-D86 -> 0
B88: =Categorias!B86 -> HIGIENE | C88: =SUM(C89:C95) -> 0 | D88: =SUM(D89:D95) -> 0 | E88: =SUM(E89:E95) -> 0 | H88: 1 | I88: 2 | J88: 3 | K88: 4 | L88: 5 | M88: 6 | N88: 7 | O88: 8 | P88: 9 | Q88: 10 | R88: 11 | S88: 12 | T88: 13 | U88: 14 | V88: 15 | W88: 16 | X88: 17 | Y88: 18 | Z88: 19 | AA88: 20 | AB88: 21 | AC88: 22 | AD88: 23 | AE88: 24 | AF88: 25 | AG88: 26 | AH88: 27 | AI88: 28 | AJ88: 29 | AK88: 30 | AL88: 31
B89: =Categorias!B87 -> Cosmeticos | C89: 0 | D89: =SUM(Julio!$H89:$AL89) -> 0 | E89: =C89-D89 -> 0
B90: =Categorias!B88 -> Peluquería / S. Belleza | C90: 0 | D90: =SUM(Julio!$H90:$AL90) -> 0 | E90: =C90-D90 -> 0
B91: =Categorias!B89 -> Lavanderia | C91: 0 | D91: =SUM(Julio!$H91:$AL91) -> 0 | E91: =C91-D91 -> 0
B92: =Categorias!B90 -> Productos de limpieza | C92: 0 | D92: =SUM(Julio!$H92:$AL92) -> 0 | E92: =C92-D92 -> 0
B93: =Categorias!B91 -> Otros | C93: 0 | D93: =SUM(Julio!$H93:$AL93) -> 0 | E93: =C93-D93 -> 0
B94: =Categorias!B92 -> - | C94: 0 | D94: =SUM(Julio!$H94:$AL94) -> 0 | E94: =C94-D94 -> 0
B95: =Categorias!B93 -> - | C95: 0 | D95: =SUM(Julio!$H95:$AL95) -> 0 | E95: =C95-D95 -> 0
B97: =Categorias!B95 -> NIÑOS | C97: =SUM(C98:C105) -> 0 | D97: =SUM(D98:D105) -> 0 | E97: =SUM(E98:E105) -> 0 | H97: 1 | I97: 2 | J97: 3 | K97: 4 | L97: 5 | M97: 6 | N97: 7 | O97: 8 | P97: 9 | Q97: 10 | R97: 11 | S97: 12 | T97: 13 | U97: 14 | V97: 15 | W97: 16 | X97: 17 | Y97: 18 | Z97: 19 | AA97: 20 | AB97: 21 | AC97: 22 | AD97: 23 | AE97: 24 | AF97: 25 | AG97: 26 | AH97: 27 | AI97: 28 | AJ97: 29 | AK97: 30 | AL97: 31
B98: =Categorias!B96 -> Jugetes/juegos | C98: 0 | D98: =SUM(Julio!$H98:$AL98) -> 0 | E98: =C98-D98 -> 0
B99: =Categorias!B97 -> - | C99: 0 | D99: =SUM(Julio!$H99:$AL99) -> 0 | E99: =C99-D99 -> 0
B100: =Categorias!B98 -> - | C100: 0 | D100: =SUM(Julio!$H100:$AL100) -> 0 | E100: =C100-D100 -> 0
B101: =Categorias!B99 -> - | C101: 0 | D101: =SUM(Julio!$H101:$AL101) -> 0 | E101: =C101-D101 -> 0
B102: =Categorias!B100 -> - | C102: 0 | D102: =SUM(Julio!$H102:$AL102) -> 0 | E102: =C102-D102 -> 0
B103: =Categorias!B101 -> - | C103: 0 | D103: =SUM(Julio!$H103:$AL103) -> 0 | E103: =C103-D103 -> 0
B104: =Categorias!B102 -> - | C104: 0 | D104: =SUM(Julio!$H104:$AL104) -> 0 | E104: =C104-D104 -> 0
B105: =Categorias!B103 -> - | C105: 0 | D105: =SUM(Julio!$H105:$AL105) -> 0 | E105: =C105-D105 -> 0
B107: =Categorias!B105 -> DESARROLLO PERSONAL | C107: =SUM(C108:C113) -> 0 | D107: =SUM(D108:D113) -> 0 | E107: =SUM(E108:E113) -> 0 | H107: 1 | I107: 2 | J107: 3 | K107: 4 | L107: 5 | M107: 6 | N107: 7 | O107: 8 | P107: 9 | Q107: 10 | R107: 11 | S107: 12 | T107: 13 | U107: 14 | V107: 15 | W107: 16 | X107: 17 | Y107: 18 | Z107: 19 | AA107: 20 | AB107: 21 | AC107: 22 | AD107: 23 | AE107: 24 | AF107: 25 | AG107: 26 | AH107: 27 | AI107: 28 | AJ107: 29 | AK107: 30 | AL107: 31
B108: =Categorias!B106 -> Libros | C108: 0 | D108: =SUM(Julio!$H108:$AL108) -> 0 | E108: =C108-D108 -> 0
B109: =Categorias!B107 -> Platzi | C109: 0 | D109: =SUM(Julio!$H109:$AL109) -> 0 | E109: =C109-D109 -> 0
B110: =Categorias!B108 -> Papeleria | C110: 0 | D110: =SUM(Julio!$H110:$AL110) -> 0 | E110: =C110-D110 -> 0
B111: =Categorias!B109 -> Inglés Thiago | C111: 0 | D111: =SUM(Julio!$H111:$AL111) -> 0 | E111: =C111-D111 -> 0
B112: =Categorias!B110 -> Arte Thiago | C112: 0 | D112: =SUM(Julio!$H112:$AL112) -> 0 | E112: =C112-D112 -> 0
B113: =Categorias!B111 -> Escuela kary | C113: 0 | D113: =SUM(Julio!$H113:$AL113) -> 0 | E113: =C113-D113 -> 0
B115: =Categorias!B113 -> DIVERSIÓN | C115: =SUM(C116:C124) -> 0 | D115: =SUM(D116:D124) -> 0 | E115: =SUM(E116:E124) -> 0 | H115: 1 | I115: 2 | J115: 3 | K115: 4 | L115: 5 | M115: 6 | N115: 7 | O115: 8 | P115: 9 | Q115: 10 | R115: 11 | S115: 12 | T115: 13 | U115: 14 | V115: 15 | W115: 16 | X115: 17 | Y115: 18 | Z115: 19 | AA115: 20 | AB115: 21 | AC115: 22 | AD115: 23 | AE115: 24 | AF115: 25 | AG115: 26 | AH115: 27 | AI115: 28 | AJ115: 29 | AK115: 30 | AL115: 31
B116: =Categorias!B114 -> Cine/teatro | C116: 0 | D116: =SUM(Julio!$H116:$AL116) -> 0 | E116: =C116-D116 -> 0
B117: =Categorias!B115 -> Gimnasio/piscina | C117: 0 | D117: =SUM(Julio!$H117:$AL117) -> 0 | E117: =C117-D117 -> 0
...

Sheet Agosto
B2: Presupuesto | C2: 44409
C4: Para crear un presupuesto: - A principios de este mes, rellene los campos en amarillo, despues de forma regular registre los gastos de cada dia en la tabla a la derecha - Todos los otros datos se convertirá automáticamente
C5: Fuente: | D5: =HYPERLINK("http://www.aprendizfinanciero.com/","http://www.aprendizfinanciero.com") -> http://www.aprendizfinanciero.com
B6: Ingresos
B8: Categoría | C8: Ingresos previstos | D8: Ingresos reales | E8: Diferencia | F8: Notas
B9: SUMA | C9: =C11 -> 41720.4 | D9: =D11 -> 41720.4 | E9: =E11 -> 0
B11: =Categorias!B11 -> INGRESOS TOTALES | C11: =SUM(C12:C20) -> 41720.4 | D11: =SUM(D12:D20) -> 41720.4 | E11: =SUM(E12:E20) -> 0 | H11: 1 | I11: 2 | J11: 3 | K11: 4 | L11: 5 | M11: 6 | N11: 7 | O11: 8 | P11: 9 | Q11: 10 | R11: 11 | S11: 12 | T11: 13 | U11: 14 | V11: 15 | W11: 16 | X11: 17 | Y11: 18 | Z11: 19 | AA11: 20 | AB11: 21 | AC11: 22 | AD11: 23 | AE11: 24 | AF11: 25 | AG11: 26 | AH11: 27 | AI11: 28 | AJ11: 29 | AK11: 30 | AL11: 31
B12: =Categorias!B12 -> Nomina | C12: 41720.4 | D12: =SUM(Agosto!$H12:$AL12) -> 41720.4 | E12: =D12-C12 -> 0 | V12: 20860.2 | AL12: 20860.2
B13: =Categorias!B13 -> Aguinaldo | C13: 0 | D13: =SUM(Agosto!$H13:$AL13) -> 0 | E13: =D13-C13 -> 0
B14: =Categorias!B14 -> Fondo de ahorro | C14: 0 | D14: =SUM(Agosto!$H14:$AL14) -> 0 | E14: =D14-C14 -> 0
B15: =Categorias!B15 -> Vales despensa | C15: 0 | D15: =SUM(Agosto!$H15:$AL15) -> 0 | E15: =D15-C15 -> 0
B16: =Categorias!B16 -> Vales comedor | C16: 0 | D16: =SUM(Agosto!$H16:$AL16) -> 0 | E16: =D16-C16 -> 0
B17: =Categorias!B17 -> - | C17: 0 | D17: =SUM(Agosto!$H17:$AL17) -> 0 | E17: =D17-C17 -> 0
B18: =Categorias!B18 -> - | C18: 0 | D18: =SUM(Agosto!$H18:$AL18) -> 0 | E18: =D18-C18 -> 0
B19: =Categorias!B19 -> - | C19: 0 | D19: =SUM(Agosto!$H19:$AL19) -> 0 | E19: =D19-C19 -> 0
B20: =Categorias!B20 -> - | C20: 0 | D20: =SUM(Agosto!$H20:$AL20) -> 0 | E20: =D20-C20 -> 0
B23: Gastos | H23: Registre de gastos diarios
B25: Categoría | C25: Gastos previstos | D25: Gastos reales | E25: Diferencia | F25: Notas | H25: Los campos siguientes son para un registro diario de gastos en cada categoría.
B26: SUMA | C26: =C28+C37+C45+C58+C68+C77+C88+C97+C107+C115+C126+C136+C146+C158 -> 28450 | D26: =D28+D37+D45+D58+D68+D77+D88+D97+D107+D115+D126+D136+D146+D158 -> 31090 | E26: =E28+E37+E45+E58+E68+E77+E88+E97+E107+E115+E126+E136+E146+E158 -> -2640 | H26: Si quieres incluir mas gastos en una celda, por el mismo dia, ingresa "=" y sigue la ecuación, por ejemplo:. = 25 + 20.5
B28: =Categorias!B24 -> ALIMENTOS Y BEBIDAS | C28: =SUM(C29:C35) -> 3000 | D28: =SUM(D29:D35) -> 3934 | E28: =SUM(E29:E35) -> -934 | H28: 1 | I28: 2 | J28: 3 | K28: 4 | L28: 5 | M28: 6 | N28: 7 | O28: 8 | P28: 9 | Q28: 10 | R28: 11 | S28: 12 | T28: 13 | U28: 14 | V28: 15 | W28: 16 | X28: 17 | Y28: 18 | Z28: 19 | AA28: 20 | AB28: 21 | AC28: 22 | AD28: 23 | AE28: 24 | AF28: 25 | AG28: 26 | AH28: 27 | AI28: 28 | AJ28: 29 | AK28: 30 | AL28: 31
B29: =Categorias!B25 -> Restaurantes | C29: 3000 | D29: =SUM(Agosto!$H29:$AL29) -> 3422 | E29: =C29-D29 -> -422 | M29: 600 | Q29: 250 | R29: 120 | S29: 297 | T29: 186 | U29: 634 | Y29: 900 | AA29: 45 | AE29: 89 | AF29: 89 | AL29: 212
B30: =Categorias!B26 -> Comida Carlos | C30: 0 | D30: =SUM(Agosto!$H30:$AL30) -> 512 | E30: =C30-D30 -> -512 | P30: 127 | S30: 200 | U30: 138 | Y30: 47
B31: =Categorias!B27 -> - | C31: 0 | D31: =SUM(Agosto!$H31:$AL31) -> 0 | E31: =C31-D31 -> 0
B32: =Categorias!B28 -> - | C32: 0 | D32: =SUM(Agosto!$H32:$AL32) -> 0 | E32: =C32-D32 -> 0
B33: =Categorias!B29 -> - | C33: 0 | D33: =SUM(Agosto!$H33:$AL33) -> 0 | E33: =C33-D33 -> 0
B34: =Categorias!B30 -> - | C34: 0 | D34: =SUM(Agosto!$H34:$AL34) -> 0 | E34: =C34-D34 -> 0
B35: =Categorias!B31 -> - | C35: 0 | D35: =SUM(Agosto!$H35:$AL35) -> 0 | E35: =C35-D35 -> 0
B37: =Categorias!B33 -> SALUD | C37: =SUM(C38:C43) -> 1200 | D37: =SUM(D38:D43) -> 1007 | E37: =SUM(E38:E43) -> 193 | H37: 1 | I37: 2 | J37: 3 | K37: 4 | L37: 5 | M37: 6 | N37: 7 | O37: 8 | P37: 9 | Q37: 10 | R37: 11 | S37: 12 | T37: 13 | U37: 14 | V37: 15 | W37: 16 | X37: 17 | Y37: 18 | Z37: 19 | AA37: 20 | AB37: 21 | AC37: 22 | AD37: 23 | AE37: 24 | AF37: 25 | AG37: 26 | AH37: 27 | AI37: 28 | AJ37: 29 | AK37: 30 | AL37: 31
B38: =Categorias!B34 -> Gastos en médicos | C38: 0 | D38: =SUM(Agosto!$H38:$AL38) -> 0 | E38: =C38-D38 -> 0
B39: =Categorias!B35 -> Medicamentos | C39: 0 | D39: =SUM(Agosto!$H39:$AL39) -> 1007 | E39: =C39-D39 -> -1007 | M39: 300 | U39: 83 | V39: 396 | AF39: 228
B40: =Categorias!B36 -> Dentista Kary | C40: 600 | D40: =SUM(Agosto!$H40:$AL40) -> 0 | E40: =C40-D40 -> 600
B41: =Categorias!B37 -> Dentista Thiago | C41: 600 | D41: =SUM(Agosto!$H41:$AL41) -> 0 | E41: =C41-D41 -> 600
B42: =Categorias!B38 -> - | C42: 0 | D42: =SUM(Agosto!$H42:$AL42) -> 0 | E42: =C42-D42 -> 0
B43: =Categorias!B39 -> - | C43: 0 | D43: =SUM(Agosto!$H43:$AL43) -> 0 | E43: =C43-D43 -> 0
B45: =Categorias!B41 -> CASA | C45: =SUM(C46:C56) -> 7300 | D45: =SUM(D46:D56) -> 8082 | E45: =SUM(E46:E56) -> -782 | H45: 1 | I45: 2 | J45: 3 | K45: 4 | L45: 5 | M45: 6 | N45: 7 | O45: 8 | P45: 9 | Q45: 10 | R45: 11 | S45: 12 | T45: 13 | U45: 14 | V45: 15 | W45: 16 | X45: 17 | Y45: 18 | Z45: 19 | AA45: 20 | AB45: 21 | AC45: 22 | AD45: 23 | AE45: 24 | AF45: 25 | AG45: 26 | AH45: 27 | AI45: 28 | AJ45: 29 | AK45: 30 | AL45: 31
B46: =Categorias!B42 -> Reparación | C46: 0 | D46: =SUM(Agosto!$H46:$AL46) -> 1042 | E46: =C46-D46 -> -1042 | U46: 1042
B47: =Categorias!B43 -> Electricidad | C47: 0 | D47: =SUM(Agosto!$H47:$AL47) -> 0 | E47: =C47-D47 -> 0
B48: =Categorias!B44 -> Gas | C48: 300 | D48: =SUM(Agosto!$H48:$AL48) -> 0 | E48: =C48-D48 -> 300
B49: =Categorias!B45 -> Casa Claudia | C49: 0 | D49: =SUM(Agosto!$H49:$AL49) -> 40 | E49: =C49-D49 -> -40 | U49: 40
B50: =Categorias!B46 -> Muebles/electrodomésticos | C50: 0 | D50: =SUM(Agosto!$H50:$AL50) -> 0 | E50: =C50-D50 -> 0
B51: =Categorias!B47 -> Predial | C51: 5000 | D51: =SUM(Agosto!$H51:$AL51) -> 5000 | E51: =C51-D51 -> 0 | H51: 5000
B52: =Categorias!B48 -> Renta Cuarto | C52: 2000 | D52: =SUM(Agosto!$H52:$AL52) -> 2000 | E52: =C52-D52 -> 0 | H52: 2000
B53: =Categorias!B49 -> - | C53: 0 | D53: =SUM(Agosto!$H53:$AL53) -> 0 | E53: =C53-D53 -> 0
B54: =Categorias!B50 -> - | C54: 0 | D54: =SUM(Agosto!$H54:$AL54) -> 0 | E54: =C54-D54 -> 0
B55: =Categorias!B51 -> - | C55: 0 | D55: =SUM(Agosto!$H55:$AL55) -> 0 | E55: =C55-D55 -> 0
B56: =Categorias!B52 -> - | C56: 0 | D56: =SUM(Agosto!$H56:$AL56) -> 0 | E56: =C56-D56 -> 0
B58: =Categorias!B54 -> ROPA Y CALZADO | C58: =SUM(C59:C66) -> 0 | D58: =SUM(D59:D66) -> 1979 | E58: =SUM(E59:E66) -> -1979 | H58: 1 | I58: 2 | J58: 3 | K58: 4 | L58: 5 | M58: 6 | N58: 7 | O58: 8 | P58: 9 | Q58: 10 | R58: 11 | S58: 12 | T58: 13 | U58: 14 | V58: 15 | W58: 16 | X58: 17 | Y58: 18 | Z58: 19 | AA58: 20 | AB58: 21 | AC58: 22 | AD58: 23 | AE58: 24 | AF58: 25 | AG58: 26 | AH58: 27 | AI58: 28 | AJ58: 29 | AK58: 30 | AL58: 31
B59: =Categorias!B55 -> Ropa de adultos | C59: 0 | D59: =SUM(Agosto!$H59:$AL59) -> 0 | E59: =C59-D59 -> 0
B60: =Categorias!B56 -> Ropa de niños | C60: 0 | D60: =SUM(Agosto!$H60:$AL60) -> 1000 | E60: =C60-D60 -> -1000 | N60: 1000
B61: =Categorias!B57 -> Calzado | C61: 0 | D61: =SUM(Agosto!$H61:$AL61) -> 979 | E61: =C61-D61 -> -979 | N61: 150 | X61: 829
B62: =Categorias!B58 -> Acessorios | C62: 0 | D62: =SUM(Agosto!$H62:$AL62) -> 0 | E62: =C62-D62 -> 0
B63: =Categorias!B59 -> Joyería | C63: 0 | D63: =SUM(Agosto!$H63:$AL63) -> 0 | E63: =C63-D63 -> 0
B64: =Categorias!B60 -> Otros | C64: 0 | D64: =SUM(Agosto!$H64:$AL64) -> 0 | E64: =C64-D64 -> 0
B65: =Categorias!B61 -> - | C65: 0 | D65: =SUM(Agosto!$H65:$AL65) -> 0 | E65: =C65-D65 -> 0
B66: =Categorias!B62 -> - | C66: 0 | D66: =SUM(Agosto!$H66:$AL66) -> 0 | E66: =C66-D66 -> 0
B68: =Categorias!B64 -> COMUNICACIÓN | C68: =SUM(C69:C75) -> 750 | D68: =SUM(D69:D75) -> 1369 | E68: =SUM(E69:E75) -> -619 | H68: 1 | I68: 2 | J68: 3 | K68: 4 | L68: 5 | M68: 6 | N68: 7 | O68: 8 | P68: 9 | Q68: 10 | R68: 11 | S68: 12 | T68: 13 | U68: 14 | V68: 15 | W68: 16 | X68: 17 | Y68: 18 | Z68: 19 | AA68: 20 | AB68: 21 | AC68: 22 | AD68: 23 | AE68: 24 | AF68: 25 | AG68: 26 | AH68: 27 | AI68: 28 | AJ68: 29 | AK68: 30 | AL68: 31
B69: =Categorias!B65 -> Cel. Claudia | C69: 300 | D69: =SUM(Agosto!$H69:$AL69) -> 250 | E69: =C69-D69 -> 50 | U69: 250
B70: =Categorias!B66 -> Cel. Carlos | C70: 250 | D70: =SUM(Agosto!$H70:$AL70) -> 300 | E70: =C70-D70 -> -50 | U70: 300
B71: =Categorias!B67 -> Cel.Kary | C71: 200 | D71: =SUM(Agosto!$H71:$AL71) -> 0 | E71: =C71-D71 -> 200
B72: =Categorias!B68 -> - | C72: 0 | D72: =SUM(Agosto!$H72:$AL72) -> 600 | E72: =C72-D72 -> -600 | U72: 600
B73: =Categorias!B69 -> - | C73: 0 | D73: =SUM(Agosto!$H73:$AL73) -> 219 | E73: =C73-D73 -> -219 | U73: 219
B74: =Categorias!B70 -> - | C74: 0 | D74: =SUM(Agosto!$H74:$AL74) -> 0 | E74: =C74-D74 -> 0
B75: =Categorias!B73 -> - | C75: 0 | D75: =SUM(Agosto!$H75:$AL75) -> 0 | E75: =C75-D75 -> 0
B77: =Categorias!B75 -> TRANSPORTE | C77: =SUM(C78:C86) -> 3500 | D77: =SUM(D78:D86) -> 55 | E77: =SUM(E78:E86) -> 3445 | H77: 1 | I77: 2 | J77: 3 | K77: 4 | L77: 5 | M77: 6 | N77: 7 | O77: 8 | P77: 9 | Q77: 10 | R77: 11 | S77: 12 | T77: 13 | U77: 14 | V77: 15 | W77: 16 | X77: 17 | Y77: 18 | Z77: 19 | AA77: 20 | AB77: 21 | AC77: 22 | AD77: 23 | AE77: 24 | AF77: 25 | AG77: 26 | AH77: 27 | AI77: 28 | AJ77: 29 | AK77: 30 | AL77: 31
B78: =Categorias!B76 -> Combustible Fusion | C78: 2000 | D78: =SUM(Agosto!$H78:$AL78) -> 0 | E78: =C78-D78 -> 2000
B79: =Categorias!B77 -> Seguro Fusion | C79: 0 | D79: =SUM(Agosto!$H79:$AL79) -> 0 | E79: =C79-D79 -> 0
B80: =Categorias!B78 -> Mantenimiento Fusion | C80: 1500 | D80: =SUM(Agosto!$H80:$AL80) -> 55 | E80: =C80-D80 -> 1445 | Y80: 55
B81: =Categorias!B79 -> Derecho vehicular Fusion | C81: 0 | D81: =SUM(Agosto!$H81:$AL81) -> 0 | E81: =C81-D81 -> 0
B82: =Categorias!B80 -> Casetas | C82: 0 | D82: =SUM(Agosto!$H82:$AL82) -> 0 | E82: =C82-D82 -> 0
B83: =Categorias!B81 -> ADO | C83: 0 | D83: =SUM(Agosto!$H83:$AL83) -> 0 | E83: =C83-D83 -> 0
B84: =Categorias!B82 -> - | C84: 0 | D84: =SUM(Agosto!$H84:$AL84) -> 0 | E84: =C84-D84 -> 0
B85: =Categorias!B83 -> - | C85: 0 | D85: =SUM(Agosto!$H85:$AL85) -> 0 | E85: =C85-D85 -> 0
B86: =Categorias!B84 -> - | C86: 0 | D86: =SUM(Agosto!$H86:$AL86) -> 0 | E86: =C86-D86 -> 0
B88: =Categorias!B86 -> HIGIENE | C88: =SUM(C89:C95) -> 200 | D88: =SUM(D89:D95) -> 210 | E88: =SUM(E89:E95) -> -10 | H88: 1 | I88: 2 | J88: 3 | K88: 4 | L88: 5 | M88: 6 | N88: 7 | O88: 8 | P88: 9 | Q88: 10 | R88: 11 | S88: 12 | T88: 13 | U88: 14 | V88: 15 | W88: 16 | X88: 17 | Y88: 18 | Z88: 19 | AA88: 20 | AB88: 21 | AC88: 22 | AD88: 23 | AE88: 24 | AF88: 25 | AG88: 26 | AH88: 27 | AI88: 28 | AJ88: 29 | AK88: 30 | AL88: 31
B89: =Categorias!B87 -> Cosmeticos | C89: 0 | D89: =SUM(Agosto!$H89:$AL89) -> 0 | E89: =C89-D89 -> 0
B90: =Categorias!B88 -> Peluquería / S. Belleza | C90: 200 | D90: =SUM(Agosto!$H90:$AL90) -> 210 | E90: =C90-D90 -> -10 | X90: 210
B91: =Categorias!B89 -> Lavanderia | C91: 0 | D91: =SUM(Agosto!$H91:$AL91) -> 0 | E91: =C91-D91 -> 0
B92: =Categorias!B90 -> Productos de limpieza | C92: 0 | D92: =SUM(Agosto!$H92:$AL92) -> 0 | E92: =C92-D92 -> 0
B93: =Categorias!B91 -> Otros | C93: 0 | D93: =SUM(Agosto!$H93:$AL93) -> 0 | E93: =C93-D93 -> 0
B94: =Categorias!B92 -> - | C94: 0 | D94: =SUM(Agosto!$H94:$AL94) -> 0 | E94: =C94-D94 -> 0
B95: =Categorias!B93 -> - | C95: 0 | D95: =SUM(Agosto!$H95:$AL95) -> 0 | E95: =C95-D95 -> 0
B97: =Categorias!B95 -> NIÑOS | C97: =SUM(C98:C105) -> 0 | D97: =SUM(D98:D105) -> 855 | E97: =SUM(E98:E105) -> -855 | H97: 1 | I97: 2 | J97: 3 | K97: 4 | L97: 5 | M97: 6 | N97: 7 | O97: 8 | P97: 9 | Q97: 10 | R97: 11 | S97: 12 | T97: 13 | U97: 14 | V97: 15 | W97: 16 | X97: 17 | Y97: 18 | Z97: 19 | AA97: 20 | AB97: 21 | AC97: 22 | AD97: 23 | AE97: 24 | AF97: 25 | AG97: 26 | AH97: 27 | AI97: 28 | AJ97: 29 | AK97: 30 | AL97: 31
B98: =Categorias!B96 -> Jugetes/juegos | C98: 0 | D98: =SUM(Agosto!$H98:$AL98) -> 0 | E98: =C98-D98 -> 0
B99: =Categorias!B97 -> - | C99: 0 | D99: =SUM(Agosto!$H99:$AL99) -> 855 | E99: =C99-D99 -> -855 | Q99: 180 | R99: 675
B100: =Categorias!B98 -> - | C100: 0 | D100: =SUM(Agosto!$H100:$AL100) -> 0 | E100: =C100-D100 -> 0
B101: =Categorias!B99 -> - | C101: 0 | D101: =SUM(Agosto!$H101:$AL101) -> 0 | E101: =C101-D101 -> 0
B102: =Categorias!B100 -> - | C102: 0 | D102: =SUM(Agosto!$H102:$AL102) -> 0 | E102: =C102-D102 -> 0
B103: =Categorias!B101 -> - | C103: 0 | D103: =SUM(Agosto!$H103:$AL103) -> 0 | E103: =C103-D103 -> 0
B104: =Categorias!B102 -> - | C104: 0 | D104: =SUM(Agosto!$H104:$AL104) -> 0 | E104: =C104-D104 -> 0
B105: =Categorias!B103 -> - | C105: 0 | D105: =SUM(Agosto!$H105:$AL105) -> 0 | E105: =C105-D105 -> 0
B107: =Categorias!B105 -> DESARROLLO PERSONAL | C107: =SUM(C108:C113) -> 0 | D107: =SUM(D108:D113) -> 0 | E107: =SUM(E108:E113) -> 0 | H107: 1 | I107: 2 | J107: 3 | K107: 4 | L107: 5 | M107: 6 | N107: 7 | O107: 8 | P107: 9 | Q107: 10 | R107: 11 | S107: 12 | T107: 13 | U107: 14 | V107: 15 | W107: 16 | X107: 17 | Y107: 18 | Z107: 19 | AA107: 20 | AB107: 21 | AC107: 22 | AD107: 23 | AE107: 24 | AF107: 25 | AG107: 26 | AH107: 27 | AI107: 28 | AJ107: 29 | AK107: 30 | AL107: 31
B108: =Categorias!B106 -> Libros | C108: 0 | D108: =SUM(Agosto!$H108:$AL108) -> 0 | E108: =C108-D108 -> 0
B109: =Categorias!B107 -> Platzi | C109: 0 | D109: =SUM(Agosto!$H109:$AL109) -> 0 | E109: =C109-D109 -> 0
B110: =Categorias!B108 -> Papeleria | C110: 0 | D110: =SUM(Agosto!$H110:$AL110) -> 0 | E110: =C110-D110 -> 0
B111: =Categorias!B109 -> Inglés Thiago | C111: 0 | D111: =SUM(Agosto!$H111:$AL111) -> 0 | E111: =C111-D111 -> 0
B112: =Categorias!B110 -> Arte Thiago | C112: 0 | D112: =SUM(Agosto!$H112:$AL112) -> 0 | E112: =C112-D112 -> 0
B113: =Categorias!B111 -> Escuela kary | C113: 0 | D113: =SUM(Agosto!$H113:$AL113) -> 0 | E113: =C113-D113 -> 0
B115: =Categorias!B113 -> DIVERSIÓN | C115: =SUM(C116:C124) -> 1300 | D115: =SUM(D116:D124) -> 1300 | E115: =SUM(E116:E124) -> 0 | H115: 1 | I115: 2 | J115: 3 | K115: 4 | L115: 5 | M115: 6 | N115: 7 | O115: 8 | P115: 9 | Q115: 10 | R115: 11 | S115: 12 | T115: 13 | U115: 14 | V115: 15 | W115: 16 | X115: 17 | Y115: 18 | Z115: 19 | AA115: 20 | AB115: 21 | AC115: 22 | AD115: 23 | AE115: 24 | AF115: 25 | AG115: 26 | AH115: 27 | AI115: 28 | AJ115: 29 | AK115: 30 | AL115: 31
B116: =Categorias!B114 -> Cine/teatro | C116: 0 | D116: =SUM(Agosto!$H116:$AL116) -> 0 | E116: =C116-D116 -> 0
B117: =Categorias!B115 -> Gimnasio/piscina | C117: 1300 | D117: =SUM(Agosto!$H117:$AL117) -> 1300 | E117: =C117-D117 -> 0 | AB117: 1300
...

Sheet Septiembre
B2: Presupuesto | C2: 44440
C4: Para crear un presupuesto: - A principios de este mes, rellene los campos en amarillo, despues de forma regular registre los gastos de cada dia en la tabla a la derecha - Todos los otros datos se convertirá automáticamente
C5: Fuente: | D5: =HYPERLINK("http://www.aprendizfinanciero.com/","http://www.aprendizfinanciero.com") -> http://www.aprendizfinanciero.com
B6: Ingresos
B8: Categoría | C8: Ingresos previstos | D8: Ingresos reales | E8: Diferencia | F8: Notas
B9: SUMA | C9: =C11 -> 41720.4 | D9: =D11 -> 0 | E9: =E11 -> -41720.4
B11: =Categorias!B11 -> INGRESOS TOTALES | C11: =SUM(C12:C20) -> 41720.4 | D11: =SUM(D12:D20) -> 0 | E11: =SUM(E12:E20) -> -41720.4 | H11: 1 | I11: 2 | J11: 3 | K11: 4 | L11: 5 | M11: 6 | N11: 7 | O11: 8 | P11: 9 | Q11: 10 | R11: 11 | S11: 12 | T11: 13 | U11: 14 | V11: 15 | W11: 16 | X11: 17 | Y11: 18 | Z11: 19 | AA11: 20 | AB11: 21 | AC11: 22 | AD11: 23 | AE11: 24 | AF11: 25 | AG11: 26 | AH11: 27 | AI11: 28 | AJ11: 29 | AK11: 30 | AL11: 31
B12: =Categorias!B12 -> Nomina | C12: 41720.4 | D12: =SUM(Septiembre!$H12:$AL12) -> 0 | E12: =D12-C12 -> -41720.4
B13: =Categorias!B13 -> Aguinaldo | C13: 0 | D13: =SUM(Septiembre!$H13:$AL13) -> 0 | E13: =D13-C13 -> 0
B14: =Categorias!B14 -> Fondo de ahorro | C14: 0 | D14: =SUM(Septiembre!$H14:$AL14) -> 0 | E14: =D14-C14 -> 0
B15: =Categorias!B15 -> Vales despensa | C15: 0 | D15: =SUM(Septiembre!$H15:$AL15) -> 0 | E15: =D15-C15 -> 0
B16: =Categorias!B16 -> Vales comedor | C16: 0 | D16: =SUM(Septiembre!$H16:$AL16) -> 0 | E16: =D16-C16 -> 0
B17: =Categorias!B17 -> - | C17: 0 | D17: =SUM(Septiembre!$H17:$AL17) -> 0 | E17: =D17-C17 -> 0
B18: =Categorias!B18 -> - | C18: 0 | D18: =SUM(Septiembre!$H18:$AL18) -> 0 | E18: =D18-C18 -> 0
B19: =Categorias!B19 -> - | C19: 0 | D19: =SUM(Septiembre!$H19:$AL19) -> 0 | E19: =D19-C19 -> 0
B20: =Categorias!B20 -> - | C20: 0 | D20: =SUM(Septiembre!$H20:$AL20) -> 0 | E20: =D20-C20 -> 0
B23: Gastos | H23: Registre de gastos diarios
B25: Categoría | C25: Gastos previstos | D25: Gastos reales | E25: Diferencia | F25: Notas | H25: Los campos siguientes son para un registro diario de gastos en cada categoría.
B26: SUMA | C26: =C28+C37+C45+C58+C68+C77+C88+C97+C107+C115+C126+C136+C146+C158 -> 33480 | D26: =D28+D37+D45+D58+D68+D77+D88+D97+D107+D115+D126+D136+D146+D158 -> 29861.25 | E26: =E28+E37+E45+E58+E68+E77+E88+E97+E107+E115+E126+E136+E146+E158 -> 3618.75 | H26: Si quieres incluir mas gastos en una celda, por el mismo dia, ingresa "=" y sigue la ecuación, por ejemplo:. = 25 + 20.5
B28: =Categorias!B24 -> ALIMENTOS Y BEBIDAS | C28: =SUM(C29:C35) -> 3000 | D28: =SUM(D29:D35) -> 3494.25 | E28: =SUM(E29:E35) -> -494.25 | H28: 1 | I28: 2 | J28: 3 | K28: 4 | L28: 5 | M28: 6 | N28: 7 | O28: 8 | P28: 9 | Q28: 10 | R28: 11 | S28: 12 | T28: 13 | U28: 14 | V28: 15 | W28: 16 | X28: 17 | Y28: 18 | Z28: 19 | AA28: 20 | AB28: 21 | AC28: 22 | AD28: 23 | AE28: 24 | AF28: 25 | AG28: 26 | AH28: 27 | AI28: 28 | AJ28: 29 | AK28: 30 | AL28: 31
B29: =Categorias!B25 -> Restaurantes | C29: 3000 | D29: =SUM(Septiembre!$H29:$AL29) -> 3117.25 | E29: =C29-D29 -> -117.25 | K29: 720.25 | M29: 125 | O29: 280 | P29: 50 | Q29: 75 | R29: 350 | S29: 117 | T29: 260 | V29: 160 | X29: 580 | Y29: 400
B30: =Categorias!B26 -> Comida Carlos | C30: 0 | D30: =SUM(Septiembre!$H30:$AL30) -> 377 | E30: =C30-D30 -> -377 | L30: 85 | T30: 73 | Y30: 109 | Z30: 110
B31: =Categorias!B27 -> - | C31: 0 | D31: =SUM(Septiembre!$H31:$AL31) -> 0 | E31: =C31-D31 -> 0
B32: =Categorias!B28 -> - | C32: 0 | D32: =SUM(Septiembre!$H32:$AL32) -> 0 | E32: =C32-D32 -> 0
B33: =Categorias!B29 -> - | C33: 0 | D33: =SUM(Septiembre!$H33:$AL33) -> 0 | E33: =C33-D33 -> 0
B34: =Categorias!B30 -> - | C34: 0 | D34: =SUM(Septiembre!$H34:$AL34) -> 0 | E34: =C34-D34 -> 0
B35: =Categorias!B31 -> - | C35: 0 | D35: =SUM(Septiembre!$H35:$AL35) -> 0 | E35: =C35-D35 -> 0
B37: =Categorias!B33 -> SALUD | C37: =SUM(C38:C43) -> 1200 | D37: =SUM(D38:D43) -> 3370 | E37: =SUM(E38:E43) -> -2170 | H37: 1 | I37: 2 | J37: 3 | K37: 4 | L37: 5 | M37: 6 | N37: 7 | O37: 8 | P37: 9 | Q37: 10 | R37: 11 | S37: 12 | T37: 13 | U37: 14 | V37: 15 | W37: 16 | X37: 17 | Y37: 18 | Z37: 19 | AA37: 20 | AB37: 21 | AC37: 22 | AD37: 23 | AE37: 24 | AF37: 25 | AG37: 26 | AH37: 27 | AI37: 28 | AJ37: 29 | AK37: 30 | AL37: 31
B38: =Categorias!B34 -> Gastos en médicos | C38: 0 | D38: =SUM(Septiembre!$H38:$AL38) -> 510 | E38: =C38-D38 -> -510 | T38: 510
B39: =Categorias!B35 -> Medicamentos | C39: 0 | D39: =SUM(Septiembre!$H39:$AL39) -> 2860 | E39: =C39-D39 -> -2860 | T39: 1100 | U39: 1600 | AC39: 160
B40: =Categorias!B36 -> Dentista Kary | C40: 600 | D40: =SUM(Septiembre!$H40:$AL40) -> 0 | E40: =C40-D40 -> 600
B41: =Categorias!B37 -> Dentista Thiago | C41: 600 | D41: =SUM(Septiembre!$H41:$AL41) -> 0 | E41: =C41-D41 -> 600
B42: =Categorias!B38 -> - | C42: 0 | D42: =SUM(Septiembre!$H42:$AL42) -> 0 | E42: =C42-D42 -> 0
B43: =Categorias!B39 -> - | C43: 0 | D43: =SUM(Septiembre!$H43:$AL43) -> 0 | E43: =C43-D43 -> 0
B45: =Categorias!B41 -> CASA | C45: =SUM(C46:C56) -> 8300 | D45: =SUM(D46:D56) -> 8168 | E45: =SUM(E46:E56) -> 132 | H45: 1 | I45: 2 | J45: 3 | K45: 4 | L45: 5 | M45: 6 | N45: 7 | O45: 8 | P45: 9 | Q45: 10 | R45: 11 | S45: 12 | T45: 13 | U45: 14 | V45: 15 | W45: 16 | X45: 17 | Y45: 18 | Z45: 19 | AA45: 20 | AB45: 21 | AC45: 22 | AD45: 23 | AE45: 24 | AF45: 25 | AG45: 26 | AH45: 27 | AI45: 28 | AJ45: 29 | AK45: 30 | AL45: 31
B46: =Categorias!B42 -> Reparación | C46: 0 | D46: =SUM(Septiembre!$H46:$AL46) -> 0 | E46: =C46-D46 -> 0
B47: =Categorias!B43 -> Electricidad | C47: 1000 | D47: =SUM(Septiembre!$H47:$AL47) -> 953 | E47: =C47-D47 -> 47 | Q47: 953
B48: =Categorias!B44 -> Gas | C48: 300 | D48: =SUM(Septiembre!$H48:$AL48) -> 215 | E48: =C48-D48 -> 85 | S48: 215
B49: =Categorias!B45 -> Casa Claudia | C49: 0 | D49: =SUM(Septiembre!$H49:$AL49) -> 0 | E49: =C49-D49 -> 0
B50: =Categorias!B46 -> Muebles/electrodomésticos | C50: 0 | D50: =SUM(Septiembre!$H50:$AL50) -> 0 | E50: =C50-D50 -> 0
B51: =Categorias!B47 -> Predial | C51: 5000 | D51: =SUM(Septiembre!$H51:$AL51) -> 5000 | E51: =C51-D51 -> 0 | I51: 5000
B52: =Categorias!B48 -> Renta Cuarto | C52: 2000 | D52: =SUM(Septiembre!$H52:$AL52) -> 2000 | E52: =C52-D52 -> 0 | I52: 2000
B53: =Categorias!B49 -> - | C53: 0 | D53: =SUM(Septiembre!$H53:$AL53) -> 0 | E53: =C53-D53 -> 0
B54: =Categorias!B50 -> - | C54: 0 | D54: =SUM(Septiembre!$H54:$AL54) -> 0 | E54: =C54-D54 -> 0
B55: =Categorias!B51 -> - | C55: 0 | D55: =SUM(Septiembre!$H55:$AL55) -> 0 | E55: =C55-D55 -> 0
B56: =Categorias!B52 -> - | C56: 0 | D56: =SUM(Septiembre!$H56:$AL56) -> 0 | E56: =C56-D56 -> 0
B58: =Categorias!B54 -> ROPA Y CALZADO | C58: =SUM(C59:C66) -> 2000 | D58: =SUM(D59:D66) -> 2313 | E58: =SUM(E59:E66) -> -313 | H58: 1 | I58: 2 | J58: 3 | K58: 4 | L58: 5 | M58: 6 | N58: 7 | O58: 8 | P58: 9 | Q58: 10 | R58: 11 | S58: 12 | T58: 13 | U58: 14 | V58: 15 | W58: 16 | X58: 17 | Y58: 18 | Z58: 19 | AA58: 20 | AB58: 21 | AC58: 22 | AD58: 23 | AE58: 24 | AF58: 25 | AG58: 26 | AH58: 27 | AI58: 28 | AJ58: 29 | AK58: 30 | AL58: 31
B59: =Categorias!B55 -> Ropa de adultos | C59: 1000 | D59: =SUM(Septiembre!$H59:$AL59) -> 1000 | E59: =C59-D59 -> 0 | L59: 1000
B60: =Categorias!B56 -> Ropa de niños | C60: 1000 | D60: =SUM(Septiembre!$H60:$AL60) -> 1313 | E60: =C60-D60 -> -313 | K60: 100 | L60: 673 | S60: 540
B61: =Categorias!B57 -> Calzado | C61: 0 | D61: =SUM(Septiembre!$H61:$AL61) -> 0 | E61: =C61-D61 -> 0
B62: =Categorias!B58 -> Acessorios | C62: 0 | D62: =SUM(Septiembre!$H62:$AL62) -> 0 | E62: =C62-D62 -> 0
B63: =Categorias!B59 -> Joyería | C63: 0 | D63: =SUM(Septiembre!$H63:$AL63) -> 0 | E63: =C63-D63 -> 0
B64: =Categorias!B60 -> Otros | C64: 0 | D64: =SUM(Septiembre!$H64:$AL64) -> 0 | E64: =C64-D64 -> 0
B65: =Categorias!B61 -> - | C65: 0 | D65: =SUM(Septiembre!$H65:$AL65) -> 0 | E65: =C65-D65 -> 0
B66: =Categorias!B62 -> - | C66: 0 | D66: =SUM(Septiembre!$H66:$AL66) -> 0 | E66: =C66-D66 -> 0
B68: =Categorias!B64 -> COMUNICACIÓN | C68: =SUM(C69:C75) -> 1570 | D68: =SUM(D69:D75) -> 690 | E68: =SUM(E69:E75) -> 880 | H68: 1 | I68: 2 | J68: 3 | K68: 4 | L68: 5 | M68: 6 | N68: 7 | O68: 8 | P68: 9 | Q68: 10 | R68: 11 | S68: 12 | T68: 13 | U68: 14 | V68: 15 | W68: 16 | X68: 17 | Y68: 18 | Z68: 19 | AA68: 20 | AB68: 21 | AC68: 22 | AD68: 23 | AE68: 24 | AF68: 25 | AG68: 26 | AH68: 27 | AI68: 28 | AJ68: 29 | AK68: 30 | AL68: 31
B69: =Categorias!B65 -> Cel. Claudia | C69: 300 | D69: =SUM(Septiembre!$H69:$AL69) -> 290 | E69: =C69-D69 -> 10 | Q69: 290
B70: =Categorias!B66 -> Cel. Carlos | C70: 250 | D70: =SUM(Septiembre!$H70:$AL70) -> 250 | E70: =C70-D70 -> 0 | Q70: 250
B71: =Categorias!B67 -> Cel.Kary | C71: 200 | D71: =SUM(Septiembre!$H71:$AL71) -> 150 | E71: =C71-D71 -> 50 | K71: 50 | Q71: 50 | S71: 50
B72: =Categorias!B68 -> - | C72: 600 | D72: =SUM(Septiembre!$H72:$AL72) -> 0 | E72: =C72-D72 -> 600
B73: =Categorias!B69 -> - | C73: 220 | D73: =SUM(Septiembre!$H73:$AL73) -> 0 | E73: =C73-D73 -> 220
B74: =Categorias!B70 -> - | C74: 0 | D74: =SUM(Septiembre!$H74:$AL74) -> 0 | E74: =C74-D74 -> 0
B75: =Categorias!B73 -> - | C75: 0 | D75: =SUM(Septiembre!$H75:$AL75) -> 0 | E75: =C75-D75 -> 0
B77: =Categorias!B75 -> TRANSPORTE | C77: =SUM(C78:C86) -> 4000 | D77: =SUM(D78:D86) -> 5160 | E77: =SUM(E78:E86) -> -1160 | H77: 1 | I77: 2 | J77: 3 | K77: 4 | L77: 5 | M77: 6 | N77: 7 | O77: 8 | P77: 9 | Q77: 10 | R77: 11 | S77: 12 | T77: 13 | U77: 14 | V77: 15 | W77: 16 | X77: 17 | Y77: 18 | Z77: 19 | AA77: 20 | AB77: 21 | AC77: 22 | AD77: 23 | AE77: 24 | AF77: 25 | AG77: 26 | AH77: 27 | AI77: 28 | AJ77: 29 | AK77: 30 | AL77: 31
B78: =Categorias!B76 -> Combustible Fusion | C78: 2000 | D78: =SUM(Septiembre!$H78:$AL78) -> 0 | E78: =C78-D78 -> 2000
B79: =Categorias!B77 -> Seguro Fusion | C79: 0 | D79: =SUM(Septiembre!$H79:$AL79) -> 0 | E79: =C79-D79 -> 0
B80: =Categorias!B78 -> Mantenimiento Fusion | C80: 1500 | D80: =SUM(Septiembre!$H80:$AL80) -> 5160 | E80: =C80-D80 -> -3660 | R80: 5000 | V80: 160
B81: =Categorias!B79 -> Derecho vehicular Fusion | C81: 0 | D81: =SUM(Septiembre!$H81:$AL81) -> 0 | E81: =C81-D81 -> 0
B82: =Categorias!B80 -> Casetas | C82: 500 | D82: =SUM(Septiembre!$H82:$AL82) -> 0 | E82: =C82-D82 -> 500
B83: =Categorias!B81 -> ADO | C83: 0 | D83: =SUM(Septiembre!$H83:$AL83) -> 0 | E83: =C83-D83 -> 0
B84: =Categorias!B82 -> - | C84: 0 | D84: =SUM(Septiembre!$H84:$AL84) -> 0 | E84: =C84-D84 -> 0
B85: =Categorias!B83 -> - | C85: 0 | D85: =SUM(Septiembre!$H85:$AL85) -> 0 | E85: =C85-D85 -> 0
B86: =Categorias!B84 -> - | C86: 0 | D86: =SUM(Septiembre!$H86:$AL86) -> 0 | E86: =C86-D86 -> 0
B88: =Categorias!B86 -> HIGIENE | C88: =SUM(C89:C95) -> 210 | D88: =SUM(D89:D95) -> 484 | E88: =SUM(E89:E95) -> -274 | H88: 1 | I88: 2 | J88: 3 | K88: 4 | L88: 5 | M88: 6 | N88: 7 | O88: 8 | P88: 9 | Q88: 10 | R88: 11 | S88: 12 | T88: 13 | U88: 14 | V88: 15 | W88: 16 | X88: 17 | Y88: 18 | Z88: 19 | AA88: 20 | AB88: 21 | AC88: 22 | AD88: 23 | AE88: 24 | AF88: 25 | AG88: 26 | AH88: 27 | AI88: 28 | AJ88: 29 | AK88: 30 | AL88: 31
B89: =Categorias!B87 -> Cosmeticos | C89: 0 | D89: =SUM(Septiembre!$H89:$AL89) -> 484 | E89: =C89-D89 -> -484 | N89: 124 | T89: 360
B90: =Categorias!B88 -> Peluquería / S. Belleza | C90: 210 | D90: =SUM(Septiembre!$H90:$AL90) -> 0 | E90: =C90-D90 -> 210
B91: =Categorias!B89 -> Lavanderia | C91: 0 | D91: =SUM(Septiembre!$H91:$AL91) -> 0 | E91: =C91-D91 -> 0
B92: =Categorias!B90 -> Productos de limpieza | C92: 0 | D92: =SUM(Septiembre!$H92:$AL92) -> 0 | E92: =C92-D92 -> 0
B93: =Categorias!B91 -> Otros | C93: 0 | D93: =SUM(Septiembre!$H93:$AL93) -> 0 | E93: =C93-D93 -> 0
B94: =Categorias!B92 -> - | C94: 0 | D94: =SUM(Septiembre!$H94:$AL94) -> 0 | E94: =C94-D94 -> 0
B95: =Categorias!B93 -> - | C95: 0 | D95: =SUM(Septiembre!$H95:$AL95) -> 0 | E95: =C95-D95 -> 0
B97: =Categorias!B95 -> NIÑOS | C97: =SUM(C98:C105) -> 700 | D97: =SUM(D98:D105) -> 286 | E97: =SUM(E98:E105) -> 414 | H97: 1 | I97: 2 | J97: 3 | K97: 4 | L97: 5 | M97: 6 | N97: 7 | O97: 8 | P97: 9 | Q97: 10 | R97: 11 | S97: 12 | T97: 13 | U97: 14 | V97: 15 | W97: 16 | X97: 17 | Y97: 18 | Z97: 19 | AA97: 20 | AB97: 21 | AC97: 22 | AD97: 23 | AE97: 24 | AF97: 25 | AG97: 26 | AH97: 27 | AI97: 28 | AJ97: 29 | AK97: 30 | AL97: 31
B98: =Categorias!B96 -> Jugetes/juegos | C98: 0 | D98: =SUM(Septiembre!$H98:$AL98) -> 0 | E98: =C98-D98 -> 0
B99: =Categorias!B97 -> - | C99: 500 | D99: =SUM(Septiembre!$H99:$AL99) -> 236 | E99: =C99-D99 -> 264 | K99: 36 | L99: 100 | S99: 100
B100: =Categorias!B98 -> - | C100: 0 | D100: =SUM(Septiembre!$H100:$AL100) -> 0 | E100: =C100-D100 -> 0
B101: =Categorias!B99 -> - | C101: 200 | D101: =SUM(Septiembre!$H101:$AL101) -> 50 | E101: =C101-D101 -> 150 | L101: 50
B102: =Categorias!B100 -> - | C102: 0 | D102: =SUM(Septiembre!$H102:$AL102) -> 0 | E102: =C102-D102 -> 0
B103: =Categorias!B101 -> - | C103: 0 | D103: =SUM(Septiembre!$H103:$AL103) -> 0 | E103: =C103-D103 -> 0
B104: =Categorias!B102 -> - | C104: 0 | D104: =SUM(Septiembre!$H104:$AL104) -> 0 | E104: =C104-D104 -> 0
B105: =Categorias!B103 -> - | C105: 0 | D105: =SUM(Septiembre!$H105:$AL105) -> 0 | E105: =C105-D105 -> 0
B107: =Categorias!B105 -> DESARROLLO PERSONAL | C107: =SUM(C108:C113) -> 0 | D107: =SUM(D108:D113) -> 0 | E107: =SUM(E108:E113) -> 0 | H107: 1 | I107: 2 | J107: 3 | K107: 4 | L107: 5 | M107: 6 | N107: 7 | O107: 8 | P107: 9 | Q107: 10 | R107: 11 | S107: 12 | T107: 13 | U107: 14 | V107: 15 | W107: 16 | X107: 17 | Y107: 18 | Z107: 19 | AA107: 20 | AB107: 21 | AC107: 22 | AD107: 23 | AE107: 24 | AF107: 25 | AG107: 26 | AH107: 27 | AI107: 28 | AJ107: 29 | AK107: 30 | AL107: 31
B108: =Categorias!B106 -> Libros | C108: 0 | D108: =SUM(Septiembre!$H108:$AL108) -> 0 | E108: =C108-D108 -> 0
B109: =Categorias!B107 -> Platzi | C109: 0 | D109: =SUM(Septiembre!$H109:$AL109) -> 0 | E109: =C109-D109 -> 0
B110: =Categorias!B108 -> Papeleria | C110: 0 | D110: =SUM(Septiembre!$H110:$AL110) -> 0 | E110: =C110-D110 -> 0
B111: =Categorias!B109 -> Inglés Thiago | C111: 0 | D111: =SUM(Septiembre!$H111:$AL111) -> 0 | E111: =C111-D111 -> 0
B112: =Categorias!B110 -> Arte Thiago | C112: 0 | D112: =SUM(Septiembre!$H112:$AL112) -> 0 | E112: =C112-D112 -> 0
B113: =Categorias!B111 -> Escuela kary | C113: 0 | D113: =SUM(Septiembre!$H113:$AL113) -> 0 | E113: =C113-D113 -> 0
B115: =Categorias!B113 -> DIVERSIÓN | C115: =SUM(C116:C124) -> 1300 | D115: =SUM(D116:D124) -> 1300 | E115: =SUM(E116:E124) -> 0 | H115: 1 | I115: 2 | J115: 3 | K115: 4 | L115: 5 | M115: 6 | N115: 7 | O115: 8 | P115: 9 | Q115: 10 | R115: 11 | S115: 12 | T115: 13 | U115: 14 | V115: 15 | W115: 16 | X115: 17 | Y115: 18 | Z115: 19 | AA115: 20 | AB115: 21 | AC115: 22 | AD115: 23 | AE115: 24 | AF115: 25 | AG115: 26 | AH115: 27 | AI115: 28 | AJ115: 29 | AK115: 30 | AL115: 31
B116: =Categorias!B114 -> Cine/teatro | C116: 0 | D116: =SUM(Septiembre!$H116:$AL116) -> 0 | E116: =C116-D116 -> 0
B117: =Categorias!B115 -> Gimnasio/piscina | C117: 1300 | D117: =SUM(Septiembre!$H117:$AL117) -> 1300 | E117: =C117-D117 -> 0 | L117: 900 | M117: 400
...

Sheet Octubre
B2: Presupuesto | C2: 44470
C4: Para crear un presupuesto: - A principios de este mes, rellene los campos en amarillo, despues de forma regular registre los gastos de cada dia en la tabla a la derecha - Todos los otros datos se convertirá automáticamente
C5: Fuente: | D5: =HYPERLINK("http://www.aprendizfinanciero.com/","http://www.aprendizfinanciero.com") -> http://www.aprendizfinanciero.com
B6: Ingresos
B8: Categoría | C8: Ingresos previstos | D8: Ingresos reales | E8: Diferencia | F8: Notas
B9: SUMA | C9: =C11 -> 44000 | D9: =D11 -> 0 | E9: =E11 -> -44000
B11: =Categorias!B11 -> INGRESOS TOTALES | C11: =SUM(C12:C20) -> 44000 | D11: =SUM(D12:D20) -> 0 | E11: =SUM(E12:E20) -> -44000 | H11: 1 | I11: 2 | J11: 3 | K11: 4 | L11: 5 | M11: 6 | N11: 7 | O11: 8 | P11: 9 | Q11: 10 | R11: 11 | S11: 12 | T11: 13 | U11: 14 | V11: 15 | W11: 16 | X11: 17 | Y11: 18 | Z11: 19 | AA11: 20 | AB11: 21 | AC11: 22 | AD11: 23 | AE11: 24 | AF11: 25 | AG11: 26 | AH11: 27 | AI11: 28 | AJ11: 29 | AK11: 30 | AL11: 31
B12: =Categorias!B12 -> Nomina | C12: 44000 | D12: =SUM(Octubre!$H12:$AL12) -> 0 | E12: =D12-C12 -> -44000
B13: =Categorias!B13 -> Aguinaldo | C13: 0 | D13: =SUM(Octubre!$H13:$AL13) -> 0 | E13: =D13-C13 -> 0
B14: =Categorias!B14 -> Fondo de ahorro | C14: 0 | D14: =SUM(Octubre!$H14:$AL14) -> 0 | E14: =D14-C14 -> 0
B15: =Categorias!B15 -> Vales despensa | C15: 0 | D15: =SUM(Octubre!$H15:$AL15) -> 0 | E15: =D15-C15 -> 0
B16: =Categorias!B16 -> Vales comedor | C16: 0 | D16: =SUM(Octubre!$H16:$AL16) -> 0 | E16: =D16-C16 -> 0
B17: =Categorias!B17 -> - | C17: 0 | D17: =SUM(Octubre!$H17:$AL17) -> 0 | E17: =D17-C17 -> 0
B18: =Categorias!B18 -> - | C18: 0 | D18: =SUM(Octubre!$H18:$AL18) -> 0 | E18: =D18-C18 -> 0
B19: =Categorias!B19 -> - | C19: 0 | D19: =SUM(Octubre!$H19:$AL19) -> 0 | E19: =D19-C19 -> 0
B20: =Categorias!B20 -> - | C20: 0 | D20: =SUM(Octubre!$H20:$AL20) -> 0 | E20: =D20-C20 -> 0
B23: Gastos | H23: Registre de gastos diarios
B25: Categoría | C25: Gastos previstos | D25: Gastos reales | E25: Diferencia | F25: Notas | H25: Los campos siguientes son para un registro diario de gastos en cada categoría.
B26: SUMA | C26: =C28+C37+C45+C58+C68+C77+C88+C97+C107+C115+C126+C136+C146+C158 -> 32990 | D26: =D28+D37+D45+D58+D68+D77+D88+D97+D107+D115+D126+D136+D146+D158 -> 9788.67 | E26: =E28+E37+E45+E58+E68+E77+E88+E97+E107+E115+E126+E136+E146+E158 -> 23201.33 | H26: Si quieres incluir mas gastos en una celda, por el mismo dia, ingresa "=" y sigue la ecuación, por ejemplo:. = 25 + 20.5
B28: =Categorias!B24 -> ALIMENTOS Y BEBIDAS | C28: =SUM(C29:C35) -> 3000 | D28: =SUM(D29:D35) -> 1246.5 | E28: =SUM(E29:E35) -> 1753.5 | H28: 1 | I28: 2 | J28: 3 | K28: 4 | L28: 5 | M28: 6 | N28: 7 | O28: 8 | P28: 9 | Q28: 10 | R28: 11 | S28: 12 | T28: 13 | U28: 14 | V28: 15 | W28: 16 | X28: 17 | Y28: 18 | Z28: 19 | AA28: 20 | AB28: 21 | AC28: 22 | AD28: 23 | AE28: 24 | AF28: 25 | AG28: 26 | AH28: 27 | AI28: 28 | AJ28: 29 | AK28: 30 | AL28: 31
B29: =Categorias!B25 -> Restaurantes | C29: 3000 | D29: =SUM(Octubre!$H29:$AL29) -> 955.3 | E29: =C29-D29 -> 2044.7 | J29: 422 | Q29: 68 | AC29: 66 | AJ29: 53 | AK29: =40+256.3 -> 296.3 | AL29: =50 -> 50
B30: =Categorias!B26 -> Comida Carlos | C30: 0 | D30: =SUM(Octubre!$H30:$AL30) -> 61.6 | E30: =C30-D30 -> -61.6 | AJ30: 34.6 | AL30: 27
B31: =Categorias!B27 -> - | C31: 0 | D31: =SUM(Octubre!$H31:$AL31) -> 29.6 | E31: =C31-D31 -> -29.6 | AJ31: 29.6
B32: =Categorias!B28 -> - | C32: 0 | D32: =SUM(Octubre!$H32:$AL32) -> 200 | E32: =C32-D32 -> -200 | AL32: 200
B33: =Categorias!B29 -> - | C33: 0 | D33: =SUM(Octubre!$H33:$AL33) -> 0 | E33: =C33-D33 -> 0
B34: =Categorias!B30 -> - | C34: 0 | D34: =SUM(Octubre!$H34:$AL34) -> 0 | E34: =C34-D34 -> 0
B35: =Categorias!B31 -> - | C35: 0 | D35: =SUM(Octubre!$H35:$AL35) -> 0 | E35: =C35-D35 -> 0
B37: =Categorias!B33 -> SALUD | C37: =SUM(C38:C43) -> 0 | D37: =SUM(D38:D43) -> 0 | E37: =SUM(E38:E43) -> 0 | H37: 1 | I37: 2 | J37: 3 | K37: 4 | L37: 5 | M37: 6 | N37: 7 | O37: 8 | P37: 9 | Q37: 10 | R37: 11 | S37: 12 | T37: 13 | U37: 14 | V37: 15 | W37: 16 | X37: 17 | Y37: 18 | Z37: 19 | AA37: 20 | AB37: 21 | AC37: 22 | AD37: 23 | AE37: 24 | AF37: 25 | AG37: 26 | AH37: 27 | AI37: 28 | AJ37: 29 | AK37: 30 | AL37: 31
B38: =Categorias!B34 -> Gastos en médicos | C38: 0 | D38: =SUM(Octubre!$H38:$AL38) -> 0 | E38: =C38-D38 -> 0
B39: =Categorias!B35 -> Medicamentos | C39: 0 | D39: =SUM(Octubre!$H39:$AL39) -> 0 | E39: =C39-D39 -> 0
B40: =Categorias!B36 -> Dentista Kary | C40: 0 | D40: =SUM(Octubre!$H40:$AL40) -> 0 | E40: =C40-D40 -> 0
B41: =Categorias!B37 -> Dentista Thiago | C41: 0 | D41: =SUM(Octubre!$H41:$AL41) -> 0 | E41: =C41-D41 -> 0
B42: =Categorias!B38 -> - | C42: 0 | D42: =SUM(Octubre!$H42:$AL42) -> 0 | E42: =C42-D42 -> 0
B43: =Categorias!B39 -> - | C43: 0 | D43: =SUM(Octubre!$H43:$AL43) -> 0 | E43: =C43-D43 -> 0
B45: =Categorias!B41 -> CASA | C45: =SUM(C46:C56) -> 15500 | D45: =SUM(D46:D56) -> 4099 | E45: =SUM(E46:E56) -> 11401 | H45: 1 | I45: 2 | J45: 3 | K45: 4 | L45: 5 | M45: 6 | N45: 7 | O45: 8 | P45: 9 | Q45: 10 | R45: 11 | S45: 12 | T45: 13 | U45: 14 | V45: 15 | W45: 16 | X45: 17 | Y45: 18 | Z45: 19 | AA45: 20 | AB45: 21 | AC45: 22 | AD45: 23 | AE45: 24 | AF45: 25 | AG45: 26 | AH45: 27 | AI45: 28 | AJ45: 29 | AK45: 30 | AL45: 31
B46: =Categorias!B42 -> Reparación | C46: 0 | D46: =SUM(Octubre!$H46:$AL46) -> 99 | E46: =C46-D46 -> -99 | AJ46: 99
B47: =Categorias!B43 -> Electricidad | C47: 1000 | D47: =SUM(Octubre!$H47:$AL47) -> 0 | E47: =C47-D47 -> 1000
B48: =Categorias!B44 -> Gas | C48: 300 | D48: =SUM(Octubre!$H48:$AL48) -> 0 | E48: =C48-D48 -> 300
B49: =Categorias!B45 -> Casa Claudia | C49: 0 | D49: =SUM(Octubre!$H49:$AL49) -> 0 | E49: =C49-D49 -> 0
B50: =Categorias!B46 -> Muebles/electrodomésticos | C50: 0 | D50: =SUM(Octubre!$H50:$AL50) -> 0 | E50: =C50-D50 -> 0
B51: =Categorias!B47 -> Predial | C51: 12000 | D51: =SUM(Octubre!$H51:$AL51) -> 0 | E51: =C51-D51 -> 12000
B52: =Categorias!B48 -> Renta Cuarto | C52: 0 | D52: =SUM(Octubre!$H52:$AL52) -> 0 | E52: =C52-D52 -> 0
B53: =Categorias!B49 -> - | C53: 0 | D53: =SUM(Octubre!$H53:$AL53) -> 0 | E53: =C53-D53 -> 0
B54: =Categorias!B50 -> - | C54: 2200 | D54: =SUM(Octubre!$H54:$AL54) -> 4000 | E54: =C54-D54 -> -1800 | X54: 4000
B55: =Categorias!B51 -> - | C55: 0 | D55: =SUM(Octubre!$H55:$AL55) -> 0 | E55: =C55-D55 -> 0
B56: =Categorias!B52 -> - | C56: 0 | D56: =SUM(Octubre!$H56:$AL56) -> 0 | E56: =C56-D56 -> 0
B58: =Categorias!B54 -> ROPA Y CALZADO | C58: =SUM(C59:C66) -> 0 | D58: =SUM(D59:D66) -> 0 | E58: =SUM(E59:E66) -> 0 | H58: 1 | I58: 2 | J58: 3 | K58: 4 | L58: 5 | M58: 6 | N58: 7 | O58: 8 | P58: 9 | Q58: 10 | R58: 11 | S58: 12 | T58: 13 | U58: 14 | V58: 15 | W58: 16 | X58: 17 | Y58: 18 | Z58: 19 | AA58: 20 | AB58: 21 | AC58: 22 | AD58: 23 | AE58: 24 | AF58: 25 | AG58: 26 | AH58: 27 | AI58: 28 | AJ58: 29 | AK58: 30 | AL58: 31
B59: =Categorias!B55 -> Ropa de adultos | C59: 0 | D59: =SUM(Octubre!$H59:$AL59) -> 0 | E59: =C59-D59 -> 0
B60: =Categorias!B56 -> Ropa de niños | C60: 0 | D60: =SUM(Octubre!$H60:$AL60) -> 0 | E60: =C60-D60 -> 0
B61: =Categorias!B57 -> Calzado | C61: 0 | D61: =SUM(Octubre!$H61:$AL61) -> 0 | E61: =C61-D61 -> 0
B62: =Categorias!B58 -> Acessorios | C62: 0 | D62: =SUM(Octubre!$H62:$AL62) -> 0 | E62: =C62-D62 -> 0
B63: =Categorias!B59 -> Joyería | C63: 0 | D63: =SUM(Octubre!$H63:$AL63) -> 0 | E63: =C63-D63 -> 0
B64: =Categorias!B60 -> Otros | C64: 0 | D64: =SUM(Octubre!$H64:$AL64) -> 0 | E64: =C64-D64 -> 0
B65: =Categorias!B61 -> - | C65: 0 | D65: =SUM(Octubre!$H65:$AL65) -> 0 | E65: =C65-D65 -> 0
B66: =Categorias!B62 -> - | C66: 0 | D66: =SUM(Octubre!$H66:$AL66) -> 0 | E66: =C66-D66 -> 0
B68: =Categorias!B64 -> COMUNICACIÓN | C68: =SUM(C69:C75) -> 750 | D68: =SUM(D69:D75) -> 0 | E68: =SUM(E69:E75) -> 750 | H68: 1 | I68: 2 | J68: 3 | K68: 4 | L68: 5 | M68: 6 | N68: 7 | O68: 8 | P68: 9 | Q68: 10 | R68: 11 | S68: 12 | T68: 13 | U68: 14 | V68: 15 | W68: 16 | X68: 17 | Y68: 18 | Z68: 19 | AA68: 20 | AB68: 21 | AC68: 22 | AD68: 23 | AE68: 24 | AF68: 25 | AG68: 26 | AH68: 27 | AI68: 28 | AJ68: 29 | AK68: 30 | AL68: 31
B69: =Categorias!B65 -> Cel. Claudia | C69: 300 | D69: =SUM(Octubre!$H69:$AL69) -> 0 | E69: =C69-D69 -> 300
B70: =Categorias!B66 -> Cel. Carlos | C70: 250 | D70: =SUM(Octubre!$H70:$AL70) -> 0 | E70: =C70-D70 -> 250
B71: =Categorias!B67 -> Cel.Kary | C71: 200 | D71: =SUM(Octubre!$H71:$AL71) -> 0 | E71: =C71-D71 -> 200
B72: =Categorias!B68 -> - | C72: 0 | D72: =SUM(Octubre!$H72:$AL72) -> 0 | E72: =C72-D72 -> 0
B73: =Categorias!B69 -> - | C73: 0 | D73: =SUM(Octubre!$H73:$AL73) -> 0 | E73: =C73-D73 -> 0
B74: =Categorias!B70 -> - | C74: 0 | D74: =SUM(Octubre!$H74:$AL74) -> 0 | E74: =C74-D74 -> 0
B75: =Categorias!B73 -> - | C75: 0 | D75: =SUM(Octubre!$H75:$AL75) -> 0 | E75: =C75-D75 -> 0
B77: =Categorias!B75 -> TRANSPORTE | C77: =SUM(C78:C86) -> 6500 | D77: =SUM(D78:D86) -> 4310.67 | E77: =SUM(E78:E86) -> 2189.33 | H77: 1 | I77: 2 | J77: 3 | K77: 4 | L77: 5 | M77: 6 | N77: 7 | O77: 8 | P77: 9 | Q77: 10 | R77: 11 | S77: 12 | T77: 13 | U77: 14 | V77: 15 | W77: 16 | X77: 17 | Y77: 18 | Z77: 19 | AA77: 20 | AB77: 21 | AC77: 22 | AD77: 23 | AE77: 24 | AF77: 25 | AG77: 26 | AH77: 27 | AI77: 28 | AJ77: 29 | AK77: 30 | AL77: 31
B78: =Categorias!B76 -> Combustible Fusion | C78: 4000 | D78: =SUM(Octubre!$H78:$AL78) -> 2594.67 | E78: =C78-D78 -> 1405.33 | O78: 794.66 | P78: 971.36 | AI78: 828.65
B79: =Categorias!B77 -> Seguro Fusion | C79: 0 | D79: =SUM(Octubre!$H79:$AL79) -> 0 | E79: =C79-D79 -> 0
B80: =Categorias!B78 -> Mantenimiento Fusion | C80: 1500 | D80: =SUM(Octubre!$H80:$AL80) -> 897 | E80: =C80-D80 -> 603 | AL80: 897
B81: =Categorias!B79 -> Derecho vehicular Fusion | C81: 0 | D81: =SUM(Octubre!$H81:$AL81) -> 0 | E81: =C81-D81 -> 0
B82: =Categorias!B80 -> Casetas | C82: 1000 | D82: =SUM(Octubre!$H82:$AL82) -> 819 | E82: =C82-D82 -> 181 | K82: 234 | O82: 117 | P82: 117 | AI82: 234 | AL82: 117
B83: =Categorias!B81 -> ADO | C83: 0 | D83: =SUM(Octubre!$H83:$AL83) -> 0 | E83: =C83-D83 -> 0
B84: =Categorias!B82 -> - | C84: 0 | D84: =SUM(Octubre!$H84:$AL84) -> 0 | E84: =C84-D84 -> 0
B85: =Categorias!B83 -> - | C85: 0 | D85: =SUM(Octubre!$H85:$AL85) -> 0 | E85: =C85-D85 -> 0
B86: =Categorias!B84 -> - | C86: 0 | D86: =SUM(Octubre!$H86:$AL86) -> 0 | E86: =C86-D86 -> 0
B88: =Categorias!B86 -> HIGIENE | C88: =SUM(C89:C95) -> 140 | D88: =SUM(D89:D95) -> 132.5 | E88: =SUM(E89:E95) -> 7.5 | H88: 1 | I88: 2 | J88: 3 | K88: 4 | L88: 5 | M88: 6 | N88: 7 | O88: 8 | P88: 9 | Q88: 10 | R88: 11 | S88: 12 | T88: 13 | U88: 14 | V88: 15 | W88: 16 | X88: 17 | Y88: 18 | Z88: 19 | AA88: 20 | AB88: 21 | AC88: 22 | AD88: 23 | AE88: 24 | AF88: 25 | AG88: 26 | AH88: 27 | AI88: 28 | AJ88: 29 | AK88: 30 | AL88: 31
B89: =Categorias!B87 -> Cosmeticos | C89: 0 | D89: =SUM(Octubre!$H89:$AL89) -> 99 | E89: =C89-D89 -> -99 | AJ89: 99
B90: =Categorias!B88 -> Peluquería / S. Belleza | C90: 140 | D90: =SUM(Octubre!$H90:$AL90) -> 0 | E90: =C90-D90 -> 140
B91: =Categorias!B89 -> Lavanderia | C91: 0 | D91: =SUM(Octubre!$H91:$AL91) -> 0 | E91: =C91-D91 -> 0
B92: =Categorias!B90 -> Productos de limpieza | C92: 0 | D92: =SUM(Octubre!$H92:$AL92) -> 33.5 | E92: =C92-D92 -> -33.5 | AI92: 33.5
B93: =Categorias!B91 -> Otros | C93: 0 | D93: =SUM(Octubre!$H93:$AL93) -> 0 | E93: =C93-D93 -> 0
B94: =Categorias!B92 -> - | C94: 0 | D94: =SUM(Octubre!$H94:$AL94) -> 0 | E94: =C94-D94 -> 0
B95: =Categorias!B93 -> - | C95: 0 | D95: =SUM(Octubre!$H95:$AL95) -> 0 | E95: =C95-D95 -> 0
B97: =Categorias!B95 -> NIÑOS | C97: =SUM(C98:C105) -> 0 | D97: =SUM(D98:D105) -> 0 | E97: =SUM(E98:E105) -> 0 | H97: 1 | I97: 2 | J97: 3 | K97: 4 | L97: 5 | M97: 6 | N97: 7 | O97: 8 | P97: 9 | Q97: 10 | R97: 11 | S97: 12 | T97: 13 | U97: 14 | V97: 15 | W97: 16 | X97: 17 | Y97: 18 | Z97: 19 | AA97: 20 | AB97: 21 | AC97: 22 | AD97: 23 | AE97: 24 | AF97: 25 | AG97: 26 | AH97: 27 | AI97: 28 | AJ97: 29 | AK97: 30 | AL97: 31
B98: =Categorias!B96 -> Jugetes/juegos | C98: 0 | D98: =SUM(Octubre!$H98:$AL98) -> 0 | E98: =C98-D98 -> 0
B99: =Categorias!B97 -> - | C99: 0 | D99: =SUM(Octubre!$H99:$AL99) -> 0 | E99: =C99-D99 -> 0
B100: =Categorias!B98 -> - | C100: 0 | D100: =SUM(Octubre!$H100:$AL100) -> 0 | E100: =C100-D100 -> 0
B101: =Categorias!B99 -> - | C101: 0 | D101: =SUM(Octubre!$H101:$AL101) -> 0 | E101: =C101-D101 -> 0
B102: =Categorias!B100 -> - | C102: 0 | D102: =SUM(Octubre!$H102:$AL102) -> 0 | E102: =C102-D102 -> 0
B103: =Categorias!B101 -> - | C103: 0 | D103: =SUM(Octubre!$H103:$AL103) -> 0 | E103: =C103-D103 -> 0
B104: =Categorias!B102 -> - | C104: 0 | D104: =SUM(Octubre!$H104:$AL104) -> 0 | E104: =C104-D104 -> 0
B105: =Categorias!B103 -> - | C105: 0 | D105: =SUM(Octubre!$H105:$AL105) -> 0 | E105: =C105-D105 -> 0
B107: =Categorias!B105 -> DESARROLLO PERSONAL | C107: =SUM(C108:C113) -> 0 | D107: =SUM(D108:D113) -> 0 | E107: =SUM(E108:E113) -> 0 | H107: 1 | I107: 2 | J107: 3 | K107: 4 | L107: 5 | M107: 6 | N107: 7 | O107: 8 | P107: 9 | Q107: 10 | R107: 11 | S107: 12 | T107: 13 | U107: 14 | V107: 15 | W107: 16 | X107: 17 | Y107: 18 | Z107: 19 | AA107: 20 | AB107: 21 | AC107: 22 | AD107: 23 | AE107: 24 | AF107: 25 | AG107: 26 | AH107: 27 | AI107: 28 | AJ107: 29 | AK107: 30 | AL107: 31
B108: =Categorias!B106 -> Libros | C108: 0 | D108: =SUM(Octubre!$H108:$AL108) -> 0 | E108: =C108-D108 -> 0
B109: =Categorias!B107 -> Platzi | C109: 0 | D109: =SUM(Octubre!$H109:$AL109) -> 0 | E109: =C109-D109 -> 0
B110: =Categorias!B108 -> Papeleria | C110: 0 | D110: =SUM(Octubre!$H110:$AL110) -> 0 | E110: =C110-D110 -> 0
B111: =Categorias!B109 -> Inglés Thiago | C111: 0 | D111: =SUM(Octubre!$H111:$AL111) -> 0 | E111: =C111-D111 -> 0
B112: =Categorias!B110 -> Arte Thiago | C112: 0 | D112: =SUM(Octubre!$H112:$AL112) -> 0 | E112: =C112-D112 -> 0
B113: =Categorias!B111 -> Escuela kary | C113: 0 | D113: =SUM(Octubre!$H113:$AL113) -> 0 | E113: =C113-D113 -> 0
B115: =Categorias!B113 -> DIVERSIÓN | C115: =SUM(C116:C124) -> 0 | D115: =SUM(D116:D124) -> 0 | E115: =SUM(E116:E124) -> 0 | H115: 1 | I115: 2 | J115: 3 | K115: 4 | L115: 5 | M115: 6 | N115: 7 | O115: 8 | P115: 9 | Q115: 10 | R115: 11 | S115: 12 | T115: 13 | U115: 14 | V115: 15 | W115: 16 | X115: 17 | Y115: 18 | Z115: 19 | AA115: 20 | AB115: 21 | AC115: 22 | AD115: 23 | AE115: 24 | AF115: 25 | AG115: 26 | AH115: 27 | AI115: 28 | AJ115: 29 | AK115: 30 | AL115: 31
B116: =Categorias!B114 -> Cine/teatro | C116: 0 | D116: =SUM(Octubre!$H116:$AL116) -> 0 | E116: =C116-D116 -> 0
B117: =Categorias!B115 -> Gimnasio/piscina | C117: 0 | D117: =SUM(Octubre!$H117:$AL117) -> 0 | E117: =C117-D117 -> 0
...

Sheet Noviembre
B2: Presupuesto | C2: 44501
C4: Para crear un presupuesto: - A principios de este mes, rellene los campos en amarillo, despues de forma regular registre los gastos de cada dia en la tabla a la derecha - Todos los otros datos se convertirá automáticamente
C5: Fuente: | D5: =HYPERLINK("http://www.aprendizfinanciero.com/","http://www.aprendizfinanciero.com") -> http://www.aprendizfinanciero.com
B6: Ingresos
B8: Categoría | C8: Ingresos previstos | D8: Ingresos reales | E8: Diferencia | F8: Notas
B9: SUMA | C9: =C11 -> 47000 | D9: =D11 -> 44000 | E9: =E11 -> -3000
B11: =Categorias!B11 -> INGRESOS TOTALES | C11: =SUM(C12:C20) -> 47000 | D11: =SUM(D12:D20) -> 44000 | E11: =SUM(E12:E20) -> -3000 | H11: 1 | I11: 2 | J11: 3 | K11: 4 | L11: 5 | M11: 6 | N11: 7 | O11: 8 | P11: 9 | Q11: 10 | R11: 11 | S11: 12 | T11: 13 | U11: 14 | V11: 15 | W11: 16 | X11: 17 | Y11: 18 | Z11: 19 | AA11: 20 | AB11: 21 | AC11: 22 | AD11: 23 | AE11: 24 | AF11: 25 | AG11: 26 | AH11: 27 | AI11: 28 | AJ11: 29 | AK11: 30 | AL11: 31
B12: =Categorias!B12 -> Nomina | C12: 44000 | D12: =SUM(Noviembre!$H12:$AL12) -> 44000 | E12: =D12-C12 -> 0 | V12: 22000 | AJ12: 22000
B13: =Categorias!B13 -> Aguinaldo | C13: 0 | D13: =SUM(Noviembre!$H13:$AL13) -> 0 | E13: =D13-C13 -> 0
B14: =Categorias!B14 -> Fondo de ahorro | C14: 0 | D14: =SUM(Noviembre!$H14:$AL14) -> 0 | E14: =D14-C14 -> 0
B15: =Categorias!B15 -> Vales despensa | C15: 3000 | D15: =SUM(Noviembre!$H15:$AL15) -> 0 | E15: =D15-C15 -> -3000
B16: =Categorias!B16 -> Vales comedor | C16: 0 | D16: =SUM(Noviembre!$H16:$AL16) -> 0 | E16: =D16-C16 -> 0
B17: =Categorias!B17 -> - | C17: 0 | D17: =SUM(Noviembre!$H17:$AL17) -> 0 | E17: =D17-C17 -> 0
B18: =Categorias!B18 -> - | C18: 0 | D18: =SUM(Noviembre!$H18:$AL18) -> 0 | E18: =D18-C18 -> 0
B19: =Categorias!B19 -> - | C19: 0 | D19: =SUM(Noviembre!$H19:$AL19) -> 0 | E19: =D19-C19 -> 0
B20: =Categorias!B20 -> - | C20: 0 | D20: =SUM(Noviembre!$H20:$AL20) -> 0 | E20: =D20-C20 -> 0
B23: Gastos | H23: Registre de gastos diarios
B25: Categoría | C25: Gastos previstos | D25: Gastos reales | E25: Diferencia | F25: Notas | H25: Los campos siguientes son para un registro diario de gastos en cada categoría.
B26: SUMA | C26: =C28+C37+C45+C58+C68+C77+C88+C97+C107+C115+C126+C136+C146+C158 -> 24190 | D26: =D28+D37+D45+D58+D68+D77+D88+D97+D107+D115+D126+D136+D146+D158 -> 32167.34 | E26: =E28+E37+E45+E58+E68+E77+E88+E97+E107+E115+E126+E136+E146+E158 -> -7977.34 | H26: Si quieres incluir mas gastos en una celda, por el mismo dia, ingresa "=" y sigue la ecuación, por ejemplo:. = 25 + 20.5
B28: =Categorias!B24 -> ALIMENTOS Y BEBIDAS | C28: =SUM(C29:C35) -> 3000 | D28: =SUM(D29:D35) -> 5275 | E28: =SUM(E29:E35) -> -2275 | H28: 1 | I28: 2 | J28: 3 | K28: 4 | L28: 5 | M28: 6 | N28: 7 | O28: 8 | P28: 9 | Q28: 10 | R28: 11 | S28: 12 | T28: 13 | U28: 14 | V28: 15 | W28: 16 | X28: 17 | Y28: 18 | Z28: 19 | AA28: 20 | AB28: 21 | AC28: 22 | AD28: 23 | AE28: 24 | AF28: 25 | AG28: 26 | AH28: 27 | AI28: 28 | AJ28: 29 | AK28: 30 | AL28: 31
B29: =Categorias!B25 -> Restaurantes | C29: 3000 | D29: =SUM(Noviembre!$H29:$AL29) -> 1951 | E29: =C29-D29 -> 1049 | O29: 300 | P29: 200 | Q29: 220 | R29: 581 | V29: 33 | AB29: 177 | AD29: 190 | AF29: 250
B30: =Categorias!B26 -> Comida Carlos | C30: 0 | D30: =SUM(Noviembre!$H30:$AL30) -> 940 | E30: =C30-D30 -> -940 | H30: 540 | Q30: 80 | S30: 30 | AC30: 60 | AJ30: =160+70 -> 230
B31: =Categorias!B27 -> - | C31: 0 | D31: =SUM(Noviembre!$H31:$AL31) -> 446 | E31: =C31-D31 -> -446 | I31: 250 | L31: 25 | N31: 86 | Z31: 24 | AF31: 35 | AG31: 26
B32: =Categorias!B28 -> - | C32: 0 | D32: =SUM(Noviembre!$H32:$AL32) -> 1571 | E32: =C32-D32 -> -1571 | P32: 80 | Q32: 585 | S32: 40 | V32: 200 | AA32: 36 | AB32: 50 | AC32: 380 | AJ32: 200
B33: =Categorias!B29 -> - | C33: 0 | D33: =SUM(Noviembre!$H33:$AL33) -> 367 | E33: =C33-D33 -> -367 | H33: 200 | K33: 41 | O33: 90 | AG33: 36
B34: =Categorias!B30 -> - | C34: 0 | D34: =SUM(Noviembre!$H34:$AL34) -> 0 | E34: =C34-D34 -> 0
B35: =Categorias!B31 -> - | C35: 0 | D35: =SUM(Noviembre!$H35:$AL35) -> 0 | E35: =C35-D35 -> 0
B37: =Categorias!B33 -> SALUD | C37: =SUM(C38:C43) -> 1200 | D37: =SUM(D38:D43) -> 1042 | E37: =SUM(E38:E43) -> 158 | H37: 1 | I37: 2 | J37: 3 | K37: 4 | L37: 5 | M37: 6 | N37: 7 | O37: 8 | P37: 9 | Q37: 10 | R37: 11 | S37: 12 | T37: 13 | U37: 14 | V37: 15 | W37: 16 | X37: 17 | Y37: 18 | Z37: 19 | AA37: 20 | AB37: 21 | AC37: 22 | AD37: 23 | AE37: 24 | AF37: 25 | AG37: 26 | AH37: 27 | AI37: 28 | AJ37: 29 | AK37: 30 | AL37: 31
B38: =Categorias!B34 -> Gastos en médicos | C38: 0 | D38: =SUM(Noviembre!$H38:$AL38) -> 0 | E38: =C38-D38 -> 0
B39: =Categorias!B35 -> Medicamentos | C39: 0 | D39: =SUM(Noviembre!$H39:$AL39) -> 1042 | E39: =C39-D39 -> -1042 | H39: 123 | J39: 243 | P39: 476 | AJ39: 200
B40: =Categorias!B36 -> Dentista Kary | C40: 600 | D40: =SUM(Noviembre!$H40:$AL40) -> 0 | E40: =C40-D40 -> 600
B41: =Categorias!B37 -> Dentista Thiago | C41: 600 | D41: =SUM(Noviembre!$H41:$AL41) -> 0 | E41: =C41-D41 -> 600
B42: =Categorias!B38 -> - | C42: 0 | D42: =SUM(Noviembre!$H42:$AL42) -> 0 | E42: =C42-D42 -> 0
B43: =Categorias!B39 -> - | C43: 0 | D43: =SUM(Noviembre!$H43:$AL43) -> 0 | E43: =C43-D43 -> 0
B45: =Categorias!B41 -> CASA | C45: =SUM(C46:C56) -> 7300 | D45: =SUM(D46:D56) -> 10752 | E45: =SUM(E46:E56) -> -3452 | H45: 1 | I45: 2 | J45: 3 | K45: 4 | L45: 5 | M45: 6 | N45: 7 | O45: 8 | P45: 9 | Q45: 10 | R45: 11 | S45: 12 | T45: 13 | U45: 14 | V45: 15 | W45: 16 | X45: 17 | Y45: 18 | Z45: 19 | AA45: 20 | AB45: 21 | AC45: 22 | AD45: 23 | AE45: 24 | AF45: 25 | AG45: 26 | AH45: 27 | AI45: 28 | AJ45: 29 | AK45: 30 | AL45: 31
B46: =Categorias!B42 -> Reparación | C46: 0 | D46: =SUM(Noviembre!$H46:$AL46) -> 0 | E46: =C46-D46 -> 0
B47: =Categorias!B43 -> Electricidad | C47: 0 | D47: =SUM(Noviembre!$H47:$AL47) -> 2600 | E47: =C47-D47 -> -2600 | P47: 2600
B48: =Categorias!B44 -> Gas | C48: 300 | D48: =SUM(Noviembre!$H48:$AL48) -> 200 | E48: =C48-D48 -> 100 | AJ48: 200
B49: =Categorias!B45 -> Casa Claudia | C49: 0 | D49: =SUM(Noviembre!$H49:$AL49) -> 0 | E49: =C49-D49 -> 0
B50: =Categorias!B46 -> Muebles/electrodomésticos | C50: 0 | D50: =SUM(Noviembre!$H50:$AL50) -> 5102 | E50: =C50-D50 -> -5102 | H50: 5102
B51: =Categorias!B47 -> Predial | C51: 5000 | D51: =SUM(Noviembre!$H51:$AL51) -> 450 | E51: =C51-D51 -> 4550 | K51: 50 | Q51: 50 | X51: 350
B52: =Categorias!B48 -> Renta Cuarto | C52: 2000 | D52: =SUM(Noviembre!$H52:$AL52) -> 2400 | E52: =C52-D52 -> -400 | K52: 400 | Q52: 400 | W52: 800 | AJ52: 800
B53: =Categorias!B49 -> - | C53: 0 | D53: =SUM(Noviembre!$H53:$AL53) -> 0 | E53: =C53-D53 -> 0
B54: =Categorias!B50 -> - | C54: 0 | D54: =SUM(Noviembre!$H54:$AL54) -> 0 | E54: =C54-D54 -> 0
B55: =Categorias!B51 -> - | C55: 0 | D55: =SUM(Noviembre!$H55:$AL55) -> 0 | E55: =C55-D55 -> 0
B56: =Categorias!B52 -> - | C56: 0 | D56: =SUM(Noviembre!$H56:$AL56) -> 0 | E56: =C56-D56 -> 0
B58: =Categorias!B54 -> ROPA Y CALZADO | C58: =SUM(C59:C66) -> 0 | D58: =SUM(D59:D66) -> 0 | E58: =SUM(E59:E66) -> 0 | H58: 1 | I58: 2 | J58: 3 | K58: 4 | L58: 5 | M58: 6 | N58: 7 | O58: 8 | P58: 9 | Q58: 10 | R58: 11 | S58: 12 | T58: 13 | U58: 14 | V58: 15 | W58: 16 | X58: 17 | Y58: 18 | Z58: 19 | AA58: 20 | AB58: 21 | AC58: 22 | AD58: 23 | AE58: 24 | AF58: 25 | AG58: 26 | AH58: 27 | AI58: 28 | AJ58: 29 | AK58: 30 | AL58: 31
B59: =Categorias!B55 -> Ropa de adultos | C59: 0 | D59: =SUM(Noviembre!$H59:$AL59) -> 0 | E59: =C59-D59 -> 0
B60: =Categorias!B56 -> Ropa de niños | C60: 0 | D60: =SUM(Noviembre!$H60:$AL60) -> 0 | E60: =C60-D60 -> 0
B61: =Categorias!B57 -> Calzado | C61: 0 | D61: =SUM(Noviembre!$H61:$AL61) -> 0 | E61: =C61-D61 -> 0
B62: =Categorias!B58 -> Acessorios | C62: 0 | D62: =SUM(Noviembre!$H62:$AL62) -> 0 | E62: =C62-D62 -> 0
B63: =Categorias!B59 -> Joyería | C63: 0 | D63: =SUM(Noviembre!$H63:$AL63) -> 0 | E63: =C63-D63 -> 0
B64: =Categorias!B60 -> Otros | C64: 0 | D64: =SUM(Noviembre!$H64:$AL64) -> 0 | E64: =C64-D64 -> 0
B65: =Categorias!B61 -> - | C65: 0 | D65: =SUM(Noviembre!$H65:$AL65) -> 0 | E65: =C65-D65 -> 0
B66: =Categorias!B62 -> - | C66: 0 | D66: =SUM(Noviembre!$H66:$AL66) -> 0 | E66: =C66-D66 -> 0
B68: =Categorias!B64 -> COMUNICACIÓN | C68: =SUM(C69:C75) -> 750 | D68: =SUM(D69:D75) -> 280 | E68: =SUM(E69:E75) -> 470 | H68: 1 | I68: 2 | J68: 3 | K68: 4 | L68: 5 | M68: 6 | N68: 7 | O68: 8 | P68: 9 | Q68: 10 | R68: 11 | S68: 12 | T68: 13 | U68: 14 | V68: 15 | W68: 16 | X68: 17 | Y68: 18 | Z68: 19 | AA68: 20 | AB68: 21 | AC68: 22 | AD68: 23 | AE68: 24 | AF68: 25 | AG68: 26 | AH68: 27 | AI68: 28 | AJ68: 29 | AK68: 30 | AL68: 31
B69: =Categorias!B65 -> Cel. Claudia | C69: 300 | D69: =SUM(Noviembre!$H69:$AL69) -> 0 | E69: =C69-D69 -> 300
B70: =Categorias!B66 -> Cel. Carlos | C70: 250 | D70: =SUM(Noviembre!$H70:$AL70) -> 0 | E70: =C70-D70 -> 250
B71: =Categorias!B67 -> Cel.Kary | C71: 200 | D71: =SUM(Noviembre!$H71:$AL71) -> 280 | E71: =C71-D71 -> -80 | Q71: 280
B72: =Categorias!B68 -> - | C72: 0 | D72: =SUM(Noviembre!$H72:$AL72) -> 0 | E72: =C72-D72 -> 0
B73: =Categorias!B69 -> - | C73: 0 | D73: =SUM(Noviembre!$H73:$AL73) -> 0 | E73: =C73-D73 -> 0
B74: =Categorias!B70 -> - | C74: 0 | D74: =SUM(Noviembre!$H74:$AL74) -> 0 | E74: =C74-D74 -> 0
B75: =Categorias!B73 -> - | C75: 0 | D75: =SUM(Noviembre!$H75:$AL75) -> 0 | E75: =C75-D75 -> 0
B77: =Categorias!B75 -> TRANSPORTE | C77: =SUM(C78:C86) -> 3500 | D77: =SUM(D78:D86) -> 7767.34 | E77: =SUM(E78:E86) -> -4267.34 | H77: 1 | I77: 2 | J77: 3 | K77: 4 | L77: 5 | M77: 6 | N77: 7 | O77: 8 | P77: 9 | Q77: 10 | R77: 11 | S77: 12 | T77: 13 | U77: 14 | V77: 15 | W77: 16 | X77: 17 | Y77: 18 | Z77: 19 | AA77: 20 | AB77: 21 | AC77: 22 | AD77: 23 | AE77: 24 | AF77: 25 | AG77: 26 | AH77: 27 | AI77: 28 | AJ77: 29 | AK77: 30 | AL77: 31
B78: =Categorias!B76 -> Combustible Fusion | C78: 2000 | D78: =SUM(Noviembre!$H78:$AL78) -> 3997.34 | E78: =C78-D78 -> -1997.34 | H78: =1010+757.34 -> 1767.34 | Q78: 600 | R78: 810 | Z78: 820
B79: =Categorias!B77 -> Seguro Fusion | C79: 0 | D79: =SUM(Noviembre!$H79:$AL79) -> 0 | E79: =C79-D79 -> 0
B80: =Categorias!B78 -> Mantenimiento Fusion | C80: 1500 | D80: =SUM(Noviembre!$H80:$AL80) -> 1259 | E80: =C80-D80 -> 241 | I80: 159 | R80: 1100
B81: =Categorias!B79 -> Derecho vehicular Fusion | C81: 0 | D81: =SUM(Noviembre!$H81:$AL81) -> 0 | E81: =C81-D81 -> 0
B82: =Categorias!B80 -> Casetas | C82: 0 | D82: =SUM(Noviembre!$H82:$AL82) -> 1006 | E82: =C82-D82 -> -1006 | K82: 117 | O82: 188 | R82: 130 | V82: 200 | Z82: 117 | AC82: 117 | AF82: 120 | AJ82: 17
B83: =Categorias!B81 -> ADO | C83: 0 | D83: =SUM(Noviembre!$H83:$AL83) -> 1465 | E83: =C83-D83 -> -1465 | X83: 465 | AC83: 500 | AF83: 500
B84: =Categorias!B82 -> - | C84: 0 | D84: =SUM(Noviembre!$H84:$AL84) -> 0 | E84: =C84-D84 -> 0
B85: =Categorias!B83 -> - | C85: 0 | D85: =SUM(Noviembre!$H85:$AL85) -> 0 | E85: =C85-D85 -> 0
B86: =Categorias!B84 -> - | C86: 0 | D86: =SUM(Noviembre!$H86:$AL86) -> 40 | E86: =C86-D86 -> -40 | N86: 40
B88: =Categorias!B86 -> HIGIENE | C88: =SUM(C89:C95) -> 140 | D88: =SUM(D89:D95) -> 425 | E88: =SUM(E89:E95) -> -285 | H88: 1 | I88: 2 | J88: 3 | K88: 4 | L88: 5 | M88: 6 | N88: 7 | O88: 8 | P88: 9 | Q88: 10 | R88: 11 | S88: 12 | T88: 13 | U88: 14 | V88: 15 | W88: 16 | X88: 17 | Y88: 18 | Z88: 19 | AA88: 20 | AB88: 21 | AC88: 22 | AD88: 23 | AE88: 24 | AF88: 25 | AG88: 26 | AH88: 27 | AI88: 28 | AJ88: 29 | AK88: 30 | AL88: 31
B89: =Categorias!B87 -> Cosmeticos | C89: 0 | D89: =SUM(Noviembre!$H89:$AL89) -> 0 | E89: =C89-D89 -> 0
B90: =Categorias!B88 -> Peluquería / S. Belleza | C90: 140 | D90: =SUM(Noviembre!$H90:$AL90) -> 160 | E90: =C90-D90 -> -20 | H90: 160
B91: =Categorias!B89 -> Lavanderia | C91: 0 | D91: =SUM(Noviembre!$H91:$AL91) -> 0 | E91: =C91-D91 -> 0
B92: =Categorias!B90 -> Productos de limpieza | C92: 0 | D92: =SUM(Noviembre!$H92:$AL92) -> 265 | E92: =C92-D92 -> -265 | H92: 145 | U92: 120
B93: =Categorias!B91 -> Otros | C93: 0 | D93: =SUM(Noviembre!$H93:$AL93) -> 0 | E93: =C93-D93 -> 0
B94: =Categorias!B92 -> - | C94: 0 | D94: =SUM(Noviembre!$H94:$AL94) -> 0 | E94: =C94-D94 -> 0
B95: =Categorias!B93 -> - | C95: 0 | D95: =SUM(Noviembre!$H95:$AL95) -> 0 | E95: =C95-D95 -> 0
B97: =Categorias!B95 -> NIÑOS | C97: =SUM(C98:C105) -> 0 | D97: =SUM(D98:D105) -> 3600 | E97: =SUM(E98:E105) -> -3600 | H97: 1 | I97: 2 | J97: 3 | K97: 4 | L97: 5 | M97: 6 | N97: 7 | O97: 8 | P97: 9 | Q97: 10 | R97: 11 | S97: 12 | T97: 13 | U97: 14 | V97: 15 | W97: 16 | X97: 17 | Y97: 18 | Z97: 19 | AA97: 20 | AB97: 21 | AC97: 22 | AD97: 23 | AE97: 24 | AF97: 25 | AG97: 26 | AH97: 27 | AI97: 28 | AJ97: 29 | AK97: 30 | AL97: 31
B98: =Categorias!B96 -> Jugetes/juegos | C98: 0 | D98: =SUM(Noviembre!$H98:$AL98) -> 0 | E98: =C98-D98 -> 0
B99: =Categorias!B97 -> - | C99: 0 | D99: =SUM(Noviembre!$H99:$AL99) -> 0 | E99: =C99-D99 -> 0
B100: =Categorias!B98 -> - | C100: 0 | D100: =SUM(Noviembre!$H100:$AL100) -> 0 | E100: =C100-D100 -> 0
B101: =Categorias!B99 -> - | C101: 0 | D101: =SUM(Noviembre!$H101:$AL101) -> 3600 | E101: =C101-D101 -> -3600 | T101: 3600
B102: =Categorias!B100 -> - | C102: 0 | D102: =SUM(Noviembre!$H102:$AL102) -> 0 | E102: =C102-D102 -> 0
B103: =Categorias!B101 -> - | C103: 0 | D103: =SUM(Noviembre!$H103:$AL103) -> 0 | E103: =C103-D103 -> 0
B104: =Categorias!B102 -> - | C104: 0 | D104: =SUM(Noviembre!$H104:$AL104) -> 0 | E104: =C104-D104 -> 0
B105: =Categorias!B103 -> - | C105: 0 | D105: =SUM(Noviembre!$H105:$AL105) -> 0 | E105: =C105-D105 -> 0
B107: =Categorias!B105 -> DESARROLLO PERSONAL | C107: =SUM(C108:C113) -> 0 | D107: =SUM(D108:D113) -> 400 | E107: =SUM(E108:E113) -> -400
B108: =Categorias!B106 -> Libros | C108: 0 | D108: =SUM(Noviembre!$H115:$AL115) -> 0 | E108: =C108-D108 -> 0
B109: =Categorias!B107 -> Platzi | C109: 0 | D109: =SUM(Noviembre!$H116:$AL116) -> 0 | E109: =C109-D109 -> 0
B110: =Categorias!B108 -> Papeleria | C110: 0 | D110: =SUM(Noviembre!$H117:$AL117) -> 0 | E110: =C110-D110 -> 0
B111: =Categorias!B109 -> Inglés Thiago | C111: 0 | D111: =SUM(Noviembre!$H118:$AL118) -> 0 | E111: =C111-D111 -> 0 | V111: 1400
B112: =Categorias!B110 -> Arte Thiago | C112: 0 | D112: =SUM(Noviembre!$H119:$AL119) -> 400 | E112: =C112-D112 -> -400
B113: =Categorias!B111 -> Escuela kary | C113: 0 | D113: =SUM(Noviembre!$H120:$AL120) -> 0 | E113: =C113-D113 -> 0 | AB113: 410
H114: 1 | I114: 2 | J114: 3 | K114: 4 | L114: 5 | M114: 6 | N114: 7 | O114: 8 | P114: 9 | Q114: 10 | R114: 11 | S114: 12 | T114: 13 | U114: 14 | V114: 15 | W114: 16 | X114: 17 | Y114: 18 | Z114: 19 | AA114: 20 | AB114: 21 | AC114: 22 | AD114: 23 | AE114: 24 | AF114: 25 | AG114: 26 | AH114: 27 | AI114: 28 | AJ114: 29 | AK114: 30 | AL114: 31
B115: =Categorias!B113 -> DIVERSIÓN | C115: =SUM(C116:C124) -> 1300 | D115: =SUM(D116:D124) -> 582 | E115: =SUM(E116:E124) -> 718
B116: =Categorias!B114 -> Cine/teatro | C116: 0 | D116: =SUM(Noviembre!$H123:$AL123) -> 382 | E116: =C116-D116 -> -382
...

Sheet Diciembre
B2: Presupuesto | C2: 44531
C4: Para crear un presupuesto: - A principios de este mes, rellene los campos en amarillo, despues de forma regular registre los gastos de cada dia en la tabla a la derecha - Todos los otros datos se convertirá automáticamente
C5: Fuente: | D5: =HYPERLINK("http://www.aprendizfinanciero.com/","http://www.aprendizfinanciero.com") -> http://www.aprendizfinanciero.com
B6: Ingresos
B8: Categoría | C8: Ingresos previstos | D8: Ingresos reales | E8: Diferencia | F8: Notas
B9: SUMA | C9: =C11 -> 50000 | D9: =D11 -> 25000 | E9: =E11 -> -25000
B11: =Categorias!B11 -> INGRESOS TOTALES | C11: =SUM(C12:C20) -> 50000 | D11: =SUM(D12:D20) -> 25000 | E11: =SUM(E12:E20) -> -25000 | H11: 1 | I11: 2 | J11: 3 | K11: 4 | L11: 5 | M11: 6 | N11: 7 | O11: 8 | P11: 9 | Q11: 10 | R11: 11 | S11: 12 | T11: 13 | U11: 14 | V11: 15 | W11: 16 | X11: 17 | Y11: 18 | Z11: 19 | AA11: 20 | AB11: 21 | AC11: 22 | AD11: 23 | AE11: 24 | AF11: 25 | AG11: 26 | AH11: 27 | AI11: 28 | AJ11: 29 | AK11: 30 | AL11: 31
B12: =Categorias!B12 -> Nomina | C12: 42000 | D12: =SUM(Diciembre!$H12:$AL12) -> 22000 | E12: =D12-C12 -> -20000 | H12: 22000
B13: =Categorias!B13 -> Aguinaldo | C13: 5000 | D13: =SUM(Diciembre!$H13:$AL13) -> 0 | E13: =D13-C13 -> -5000
B14: =Categorias!B14 -> Fondo de ahorro | C14: 0 | D14: =SUM(Diciembre!$H14:$AL14) -> 0 | E14: =D14-C14 -> 0
B15: =Categorias!B15 -> Vales despensa | C15: 3000 | D15: =SUM(Diciembre!$H15:$AL15) -> 3000 | E15: =D15-C15 -> 0 | H15: 3000
B16: =Categorias!B16 -> Vales comedor | C16: 0 | D16: =SUM(Diciembre!$H16:$AL16) -> 0 | E16: =D16-C16 -> 0
B17: =Categorias!B17 -> - | C17: 0 | D17: =SUM(Diciembre!$H17:$AL17) -> 0 | E17: =D17-C17 -> 0
B18: =Categorias!B18 -> - | C18: 0 | D18: =SUM(Diciembre!$H18:$AL18) -> 0 | E18: =D18-C18 -> 0
B19: =Categorias!B19 -> - | C19: 0 | D19: =SUM(Diciembre!$H19:$AL19) -> 0 | E19: =D19-C19 -> 0
B20: =Categorias!B20 -> - | C20: 0 | D20: =SUM(Diciembre!$H20:$AL20) -> 0 | E20: =D20-C20 -> 0
B23: Gastos | H23: Registre de gastos diarios
B25: Categoría | C25: Gastos previstos | D25: Gastos reales | E25: Diferencia | F25: Notas | H25: Los campos siguientes son para un registro diario de gastos en cada categoría.
B26: SUMA | C26: =C28+C37+C45+C58+C68+C77+C88+C97+C107+C115+C126+C136+C146+C158 -> 24190 | D26: =D28+D37+D45+D58+D68+D77+D88+D97+D107+D115+D126+D136+D146+D158 -> 16816 | E26: =E28+E37+E45+E58+E68+E77+E88+E97+E107+E115+E126+E136+E146+E158 -> 7374 | H26: Si quieres incluir mas gastos en una celda, por el mismo dia, ingresa "=" y sigue la ecuación, por ejemplo:. = 25 + 20.5
B28: =Categorias!B24 -> ALIMENTOS Y BEBIDAS | C28: =SUM(C29:C35) -> 3000 | D28: =SUM(D29:D35) -> 4035 | E28: =SUM(E29:E35) -> -1035 | H28: 1 | I28: 2 | J28: 3 | K28: 4 | L28: 5 | M28: 6 | N28: 7 | O28: 8 | P28: 9 | Q28: 10 | R28: 11 | S28: 12 | T28: 13 | U28: 14 | V28: 15 | W28: 16 | X28: 17 | Y28: 18 | Z28: 19 | AA28: 20 | AB28: 21 | AC28: 22 | AD28: 23 | AE28: 24 | AF28: 25 | AG28: 26 | AH28: 27 | AI28: 28 | AJ28: 29 | AK28: 30 | AL28: 31
B29: =Categorias!B25 -> Restaurantes | C29: 3000 | D29: =SUM(Diciembre!$H29:$AL29) -> 3470 | E29: =C29-D29 -> -470 | J29: 350 | M29: 350 | O29: 2100 | Q29: 280 | S29: 390
B30: =Categorias!B26 -> Comida Carlos | C30: 0 | D30: =SUM(Diciembre!$H30:$AL30) -> 175 | E30: =C30-D30 -> -175 | M30: 65 | S30: 110
B31: =Categorias!B27 -> - | C31: 0 | D31: =SUM(Diciembre!$H31:$AL31) -> 30 | E31: =C31-D31 -> -30 | J31: 30
B32: =Categorias!B28 -> - | C32: 0 | D32: =SUM(Diciembre!$H32:$AL32) -> 80 | E32: =C32-D32 -> -80 | L32: 80
B33: =Categorias!B29 -> - | C33: 0 | D33: =SUM(Diciembre!$H33:$AL33) -> 0 | E33: =C33-D33 -> 0
B34: =Categorias!B30 -> - | C34: 0 | D34: =SUM(Diciembre!$H34:$AL34) -> 280 | E34: =C34-D34 -> -280 | H34: 280
B35: =Categorias!B31 -> - | C35: 0 | D35: =SUM(Diciembre!$H35:$AL35) -> 0 | E35: =C35-D35 -> 0
B37: =Categorias!B33 -> SALUD | C37: =SUM(C38:C43) -> 1200 | D37: =SUM(D38:D43) -> 0 | E37: =SUM(E38:E43) -> 1200 | H37: 1 | I37: 2 | J37: 3 | K37: 4 | L37: 5 | M37: 6 | N37: 7 | O37: 8 | P37: 9 | Q37: 10 | R37: 11 | S37: 12 | T37: 13 | U37: 14 | V37: 15 | W37: 16 | X37: 17 | Y37: 18 | Z37: 19 | AA37: 20 | AB37: 21 | AC37: 22 | AD37: 23 | AE37: 24 | AF37: 25 | AG37: 26 | AH37: 27 | AI37: 28 | AJ37: 29 | AK37: 30 | AL37: 31
B38: =Categorias!B34 -> Gastos en médicos | C38: 0 | D38: =SUM(Diciembre!$H38:$AL38) -> 0 | E38: =C38-D38 -> 0
B39: =Categorias!B35 -> Medicamentos | C39: 0 | D39: =SUM(Diciembre!$H39:$AL39) -> 0 | E39: =C39-D39 -> 0
B40: =Categorias!B36 -> Dentista Kary | C40: 600 | D40: =SUM(Diciembre!$H40:$AL40) -> 0 | E40: =C40-D40 -> 600
B41: =Categorias!B37 -> Dentista Thiago | C41: 600 | D41: =SUM(Diciembre!$H41:$AL41) -> 0 | E41: =C41-D41 -> 600
B42: =Categorias!B38 -> - | C42: 0 | D42: =SUM(Diciembre!$H42:$AL42) -> 0 | E42: =C42-D42 -> 0
B43: =Categorias!B39 -> - | C43: 0 | D43: =SUM(Diciembre!$H43:$AL43) -> 0 | E43: =C43-D43 -> 0
B45: =Categorias!B41 -> CASA | C45: =SUM(C46:C56) -> 7300 | D45: =SUM(D46:D56) -> 1500 | E45: =SUM(E46:E56) -> 5800 | H45: 1 | I45: 2 | J45: 3 | K45: 4 | L45: 5 | M45: 6 | N45: 7 | O45: 8 | P45: 9 | Q45: 10 | R45: 11 | S45: 12 | T45: 13 | U45: 14 | V45: 15 | W45: 16 | X45: 17 | Y45: 18 | Z45: 19 | AA45: 20 | AB45: 21 | AC45: 22 | AD45: 23 | AE45: 24 | AF45: 25 | AG45: 26 | AH45: 27 | AI45: 28 | AJ45: 29 | AK45: 30 | AL45: 31
B46: =Categorias!B42 -> Reparación | C46: 0 | D46: =SUM(Diciembre!$H46:$AL46) -> 0 | E46: =C46-D46 -> 0
B47: =Categorias!B43 -> Electricidad | C47: 0 | D47: =SUM(Diciembre!$H47:$AL47) -> 0 | E47: =C47-D47 -> 0
B48: =Categorias!B44 -> Gas | C48: 300 | D48: =SUM(Diciembre!$H48:$AL48) -> 0 | E48: =C48-D48 -> 300
B49: =Categorias!B45 -> Casa Claudia | C49: 0 | D49: =SUM(Diciembre!$H49:$AL49) -> 0 | E49: =C49-D49 -> 0
B50: =Categorias!B46 -> Muebles/electrodomésticos | C50: 0 | D50: =SUM(Diciembre!$H50:$AL50) -> 0 | E50: =C50-D50 -> 0
B51: =Categorias!B47 -> Predial | C51: 5000 | D51: =SUM(Diciembre!$H51:$AL51) -> 700 | E51: =C51-D51 -> 4300 | H51: 700
